Workbook

Sheet Stand-Ohada
A2: IFRS BUSINESS PLAN | U2: OHADA BUSINESS PLAN
A5: Financials | B5: Full Year | H5: Growth % | N5: Adjustments | U5: Financials | V5: Full Year | AB5: Growth %
A6: LC (Million) | B6: Act'24 | C6: Act'25 | D6: Bud'26 | E6: 5+7 FC 2026 | F6: Bud'27 | G6: Bud'28 | H6: Act'25 vs Act'24 | I6: 5+7 FC 2026 vs Act'25 | J6: 5+7 FC 2026 vs Bud'26 | K6: Bud'27 vs 5+7 FC 2026 | L6: Bud'28 vs Bud'27 | N6: Act'24 | O6: Act'25 | P6: Bud'26 | Q6: 5+7 FC 2026 | R6: Bud'27 | S6: Bud'28 | U6: LC (Million) | V6: Act'24 | W6: Act'25 | X6: Bud'26 | Y6: 5+7 FC 2026 | Z6: Bud'27 | AA6: Bud'28 | AB6: Act'25 vs Act'24 | AC6: 5+7 FC 2026 vs Act'25 | AD6: 5+7 FC 2026 vs Bud'26 | AE6: Bud'27 vs 5+7 FC 2026 | AF6: Bud'28 vs Bud'27
A7: Total Revenue | B7: 283449 | C7: =299018+2123 -> 301141 | D7: 328333 | E7: 350332 | F7: 372353 | G7: 424428 | H7: =IFERROR(IF(C7/B7-1>=0,"▲","▼")&TEXT(ABS(C7/B7-1),"0,0%"),"NM") -> ▲6,2% | I7: =IFERROR(IF(E7/C7-1>=0,"▲","▼")&TEXT(ABS(E7/C7-1),"0,0%"),"NM") -> ▲16,3% | J7: =IFERROR(IF(E7/D7-1>=0,"▲","▼")&TEXT(ABS(E7/D7-1),"0,0%"),"NM") -> ▲6,7% | K7: =IFERROR(IF(F7/E7-1>=0,"▲","▼")&TEXT(ABS(F7/E7-1),"0,0%"),"NM") -> ▲6,3% | L7: =IFERROR(IF(G7/F7-1>=0,"▲","▼")&TEXT(ABS(G7/F7-1),"0,0%"),"NM") -> ▲14,0% | N7: =+Adjustments!C26 -> -2053.9153 | O7: =+Adjustments!D26 -> 238.81677 | P7: =+Adjustments!E26 -> 279.41563 | Q7: =+Adjustments!F26 -> 279.41563 | R7: =+Adjustments!G26 -> 298.6953 | S7: =+Adjustments!H26 -> 340.51265 | U7: Total Revenue | V7: =+B7+N7 -> 281395.08 | W7: =+C7+O7 -> 301379.82 | X7: =+D7+P7 -> 328612.42 | Y7: =+E7+Q7 -> 350611.42 | Z7: =+F7+R7 -> 372651.7 | AA7: =+G7+S7 -> 424768.51 | AB7: =IFERROR(IF(W7/V7-1>=0,"▲","▼")&TEXT(ABS(W7/V7-1),"0,0%"),"NM") -> ▲7,1% | AC7: =IFERROR(IF(Y7/W7-1>=0,"▲","▼")&TEXT(ABS(Y7/W7-1),"0,0%"),"NM") -> ▲16,3% | AD7: =IFERROR(IF(Y7/X7-1>=0,"▲","▼")&TEXT(ABS(Y7/X7-1),"0,0%"),"NM") -> ▲6,7% | AE7: =IFERROR(IF(Z7/Y7-1>=0,"▲","▼")&TEXT(ABS(Z7/Y7-1),"0,0%"),"NM") -> ▲6,3% | AF7: =IFERROR(IF(AA7/Z7-1>=0,"▲","▼")&TEXT(ABS(AA7/Z7-1),"0,0%"),"NM") -> ▲14,0%
A8: Service Revenue | B8: 282737 | C8: =298233+2123 -> 300356 | D8: 326160 | E8: 348916 | F8: 369475 | G8: 421483 | H8: =IFERROR(IF(C8/B8-1>=0,"▲","▼")&TEXT(ABS(C8/B8-1),"0,0%"),"NM") -> ▲6,2% | I8: =IFERROR(IF(E8/C8-1>=0,"▲","▼")&TEXT(ABS(E8/C8-1),"0,0%"),"NM") -> ▲16,2% | J8: =IFERROR(IF(E8/D8-1>=0,"▲","▼")&TEXT(ABS(E8/D8-1),"0,0%"),"NM") -> ▲7,0% | K8: =IFERROR(IF(F8/E8-1>=0,"▲","▼")&TEXT(ABS(F8/E8-1),"0,0%"),"NM") -> ▲5,9% | L8: =IFERROR(IF(G8/F8-1>=0,"▲","▼")&TEXT(ABS(G8/F8-1),"0,0%"),"NM") -> ▲14,1% | N8: -2053.9153 | O8: 238.81677 | P8: 279.41563 | Q8: 279.41563 | R8: 298.6953 | S8: 340.51265 | U8: Service Revenue | V8: =+B8+N8 -> 280683.08 | W8: =+C8+O8 -> 300594.82 | X8: =+D8+P8 -> 326439.42 | Y8: =+E8+Q8 -> 349195.42 | Z8: =+F8+R8 -> 369773.7 | AA8: =+G8+S8 -> 421823.51 | AB8: =IFERROR(IF(W8/V8-1>=0,"▲","▼")&TEXT(ABS(W8/V8-1),"0,0%"),"NM") -> ▲7,1% | AC8: =IFERROR(IF(Y8/W8-1>=0,"▲","▼")&TEXT(ABS(Y8/W8-1),"0,0%"),"NM") -> ▲16,2% | AD8: =IFERROR(IF(Y8/X8-1>=0,"▲","▼")&TEXT(ABS(Y8/X8-1),"0,0%"),"NM") -> ▲7,0% | AE8: =IFERROR(IF(Z8/Y8-1>=0,"▲","▼")&TEXT(ABS(Z8/Y8-1),"0,0%"),"NM") -> ▲5,9% | AF8: =IFERROR(IF(AA8/Z8-1>=0,"▲","▼")&TEXT(ABS(AA8/Z8-1),"0,0%"),"NM") -> ▲14,1%
A9: Total Voice Revenue | B9: 129748 | C9: =124243+2123 -> 126366 | D9: 120217 | E9: 120895 | F9: 115792 | G9: 111780 | H9: =IFERROR(IF(C9/B9-1>=0,"▲","▼")&TEXT(ABS(C9/B9-1),"0,0%"),"NM") -> ▼2,6% | I9: =IFERROR(IF(E9/C9-1>=0,"▲","▼")&TEXT(ABS(E9/C9-1),"0,0%"),"NM") -> ▼4,3% | J9: =IFERROR(IF(E9/D9-1>=0,"▲","▼")&TEXT(ABS(E9/D9-1),"0,0%"),"NM") -> ▲0,6% | K9: =IFERROR(IF(F9/E9-1>=0,"▲","▼")&TEXT(ABS(F9/E9-1),"0,0%"),"NM") -> ▼4,2% | L9: =IFERROR(IF(G9/F9-1>=0,"▲","▼")&TEXT(ABS(G9/F9-1),"0,0%"),"NM") -> ▼3,5% | N9: =+N7 -> -2053.9153 | O9: =+O7 -> 238.81677 | P9: =+P7 -> 279.41563 | Q9: =+Q7 -> 279.41563 | R9: =+R7 -> 298.6953 | S9: =+S7 -> 340.51265 | U9: Total Voice Revenue | V9: =+B9+N9 -> 127694.08 | W9: =+C9+O9 -> 126604.82 | X9: =+D9+P9 -> 120496.42 | Y9: =+E9+Q9 -> 121174.42 | Z9: =+F9+R9 -> 116090.7 | AA9: =+G9+S9 -> 112120.51 | AB9: =IFERROR(IF(W9/V9-1>=0,"▲","▼")&TEXT(ABS(W9/V9-1),"0,0%"),"NM") -> ▼0,9% | AC9: =IFERROR(IF(Y9/W9-1>=0,"▲","▼")&TEXT(ABS(Y9/W9-1),"0,0%"),"NM") -> ▼4,3% | AD9: =IFERROR(IF(Y9/X9-1>=0,"▲","▼")&TEXT(ABS(Y9/X9-1),"0,0%"),"NM") -> ▲0,6% | AE9: =IFERROR(IF(Z9/Y9-1>=0,"▲","▼")&TEXT(ABS(Z9/Y9-1),"0,0%"),"NM") -> ▼4,2% | AF9: =IFERROR(IF(AA9/Z9-1>=0,"▲","▼")&TEXT(ABS(AA9/Z9-1),"0,0%"),"NM") -> ▼3,4%
A10: Total Data Revenue | B10: 109803 | C10: 133662 | D10: 162282 | E10: 188118 | F10: 201230 | G10: 245526 | H10: =IFERROR(IF(C10/B10-1>=0,"▲","▼")&TEXT(ABS(C10/B10-1),"0,0%"),"NM") -> ▲21,7% | I10: =IFERROR(IF(E10/C10-1>=0,"▲","▼")&TEXT(ABS(E10/C10-1),"0,0%"),"NM") -> ▲40,7% | J10: =IFERROR(IF(E10/D10-1>=0,"▲","▼")&TEXT(ABS(E10/D10-1),"0,0%"),"NM") -> ▲15,9% | K10: =IFERROR(IF(F10/E10-1>=0,"▲","▼")&TEXT(ABS(F10/E10-1),"0,0%"),"NM") -> ▲7,0% | L10: =IFERROR(IF(G10/F10-1>=0,"▲","▼")&TEXT(ABS(G10/F10-1),"0,0%"),"NM") -> ▲22,0% | U10: Total Data Revenue | V10: 109803 | W10: 133662 | X10: 162282 | Y10: 188118 | Z10: 201230 | AA10: 245526 | AB10: =IFERROR(IF(W10/V10-1>=0,"▲","▼")&TEXT(ABS(W10/V10-1),"0,0%"),"NM") -> ▲21,7% | AC10: =IFERROR(IF(Y10/W10-1>=0,"▲","▼")&TEXT(ABS(Y10/W10-1),"0,0%"),"NM") -> ▲40,7% | AD10: =IFERROR(IF(Y10/X10-1>=0,"▲","▼")&TEXT(ABS(Y10/X10-1),"0,0%"),"NM") -> ▲15,9% | AE10: =IFERROR(IF(Z10/Y10-1>=0,"▲","▼")&TEXT(ABS(Z10/Y10-1),"0,0%"),"NM") -> ▲7,0% | AF10: =IFERROR(IF(AA10/Z10-1>=0,"▲","▼")&TEXT(ABS(AA10/Z10-1),"0,0%"),"NM") -> ▲22,0%
A11: Digital Revenue | B11: 8305 | C11: 5106 | D11: 6469 | E11: 3766 | F11: 7452 | G11: 8582 | H11: =IFERROR(IF(C11/B11-1>=0,"▲","▼")&TEXT(ABS(C11/B11-1),"0,0%"),"NM") -> ▼38,5% | I11: =IFERROR(IF(E11/C11-1>=0,"▲","▼")&TEXT(ABS(E11/C11-1),"0,0%"),"NM") -> ▼26,2% | J11: =IFERROR(IF(E11/D11-1>=0,"▲","▼")&TEXT(ABS(E11/D11-1),"0,0%"),"NM") -> ▼41,8% | K11: =IFERROR(IF(F11/E11-1>=0,"▲","▼")&TEXT(ABS(F11/E11-1),"0,0%"),"NM") -> ▲97,9% | L11: =IFERROR(IF(G11/F11-1>=0,"▲","▼")&TEXT(ABS(G11/F11-1),"0,0%"),"NM") -> ▲15,2% | U11: Digital Revenue | V11: 8305 | W11: 5106 | X11: 6469 | Y11: 3766 | Z11: 7452 | AA11: 8582 | AB11: =IFERROR(IF(W11/V11-1>=0,"▲","▼")&TEXT(ABS(W11/V11-1),"0,0%"),"NM") -> ▼38,5% | AC11: =IFERROR(IF(Y11/W11-1>=0,"▲","▼")&TEXT(ABS(Y11/W11-1),"0,0%"),"NM") -> ▼26,2% | AD11: =IFERROR(IF(Y11/X11-1>=0,"▲","▼")&TEXT(ABS(Y11/X11-1),"0,0%"),"NM") -> ▼41,8% | AE11: =IFERROR(IF(Z11/Y11-1>=0,"▲","▼")&TEXT(ABS(Z11/Y11-1),"0,0%"),"NM") -> ▲97,9% | AF11: =IFERROR(IF(AA11/Z11-1>=0,"▲","▼")&TEXT(ABS(AA11/Z11-1),"0,0%"),"NM") -> ▲15,2%
A12: SMS Revenue | B12: 3405 | C12: 3020 | D12: 2552 | E12: 2222 | F12: 2257 | G12: 1981 | H12: =IFERROR(IF(C12/B12-1>=0,"▲","▼")&TEXT(ABS(C12/B12-1),"0,0%"),"NM") -> ▼11,3% | I12: =IFERROR(IF(E12/C12-1>=0,"▲","▼")&TEXT(ABS(E12/C12-1),"0,0%"),"NM") -> ▼26,4% | J12: =IFERROR(IF(E12/D12-1>=0,"▲","▼")&TEXT(ABS(E12/D12-1),"0,0%"),"NM") -> ▼12,9% | K12: =IFERROR(IF(F12/E12-1>=0,"▲","▼")&TEXT(ABS(F12/E12-1),"0,0%"),"NM") -> ▲1,6% | L12: =IFERROR(IF(G12/F12-1>=0,"▲","▼")&TEXT(ABS(G12/F12-1),"0,0%"),"NM") -> ▼12,2% | U12: SMS Revenue | V12: 3405 | W12: 3020 | X12: 2552 | Y12: 2222 | Z12: 2257 | AA12: 1981 | AB12: =IFERROR(IF(W12/V12-1>=0,"▲","▼")&TEXT(ABS(W12/V12-1),"0,0%"),"NM") -> ▼11,3% | AC12: =IFERROR(IF(Y12/W12-1>=0,"▲","▼")&TEXT(ABS(Y12/W12-1),"0,0%"),"NM") -> ▼26,4% | AD12: =IFERROR(IF(Y12/X12-1>=0,"▲","▼")&TEXT(ABS(Y12/X12-1),"0,0%"),"NM") -> ▼12,9% | AE12: =IFERROR(IF(Z12/Y12-1>=0,"▲","▼")&TEXT(ABS(Z12/Y12-1),"0,0%"),"NM") -> ▲1,6% | AF12: =IFERROR(IF(AA12/Z12-1>=0,"▲","▼")&TEXT(ABS(AA12/Z12-1),"0,0%"),"NM") -> ▼12,2%
A13: Total Wholesale (excl. Interconnect) | B13: 7140 | C13: 8500 | D13: 6610 | E13: 7123 | F13: 7111 | G13: 7844 | H13: =IFERROR(IF(C13/B13-1>=0,"▲","▼")&TEXT(ABS(C13/B13-1),"0,0%"),"NM") -> ▲19,0% | I13: =IFERROR(IF(E13/C13-1>=0,"▲","▼")&TEXT(ABS(E13/C13-1),"0,0%"),"NM") -> ▼16,2% | J13: =IFERROR(IF(E13/D13-1>=0,"▲","▼")&TEXT(ABS(E13/D13-1),"0,0%"),"NM") -> ▲7,8% | K13: =IFERROR(IF(F13/E13-1>=0,"▲","▼")&TEXT(ABS(F13/E13-1),"0,0%"),"NM") -> ▼0,2% | L13: =IFERROR(IF(G13/F13-1>=0,"▲","▼")&TEXT(ABS(G13/F13-1),"0,0%"),"NM") -> ▲10,3% | U13: Total Wholesale (excl. Interconnect) | V13: 7140 | W13: 8500 | X13: 6610 | Y13: 7123 | Z13: 7111 | AA13: 7844 | AB13: =IFERROR(IF(W13/V13-1>=0,"▲","▼")&TEXT(ABS(W13/V13-1),"0,0%"),"NM") -> ▲19,0% | AC13: =IFERROR(IF(Y13/W13-1>=0,"▲","▼")&TEXT(ABS(Y13/W13-1),"0,0%"),"NM") -> ▼16,2% | AD13: =IFERROR(IF(Y13/X13-1>=0,"▲","▼")&TEXT(ABS(Y13/X13-1),"0,0%"),"NM") -> ▲7,8% | AE13: =IFERROR(IF(Z13/Y13-1>=0,"▲","▼")&TEXT(ABS(Z13/Y13-1),"0,0%"),"NM") -> ▼0,2% | AF13: =IFERROR(IF(AA13/Z13-1>=0,"▲","▼")&TEXT(ABS(AA13/Z13-1),"0,0%"),"NM") -> ▲10,3%
A14: ICT Revenue | B14: 22989 | C14: 23981 | D14: 28030 | E14: =26683+110 -> 26793 | F14: 35633 | G14: 45771 | H14: =IFERROR(IF(C14/B14-1>=0,"▲","▼")&TEXT(ABS(C14/B14-1),"0,0%"),"NM") -> ▲4,3% | I14: =IFERROR(IF(E14/C14-1>=0,"▲","▼")&TEXT(ABS(E14/C14-1),"0,0%"),"NM") -> ▲11,7% | J14: =IFERROR(IF(E14/D14-1>=0,"▲","▼")&TEXT(ABS(E14/D14-1),"0,0%"),"NM") -> ▼4,4% | K14: =IFERROR(IF(F14/E14-1>=0,"▲","▼")&TEXT(ABS(F14/E14-1),"0,0%"),"NM") -> ▲33,0% | L14: =IFERROR(IF(G14/F14-1>=0,"▲","▼")&TEXT(ABS(G14/F14-1),"0,0%"),"NM") -> ▲28,5% | U14: ICT Revenue | V14: 22989 | W14: 23981 | X14: 28030 | Y14: =26683+110 -> 26793 | Z14: 35633 | AA14: 45771 | AB14: =IFERROR(IF(W14/V14-1>=0,"▲","▼")&TEXT(ABS(W14/V14-1),"0,0%"),"NM") -> ▲4,3% | AC14: =IFERROR(IF(Y14/W14-1>=0,"▲","▼")&TEXT(ABS(Y14/W14-1),"0,0%"),"NM") -> ▲11,7% | AD14: =IFERROR(IF(Y14/X14-1>=0,"▲","▼")&TEXT(ABS(Y14/X14-1),"0,0%"),"NM") -> ▼4,4% | AE14: =IFERROR(IF(Z14/Y14-1>=0,"▲","▼")&TEXT(ABS(Z14/Y14-1),"0,0%"),"NM") -> ▲33,0% | AF14: =IFERROR(IF(AA14/Z14-1>=0,"▲","▼")&TEXT(ABS(AA14/Z14-1),"0,0%"),"NM") -> ▲28,5%
A15: Fixed Connectivity | B15: 14624 | C15: 16632 | D15: 17895 | E15: 17895 | F15: 22369 | G15: 28409 | H15: =IFERROR(IF(C15/B15-1>=0,"▲","▼")&TEXT(ABS(C15/B15-1),"0,0%"),"NM") -> ▲13,7% | I15: =IFERROR(IF(E15/C15-1>=0,"▲","▼")&TEXT(ABS(E15/C15-1),"0,0%"),"NM") -> ▲7,6% | J15: =IFERROR(IF(E15/D15-1>=0,"▲","▼")&TEXT(ABS(E15/D15-1),"0,0%"),"NM") -> ▲0,0% | K15: =IFERROR(IF(F15/E15-1>=0,"▲","▼")&TEXT(ABS(F15/E15-1),"0,0%"),"NM") -> ▲25,0% | L15: =IFERROR(IF(G15/F15-1>=0,"▲","▼")&TEXT(ABS(G15/F15-1),"0,0%"),"NM") -> ▲27,0% | U15: Fixed Connectivity | V15: 14624 | W15: 16632 | X15: 17895 | Y15: 17895 | Z15: 22369 | AA15: 28409 | AB15: =IFERROR(IF(W15/V15-1>=0,"▲","▼")&TEXT(ABS(W15/V15-1),"0,0%"),"NM") -> ▲13,7% | AC15: =IFERROR(IF(Y15/W15-1>=0,"▲","▼")&TEXT(ABS(Y15/W15-1),"0,0%"),"NM") -> ▲7,6% | AD15: =IFERROR(IF(Y15/X15-1>=0,"▲","▼")&TEXT(ABS(Y15/X15-1),"0,0%"),"NM") -> ▲0,0% | AE15: =IFERROR(IF(Z15/Y15-1>=0,"▲","▼")&TEXT(ABS(Z15/Y15-1),"0,0%"),"NM") -> ▲25,0% | AF15: =IFERROR(IF(AA15/Z15-1>=0,"▲","▼")&TEXT(ABS(AA15/Z15-1),"0,0%"),"NM") -> ▲27,0%
A16: Converged Service Revenue | B16: 6538 | C16: 7349 | D16: 10134 | E16: 8897 | F16: 13264 | G16: 17362 | H16: =IFERROR(IF(C16/B16-1>=0,"▲","▼")&TEXT(ABS(C16/B16-1),"0,0%"),"NM") -> ▲12,4% | I16: =IFERROR(IF(E16/C16-1>=0,"▲","▼")&TEXT(ABS(E16/C16-1),"0,0%"),"NM") -> ▲21,1% | J16: =IFERROR(IF(E16/D16-1>=0,"▲","▼")&TEXT(ABS(E16/D16-1),"0,0%"),"NM") -> ▼12,2% | K16: =IFERROR(IF(F16/E16-1>=0,"▲","▼")&TEXT(ABS(F16/E16-1),"0,0%"),"NM") -> ▲49,1% | L16: =IFERROR(IF(G16/F16-1>=0,"▲","▼")&TEXT(ABS(G16/F16-1),"0,0%"),"NM") -> ▲30,9% | U16: Converged Service Revenue | V16: 6538 | W16: 7349 | X16: 10134 | Y16: 8897 | Z16: 13264 | AA16: 17362 | AB16: =IFERROR(IF(W16/V16-1>=0,"▲","▼")&TEXT(ABS(W16/V16-1),"0,0%"),"NM") -> ▲12,4% | AC16: =IFERROR(IF(Y16/W16-1>=0,"▲","▼")&TEXT(ABS(Y16/W16-1),"0,0%"),"NM") -> ▲21,1% | AD16: =IFERROR(IF(Y16/X16-1>=0,"▲","▼")&TEXT(ABS(Y16/X16-1),"0,0%"),"NM") -> ▼12,2% | AE16: =IFERROR(IF(Z16/Y16-1>=0,"▲","▼")&TEXT(ABS(Z16/Y16-1),"0,0%"),"NM") -> ▲49,1% | AF16: =IFERROR(IF(AA16/Z16-1>=0,"▲","▼")&TEXT(ABS(AA16/Z16-1),"0,0%"),"NM") -> ▲30,9%
A17: Non-service revenue | B17: 711 | C17: 785 | D17: 2173 | E17: 1415 | F17: 2878 | G17: 2945 | H17: =IFERROR(IF(C17/B17-1>=0,"▲","▼")&TEXT(ABS(C17/B17-1),"0,0%"),"NM") -> ▲10,4% | I17: =IFERROR(IF(E17/C17-1>=0,"▲","▼")&TEXT(ABS(E17/C17-1),"0,0%"),"NM") -> ▲80,3% | J17: =IFERROR(IF(E17/D17-1>=0,"▲","▼")&TEXT(ABS(E17/D17-1),"0,0%"),"NM") -> ▼34,9% | K17: =IFERROR(IF(F17/E17-1>=0,"▲","▼")&TEXT(ABS(F17/E17-1),"0,0%"),"NM") -> ▲103,4% | L17: =IFERROR(IF(G17/F17-1>=0,"▲","▼")&TEXT(ABS(G17/F17-1),"0,0%"),"NM") -> ▲2,3% | U17: Non-service revenue | V17: 711 | W17: 785 | X17: 2173 | Y17: 1415 | Z17: 2878 | AA17: 2945 | AB17: =IFERROR(IF(W17/V17-1>=0,"▲","▼")&TEXT(ABS(W17/V17-1),"0,0%"),"NM") -> ▲10,4% | AC17: =IFERROR(IF(Y17/W17-1>=0,"▲","▼")&TEXT(ABS(Y17/W17-1),"0,0%"),"NM") -> ▲80,3% | AD17: =IFERROR(IF(Y17/X17-1>=0,"▲","▼")&TEXT(ABS(Y17/X17-1),"0,0%"),"NM") -> ▼34,9% | AE17: =IFERROR(IF(Z17/Y17-1>=0,"▲","▼")&TEXT(ABS(Z17/Y17-1),"0,0%"),"NM") -> ▲103,4% | AF17: =IFERROR(IF(AA17/Z17-1>=0,"▲","▼")&TEXT(ABS(AA17/Z17-1),"0,0%"),"NM") -> ▲2,3%
A18: Cost of Sales | B18: =81375+1279 -> 82654 | C18: =78312+3454 -> 81766 | D18: 84313 | E18: 89950 | F18: 93684 | G18: 103375 | H18: =IFERROR(IF(C18/B18-1>=0,"▲","▼")&TEXT(ABS(C18/B18-1),"0,0%"),"NM") -> ▼1,1% | I18: =IFERROR(IF(E18/C18-1>=0,"▲","▼")&TEXT(ABS(E18/C18-1),"0,0%"),"NM") -> ▲10,0% | J18: =IFERROR(IF(E18/D18-1>=0,"▲","▼")&TEXT(ABS(E18/D18-1),"0,0%"),"NM") -> ▲6,7% | K18: =IFERROR(IF(F18/E18-1>=0,"▲","▼")&TEXT(ABS(F18/E18-1),"0,0%"),"NM") -> ▲4,2% | L18: =IFERROR(IF(G18/F18-1>=0,"▲","▼")&TEXT(ABS(G18/F18-1),"0,0%"),"NM") -> ▲10,3% | N18: =+Adjustments!C27 -> 4145.9253 | O18: =+Adjustments!D27 -> 2161.8265 | P18: =+Adjustments!E27 -> 2161.8265 | Q18: =+Adjustments!F27 -> 2161.8265 | R18: =+Adjustments!G27 -> 2295.5803 | S18: =+Adjustments!H27 -> 2611.5365 | U18: Cost of Sales | V18: =B18-N18 -> 78508.075 | W18: =C18-O18 -> 79604.174 | X18: =D18-P18 -> 82151.174 | Y18: =E18-Q18 -> 87788.174 | Z18: =F18-R18 -> 91388.42 | AA18: =G18-S18 -> 100763.46 | AB18: =IFERROR(IF(W18/V18-1>=0,"▲","▼")&TEXT(ABS(W18/V18-1),"0,0%"),"NM") -> ▲1,4% | AC18: =IFERROR(IF(Y18/W18-1>=0,"▲","▼")&TEXT(ABS(Y18/W18-1),"0,0%"),"NM") -> ▲10,3% | AD18: =IFERROR(IF(Y18/X18-1>=0,"▲","▼")&TEXT(ABS(Y18/X18-1),"0,0%"),"NM") -> ▲6,9% | AE18: =IFERROR(IF(Z18/Y18-1>=0,"▲","▼")&TEXT(ABS(Z18/Y18-1),"0,0%"),"NM") -> ▲4,1% | AF18: =IFERROR(IF(AA18/Z18-1>=0,"▲","▼")&TEXT(ABS(AA18/Z18-1),"0,0%"),"NM") -> ▲10,3%
A19: Contribution Margin | B19: =B7-B18 -> 200795 | C19: =C7-C18 -> 219375 | D19: =D7-D18 -> 244020 | E19: =E7-E18 -> 260382 | F19: =F7-F18 -> 278669 | G19: =G7-G18 -> 321053 | H19: =IFERROR(IF(C19/B19-1>=0,"▲","▼")&TEXT(ABS(C19/B19-1),"0,0%"),"NM") -> ▲9,3% | I19: =IFERROR(IF(E19/C19-1>=0,"▲","▼")&TEXT(ABS(E19/C19-1),"0,0%"),"NM") -> ▲18,7% | J19: =IFERROR(IF(E19/D19-1>=0,"▲","▼")&TEXT(ABS(E19/D19-1),"0,0%"),"NM") -> ▲6,7% | K19: =IFERROR(IF(F19/E19-1>=0,"▲","▼")&TEXT(ABS(F19/E19-1),"0,0%"),"NM") -> ▲7,0% | L19: =IFERROR(IF(G19/F19-1>=0,"▲","▼")&TEXT(ABS(G19/F19-1),"0,0%"),"NM") -> ▲15,2% | U19: Contribution Margin | V19: =V7-V18 -> 202887.01 | W19: =W7-W18 -> 221775.64 | X19: =X7-X18 -> 246461.24 | Y19: =Y7-Y18 -> 262823.24 | Z19: =Z7-Z18 -> 281263.28 | AA19: =AA7-AA18 -> 324005.05 | AB19: =IFERROR(IF(W19/V19-1>=0,"▲","▼")&TEXT(ABS(W19/V19-1),"0,0%"),"NM") -> ▲9,3% | AC19: =IFERROR(IF(Y19/W19-1>=0,"▲","▼")&TEXT(ABS(Y19/W19-1),"0,0%"),"NM") -> ▲18,5% | AD19: =IFERROR(IF(Y19/X19-1>=0,"▲","▼")&TEXT(ABS(Y19/X19-1),"0,0%"),"NM") -> ▲6,6% | AE19: =IFERROR(IF(Z19/Y19-1>=0,"▲","▼")&TEXT(ABS(Z19/Y19-1),"0,0%"),"NM") -> ▲7,0% | AF19: =IFERROR(IF(AA19/Z19-1>=0,"▲","▼")&TEXT(ABS(AA19/Z19-1),"0,0%"),"NM") -> ▲15,2%
A20: Operating Expenditure | B20: 91915 | C20: 96259 | D20: 102939 | E20: 103460 | F20: 111303 | G20: 121421 | H20: =IFERROR(IF(C20/B20-1>=0,"▲","▼")&TEXT(ABS(C20/B20-1),"0,0%"),"NM") -> ▲4,7% | I20: =IFERROR(IF(E20/C20-1>=0,"▲","▼")&TEXT(ABS(E20/C20-1),"0,0%"),"NM") -> ▲7,5% | J20: =IFERROR(IF(E20/D20-1>=0,"▲","▼")&TEXT(ABS(E20/D20-1),"0,0%"),"NM") -> ▲0,5% | K20: =IFERROR(IF(F20/E20-1>=0,"▲","▼")&TEXT(ABS(F20/E20-1),"0,0%"),"NM") -> ▲7,6% | L20: =IFERROR(IF(G20/F20-1>=0,"▲","▼")&TEXT(ABS(G20/F20-1),"0,0%"),"NM") -> ▲9,1% | N20: =+Adjustments!C28 -> -26974.604 | O20: =+Adjustments!D28 -> -25828.494 | P20: =+Adjustments!E28 -> -25828.494 | Q20: =+Adjustments!F28 -> -25828.494 | R20: =+Adjustments!G28 -> -25828.494 | S20: =+Adjustments!H28 -> -25828.494 | U20: Operating Expenditure | V20: =+B20-N20 -> 118889.6 | W20: =+C20-O20 -> 122087.49 | X20: =+D20-P20 -> 128767.49 | Y20: =+E20-Q20 -> 129288.49 | Z20: =+F20-R20 -> 137131.49 | AA20: =+G20-S20 -> 147249.49 | AB20: =IFERROR(IF(W20/V20-1>=0,"▲","▼")&TEXT(ABS(W20/V20-1),"0,0%"),"NM") -> ▲2,7% | AC20: =IFERROR(IF(Y20/W20-1>=0,"▲","▼")&TEXT(ABS(Y20/W20-1),"0,0%"),"NM") -> ▲5,9% | AD20: =IFERROR(IF(Y20/X20-1>=0,"▲","▼")&TEXT(ABS(Y20/X20-1),"0,0%"),"NM") -> ▲0,4% | AE20: =IFERROR(IF(Z20/Y20-1>=0,"▲","▼")&TEXT(ABS(Z20/Y20-1),"0,0%"),"NM") -> ▲6,1% | AF20: =IFERROR(IF(AA20/Z20-1>=0,"▲","▼")&TEXT(ABS(AA20/Z20-1),"0,0%"),"NM") -> ▲7,4%
A21: EBITDA | B21: =B19-B20 -> 108880 | C21: =C19-C20 -> 123116 | D21: =D19-D20 -> 141081 | E21: =E19-E20 -> 156922 | F21: =F19-F20 -> 167366 | G21: =G19-G20 -> 199632 | H21: =IFERROR(IF(C21/B21-1>=0,"▲","▼")&TEXT(ABS(C21/B21-1),"0,0%"),"NM") -> ▲13,1% | I21: =IFERROR(IF(E21/C21-1>=0,"▲","▼")&TEXT(ABS(E21/C21-1),"0,0%"),"NM") -> ▲27,5% | J21: =IFERROR(IF(E21/D21-1>=0,"▲","▼")&TEXT(ABS(E21/D21-1),"0,0%"),"NM") -> ▲11,2% | K21: =IFERROR(IF(F21/E21-1>=0,"▲","▼")&TEXT(ABS(F21/E21-1),"0,0%"),"NM") -> ▲6,7% | L21: =IFERROR(IF(G21/F21-1>=0,"▲","▼")&TEXT(ABS(G21/F21-1),"0,0%"),"NM") -> ▲19,3% | U21: EBITDA | V21: =V19-V20 -> 83997.406 | W21: =W19-W20 -> 99688.15 | X21: =X19-X20 -> 117693.75 | Y21: =Y19-Y20 -> 133534.75 | Z21: =Z19-Z20 -> 144131.78 | AA21: =AA19-AA20 -> 176755.56 | AB21: =IFERROR(IF(W21/V21-1>=0,"▲","▼")&TEXT(ABS(W21/V21-1),"0,0%"),"NM") -> ▲18,7% | AC21: =IFERROR(IF(Y21/W21-1>=0,"▲","▼")&TEXT(ABS(Y21/W21-1),"0,0%"),"NM") -> ▲34,0% | AD21: =IFERROR(IF(Y21/X21-1>=0,"▲","▼")&TEXT(ABS(Y21/X21-1),"0,0%"),"NM") -> ▲13,5% | AE21: =IFERROR(IF(Z21/Y21-1>=0,"▲","▼")&TEXT(ABS(Z21/Y21-1),"0,0%"),"NM") -> ▲7,9% | AF21: =IFERROR(IF(AA21/Z21-1>=0,"▲","▼")&TEXT(ABS(AA21/Z21-1),"0,0%"),"NM") -> ▲22,6%
A22: Depreciation & Amortisation | B22: 72876 | C22: =75312 -> 75312 | D22: 80867 | E22: 81255 | F22: 97814 | G22: 117318 | H22: =IFERROR(IF(C22/B22-1>=0,"▲","▼")&TEXT(ABS(C22/B22-1),"0,0%"),"NM") -> ▲3,3% | I22: =IFERROR(IF(E22/C22-1>=0,"▲","▼")&TEXT(ABS(E22/C22-1),"0,0%"),"NM") -> ▲7,9% | J22: =IFERROR(IF(E22/D22-1>=0,"▲","▼")&TEXT(ABS(E22/D22-1),"0,0%"),"NM") -> ▲0,5% | K22: =IFERROR(IF(F22/E22-1>=0,"▲","▼")&TEXT(ABS(F22/E22-1),"0,0%"),"NM") -> ▲20,4% | L22: =IFERROR(IF(G22/F22-1>=0,"▲","▼")&TEXT(ABS(G22/F22-1),"0,0%"),"NM") -> ▲19,9% | N22: =+Adjustments!C30 -> 17775.848 | O22: =+Adjustments!D30 -> 17636.6 | P22: =+Adjustments!E30 -> 17636.6 | Q22: =+Adjustments!F30 -> 17636.6 | R22: =+Adjustments!G30 -> 17502.846 | S22: =+Adjustments!H30 -> 17186.89 | U22: Depreciation & Amortisation | V22: =+B22-N22 -> 55100.152 | W22: =+C22-O22 -> 57675.4 | X22: =+D22-P22 -> 63230.4 | Y22: =+E22-Q22 -> 63618.4 | Z22: =+F22-R22 -> 80311.154 | AA22: =+G22-S22 -> 100131.11 | AB22: =IFERROR(IF(W22/V22-1>=0,"▲","▼")&TEXT(ABS(W22/V22-1),"0,0%"),"NM") -> ▲4,7% | AC22: =IFERROR(IF(Y22/W22-1>=0,"▲","▼")&TEXT(ABS(Y22/W22-1),"0,0%"),"NM") -> ▲10,3% | AD22: =IFERROR(IF(Y22/X22-1>=0,"▲","▼")&TEXT(ABS(Y22/X22-1),"0,0%"),"NM") -> ▲0,6% | AE22: =IFERROR(IF(Z22/Y22-1>=0,"▲","▼")&TEXT(ABS(Z22/Y22-1),"0,0%"),"NM") -> ▲26,2% | AF22: =IFERROR(IF(AA22/Z22-1>=0,"▲","▼")&TEXT(ABS(AA22/Z22-1),"0,0%"),"NM") -> ▲24,7%
A23: EBIT | B23: =B21-B22 -> 36004 | C23: =C21-C22 -> 47804 | D23: =D21-D22 -> 60214 | E23: =E21-E22 -> 75667 | F23: =F21-F22 -> 69552 | G23: =G21-G22 -> 82314 | H23: =IFERROR(IF(C23/B23-1>=0,"▲","▼")&TEXT(ABS(C23/B23-1),"0,0%"),"NM") -> ▲32,8% | I23: =IFERROR(IF(E23/C23-1>=0,"▲","▼")&TEXT(ABS(E23/C23-1),"0,0%"),"NM") -> ▲58,3% | J23: =IFERROR(IF(E23/D23-1>=0,"▲","▼")&TEXT(ABS(E23/D23-1),"0,0%"),"NM") -> ▲25,7% | K23: =IFERROR(IF(F23/E23-1>=0,"▲","▼")&TEXT(ABS(F23/E23-1),"0,0%"),"NM") -> ▼8,1% | L23: =IFERROR(IF(G23/F23-1>=0,"▲","▼")&TEXT(ABS(G23/F23-1),"0,0%"),"NM") -> ▲18,3% | U23: EBIT | V23: =V21-V22 -> 28897.254 | W23: =W21-W22 -> 42012.749 | X23: =X21-X22 -> 54463.348 | Y23: =Y21-Y22 -> 69916.348 | Z23: =Z21-Z22 -> 63820.628 | AA23: =AA21-AA22 -> 76624.445 | AB23: =IFERROR(IF(W23/V23-1>=0,"▲","▼")&TEXT(ABS(W23/V23-1),"0,0%"),"NM") -> ▲45,4% | AC23: =IFERROR(IF(Y23/W23-1>=0,"▲","▼")&TEXT(ABS(Y23/W23-1),"0,0%"),"NM") -> ▲66,4% | AD23: =IFERROR(IF(Y23/X23-1>=0,"▲","▼")&TEXT(ABS(Y23/X23-1),"0,0%"),"NM") -> ▲28,4% | AE23: =IFERROR(IF(Z23/Y23-1>=0,"▲","▼")&TEXT(ABS(Z23/Y23-1),"0,0%"),"NM") -> ▼8,7% | AF23: =IFERROR(IF(AA23/Z23-1>=0,"▲","▼")&TEXT(ABS(AA23/Z23-1),"0,0%"),"NM") -> ▲20,1%
A24: Finance Costs | B24: 18334 | C24: 19946 | D24: 22095 | E24: 22553 | F24: 21178 | G24: 19300 | H24: =IFERROR(IF(C24/B24-1>=0,"▲","▼")&TEXT(ABS(C24/B24-1),"0,0%"),"NM") -> ▲8,8% | I24: =IFERROR(IF(E24/C24-1>=0,"▲","▼")&TEXT(ABS(E24/C24-1),"0,0%"),"NM") -> ▲13,1% | J24: =IFERROR(IF(E24/D24-1>=0,"▲","▼")&TEXT(ABS(E24/D24-1),"0,0%"),"NM") -> ▲2,1% | K24: =IFERROR(IF(F24/E24-1>=0,"▲","▼")&TEXT(ABS(F24/E24-1),"0,0%"),"NM") -> ▼6,1% | L24: =IFERROR(IF(G24/F24-1>=0,"▲","▼")&TEXT(ABS(G24/F24-1),"0,0%"),"NM") -> ▼8,9% | N24: =+Adjustments!C31 -> 10948.812 | O24: =+Adjustments!D31 -> 8832.6109 | P24: =+Adjustments!E31 -> 8832.6109 | Q24: =+Adjustments!F31 -> 8832.6109 | R24: =+Adjustments!G31 -> 8832.6109 | S24: =+Adjustments!H31 -> 8832.6109 | U24: Finance Costs | V24: =B24-N24 -> 7385.1881 | W24: =C24-O24 -> 11113.389 | X24: =D24-P24 -> 13262.389 | Y24: =E24-Q24 -> 13720.389 | Z24: =F24-R24 -> 12345.389 | AA24: =G24-S24 -> 10467.389 | AB24: =IFERROR(IF(W24/V24-1>=0,"▲","▼")&TEXT(ABS(W24/V24-1),"0,0%"),"NM") -> ▲50,5% | AC24: =IFERROR(IF(Y24/W24-1>=0,"▲","▼")&TEXT(ABS(Y24/W24-1),"0,0%"),"NM") -> ▲23,5% | AD24: =IFERROR(IF(Y24/X24-1>=0,"▲","▼")&TEXT(ABS(Y24/X24-1),"0,0%"),"NM") -> ▲3,5% | AE24: =IFERROR(IF(Z24/Y24-1>=0,"▲","▼")&TEXT(ABS(Z24/Y24-1),"0,0%"),"NM") -> ▼10,0% | AF24: =IFERROR(IF(AA24/Z24-1>=0,"▲","▼")&TEXT(ABS(AA24/Z24-1),"0,0%"),"NM") -> ▼15,2%
A25: Taxation | B25: 7075 | C25: 6817 | D25: 13384 | E25: 16991 | F25: 16973 | G25: 22097 | H25: =IFERROR(IF(C25/B25-1>=0,"▲","▼")&TEXT(ABS(C25/B25-1),"0,0%"),"NM") -> ▼3,6% | I25: =IFERROR(IF(E25/C25-1>=0,"▲","▼")&TEXT(ABS(E25/C25-1),"0,0%"),"NM") -> ▲149,2% | J25: =IFERROR(IF(E25/D25-1>=0,"▲","▼")&TEXT(ABS(E25/D25-1),"0,0%"),"NM") -> ▲27,0% | K25: =IFERROR(IF(F25/E25-1>=0,"▲","▼")&TEXT(ABS(F25/E25-1),"0,0%"),"NM") -> ▼0,1% | L25: =IFERROR(IF(G25/F25-1>=0,"▲","▼")&TEXT(ABS(G25/F25-1),"0,0%"),"NM") -> ▲30,2% | N25: =+Adjustments!C33 -> -595.22915 | O25: =+Adjustments!D33 -> -1368.8821 | P25: =+Adjustments!E33 -> -1000 | Q25: =+Adjustments!F33 -> -1000 | R25: =+Adjustments!G33 -> -1000 | S25: =+Adjustments!H33 -> -1000 | U25: Taxation | V25: =B25-N25 -> 7670.2291 | W25: =C25-O25 -> 8185.8821 | X25: =D25-P25 -> 14384 | Y25: =E25-Q25 -> 17991 | Z25: =F25-R25 -> 17973 | AA25: =G25-S25 -> 23097 | AB25: =IFERROR(IF(W25/V25-1>=0,"▲","▼")&TEXT(ABS(W25/V25-1),"0,0%"),"NM") -> ▲6,7% | AC25: =IFERROR(IF(Y25/W25-1>=0,"▲","▼")&TEXT(ABS(Y25/W25-1),"0,0%"),"NM") -> ▲119,8% | AD25: =IFERROR(IF(Y25/X25-1>=0,"▲","▼")&TEXT(ABS(Y25/X25-1),"0,0%"),"NM") -> ▲25,1% | AE25: =IFERROR(IF(Z25/Y25-1>=0,"▲","▼")&TEXT(ABS(Z25/Y25-1),"0,0%"),"NM") -> ▼0,1% | AF25: =IFERROR(IF(AA25/Z25-1>=0,"▲","▼")&TEXT(ABS(AA25/Z25-1),"0,0%"),"NM") -> ▲28,5%
A26: Profit (Loss) after taxation | B26: =B23-B24-B25 -> 10595 | C26: =C23-C24-C25 -> 21041 | D26: =D23-D24-D25 -> 24735 | E26: =E23-E24-E25 -> 36123 | F26: =F23-F24-F25 -> 31401 | G26: =G23-G24-G25 -> 40917 | H26: =IFERROR(IF(C26/B26-1>=0,"▲","▼")&TEXT(ABS(C26/B26-1),"0,0%"),"NM") -> ▲98,6% | I26: =IFERROR(IF(E26/C26-1>=0,"▲","▼")&TEXT(ABS(E26/C26-1),"0,0%"),"NM") -> ▲71,7% | J26: =IFERROR(IF(E26/D26-1>=0,"▲","▼")&TEXT(ABS(E26/D26-1),"0,0%"),"NM") -> ▲46,0% | K26: =IFERROR(IF(F26/E26-1>=0,"▲","▼")&TEXT(ABS(F26/E26-1),"0,0%"),"NM") -> ▼13,1% | L26: =IFERROR(IF(G26/F26-1>=0,"▲","▼")&TEXT(ABS(G26/F26-1),"0,0%"),"NM") -> ▲30,3% | U26: Profit (Loss) after taxation | V26: =V23-V24-V25 -> 13841.837 | W26: =W23-W24-W25 -> 22713.478 | X26: =X23-X24-X25 -> 26816.959 | Y26: =Y23-Y24-Y25 -> 38204.959 | Z26: =Z23-Z24-Z25 -> 33502.239 | AA26: =AA23-AA24-AA25 -> 43060.056 | AB26: =IFERROR(IF(W26/V26-1>=0,"▲","▼")&TEXT(ABS(W26/V26-1),"0,0%"),"NM") -> ▲64,1% | AC26: =IFERROR(IF(Y26/W26-1>=0,"▲","▼")&TEXT(ABS(Y26/W26-1),"0,0%"),"NM") -> ▲68,2% | AD26: =IFERROR(IF(Y26/X26-1>=0,"▲","▼")&TEXT(ABS(Y26/X26-1),"0,0%"),"NM") -> ▲42,5% | AE26: =IFERROR(IF(Z26/Y26-1>=0,"▲","▼")&TEXT(ABS(Z26/Y26-1),"0,0%"),"NM") -> ▼12,3% | AF26: =IFERROR(IF(AA26/Z26-1>=0,"▲","▼")&TEXT(ABS(AA26/Z26-1),"0,0%"),"NM") -> ▲28,5%
A28: Capex LC | B28: 45099 | C28: 64862 | D28: 86641 | E28: 106434 | F28: 79152 | G28: 77427 | H28: =IFERROR(IF(C28/B28-1>=0,"▲","▼")&TEXT(ABS(C28/B28-1),"0,0%"),"NM") -> ▲43,8% | I28: =IFERROR(IF(E28/C28-1>=0,"▲","▼")&TEXT(ABS(E28/C28-1),"0,0%"),"NM") -> ▲64,1% | J28: =IFERROR(IF(E28/D28-1>=0,"▲","▼")&TEXT(ABS(E28/D28-1),"0,0%"),"NM") -> ▲22,8% | K28: =IFERROR(IF(F28/E28-1>=0,"▲","▼")&TEXT(ABS(F28/E28-1),"0,0%"),"NM") -> ▼25,6% | L28: =IFERROR(IF(G28/F28-1>=0,"▲","▼")&TEXT(ABS(G28/F28-1),"0,0%"),"NM") -> ▼2,2% | U28: Capex LC | V28: 45099 | W28: 64862 | X28: 86641 | Y28: 106434 | Z28: 79152 | AA28: 77427 | AB28: =IFERROR(IF(W28/V28-1>=0,"▲","▼")&TEXT(ABS(W28/V28-1),"0,0%"),"NM") -> ▲43,8% | AC28: =IFERROR(IF(Y28/W28-1>=0,"▲","▼")&TEXT(ABS(Y28/W28-1),"0,0%"),"NM") -> ▲64,1% | AD28: =IFERROR(IF(Y28/X28-1>=0,"▲","▼")&TEXT(ABS(Y28/X28-1),"0,0%"),"NM") -> ▲22,8% | AE28: =IFERROR(IF(Z28/Y28-1>=0,"▲","▼")&TEXT(ABS(Z28/Y28-1),"0,0%"),"NM") -> ▼25,6% | AF28: =IFERROR(IF(AA28/Z28-1>=0,"▲","▼")&TEXT(ABS(AA28/Z28-1),"0,0%"),"NM") -> ▼2,2%
A30: Contribution Margin | B30: 71,0% | C30: 0.738 | D30: 74,3% | E30: 0.743 | F30: 74,8% | G30: 75,6% | H30: =IFERROR(IF(IF(ISTEXT(C30),_xlfn.NUMBERVALUE(SUBSTITUTE(C30,"%",""),",",".")/100,C30)-IF(ISTEXT(B30),_xlfn.NUMBERVALUE(SUBSTITUTE(B30,"%",""),",",".")/100,B30)>=0,"▲","▼")&TEXT(ABS(IF(ISTEXT(C30),_xlfn.NUMBERVALUE(SUBSTITUTE(C30,"%",""),",",".")/100,C30)-IF(ISTEXT(B30),_xlfn.NUMBERVALUE(SUBSTITUTE(B30,"%",""),",",".")/100,B30))*100,"0,0")&" pp","NM") -> ▲2,8 pp | I30: =IFERROR(IF(IF(ISTEXT(E30),_xlfn.NUMBERVALUE(SUBSTITUTE(E30,"%",""),",",".")/100,E30)-IF(ISTEXT(C30),_xlfn.NUMBERVALUE(SUBSTITUTE(C30,"%",""),",",".")/100,C30)>=0,"▲","▼")&TEXT(ABS(IF(ISTEXT(E30),_xlfn.NUMBERVALUE(SUBSTITUTE(E30,"%",""),",",".")/100,E30)-IF(ISTEXT(C30),_xlfn.NUMBERVALUE(SUBSTITUTE(C30,"%",""),",",".")/100,C30))*100,"0,0")&" pp","NM") -> ▲0,5 pp | J30: =IFERROR(IF(IF(ISTEXT(E30),_xlfn.NUMBERVALUE(SUBSTITUTE(E30,"%",""),",",".")/100,E30)-IF(ISTEXT(D30),_xlfn.NUMBERVALUE(SUBSTITUTE(D30,"%",""),",",".")/100,D30)>=0,"▲","▼")&TEXT(ABS(IF(ISTEXT(E30),_xlfn.NUMBERVALUE(SUBSTITUTE(E30,"%",""),",",".")/100,E30)-IF(ISTEXT(D30),_xlfn.NUMBERVALUE(SUBSTITUTE(D30,"%",""),",",".")/100,D30))*100,"0,0")&" pp","NM") -> ▲0,0 pp | K30: =IFERROR(IF(IF(ISTEXT(F30),_xlfn.NUMBERVALUE(SUBSTITUTE(F30,"%",""),",",".")/100,F30)-IF(ISTEXT(E30),_xlfn.NUMBERVALUE(SUBSTITUTE(E30,"%",""),",",".")/100,E30)>=0,"▲","▼")&TEXT(ABS(IF(ISTEXT(F30),_xlfn.NUMBERVALUE(SUBSTITUTE(F30,"%",""),",",".")/100,F30)-IF(ISTEXT(E30),_xlfn.NUMBERVALUE(SUBSTITUTE(E30,"%",""),",",".")/100,E30))*100,"0,0")&" pp","NM") -> ▲0,5 pp | L30: =IFERROR(IF(IF(ISTEXT(G30),_xlfn.NUMBERVALUE(SUBSTITUTE(G30,"%",""),",",".")/100,G30)-IF(ISTEXT(F30),_xlfn.NUMBERVALUE(SUBSTITUTE(F30,"%",""),",",".")/100,F30)>=0,"▲","▼")&TEXT(ABS(IF(ISTEXT(G30),_xlfn.NUMBERVALUE(SUBSTITUTE(G30,"%",""),",",".")/100,G30)-IF(ISTEXT(F30),_xlfn.NUMBERVALUE(SUBSTITUTE(F30,"%",""),",",".")/100,F30))*100,"0,0")&" pp","NM") -> ▲0,8 pp | U30: Contribution Margin | V30: 71,0% | W30: 0.738 | X30: 74,3% | Y30: 0.743 | Z30: 74,8% | AA30: 75,6% | AB30: =IFERROR(IF(IF(ISTEXT(W30),_xlfn.NUMBERVALUE(SUBSTITUTE(W30,"%",""),",",".")/100,W30)-IF(ISTEXT(V30),_xlfn.NUMBERVALUE(SUBSTITUTE(V30,"%",""),",",".")/100,V30)>=0,"▲","▼")&TEXT(ABS(IF(ISTEXT(W30),_xlfn.NUMBERVALUE(SUBSTITUTE(W30,"%",""),",",".")/100,W30)-IF(ISTEXT(V30),_xlfn.NUMBERVALUE(SUBSTITUTE(V30,"%",""),",",".")/100,V30))*100,"0,0")&" pp","NM") -> ▲2,8 pp | AC30: =IFERROR(IF(IF(ISTEXT(Y30),_xlfn.NUMBERVALUE(SUBSTITUTE(Y30,"%",""),",",".")/100,Y30)-IF(ISTEXT(W30),_xlfn.NUMBERVALUE(SUBSTITUTE(W30,"%",""),",",".")/100,W30)>=0,"▲","▼")&TEXT(ABS(IF(ISTEXT(Y30),_xlfn.NUMBERVALUE(SUBSTITUTE(Y30,"%",""),",",".")/100,Y30)-IF(ISTEXT(W30),_xlfn.NUMBERVALUE(SUBSTITUTE(W30,"%",""),",",".")/100,W30))*100,"0,0")&" pp","NM") -> ▲0,5 pp | AD30: =IFERROR(IF(IF(ISTEXT(Y30),_xlfn.NUMBERVALUE(SUBSTITUTE(Y30,"%",""),",",".")/100,Y30)-IF(ISTEXT(X30),_xlfn.NUMBERVALUE(SUBSTITUTE(X30,"%",""),",",".")/100,X30)>=0,"▲","▼")&TEXT(ABS(IF(ISTEXT(Y30),_xlfn.NUMBERVALUE(SUBSTITUTE(Y30,"%",""),",",".")/100,Y30)-IF(ISTEXT(X30),_xlfn.NUMBERVALUE(SUBSTITUTE(X30,"%",""),",",".")/100,X30))*100,"0,0")&" pp","NM") -> ▲0,0 pp | AE30: =IFERROR(IF(IF(ISTEXT(Z30),_xlfn.NUMBERVALUE(SUBSTITUTE(Z30,"%",""),",",".")/100,Z30)-IF(ISTEXT(Y30),_xlfn.NUMBERVALUE(SUBSTITUTE(Y30,"%",""),",",".")/100,Y30)>=0,"▲","▼")&TEXT(ABS(IF(ISTEXT(Z30),_xlfn.NUMBERVALUE(SUBSTITUTE(Z30,"%",""),",",".")/100,Z30)-IF(ISTEXT(Y30),_xlfn.NUMBERVALUE(SUBSTITUTE(Y30,"%",""),",",".")/100,Y30))*100,"0,0")&" pp","NM") -> ▲0,5 pp | AF30: =IFERROR(IF(IF(ISTEXT(AA30),_xlfn.NUMBERVALUE(SUBSTITUTE(AA30,"%",""),",",".")/100,AA30)-IF(ISTEXT(Z30),_xlfn.NUMBERVALUE(SUBSTITUTE(Z30,"%",""),",",".")/100,Z30)>=0,"▲","▼")&TEXT(ABS(IF(ISTEXT(AA30),_xlfn.NUMBERVALUE(SUBSTITUTE(AA30,"%",""),",",".")/100,AA30)-IF(ISTEXT(Z30),_xlfn.NUMBERVALUE(SUBSTITUTE(Z30,"%",""),",",".")/100,Z30))*100,"0,0")&" pp","NM") -> ▲0,8 pp
A31: COS to Revenue | B31: 29,0% | C31: 0.262 | D31: 25,7% | E31: 0.257 | F31: 25,2% | G31: 24,4% | H31: =IFERROR(IF(IF(ISTEXT(C31),_xlfn.NUMBERVALUE(SUBSTITUTE(C31,"%",""),",",".")/100,C31)-IF(ISTEXT(B31),_xlfn.NUMBERVALUE(SUBSTITUTE(B31,"%",""),",",".")/100,B31)>=0,"▲","▼")&TEXT(ABS(IF(ISTEXT(C31),_xlfn.NUMBERVALUE(SUBSTITUTE(C31,"%",""),",",".")/100,C31)-IF(ISTEXT(B31),_xlfn.NUMBERVALUE(SUBSTITUTE(B31,"%",""),",",".")/100,B31))*100,"0,0")&" pp","NM") -> ▼2,8 pp | I31: =IFERROR(IF(IF(ISTEXT(E31),_xlfn.NUMBERVALUE(SUBSTITUTE(E31,"%",""),",",".")/100,E31)-IF(ISTEXT(C31),_xlfn.NUMBERVALUE(SUBSTITUTE(C31,"%",""),",",".")/100,C31)>=0,"▲","▼")&TEXT(ABS(IF(ISTEXT(E31),_xlfn.NUMBERVALUE(SUBSTITUTE(E31,"%",""),",",".")/100,E31)-IF(ISTEXT(C31),_xlfn.NUMBERVALUE(SUBSTITUTE(C31,"%",""),",",".")/100,C31))*100,"0,0")&" pp","NM") -> ▼0,5 pp | J31: =IFERROR(IF(IF(ISTEXT(E31),_xlfn.NUMBERVALUE(SUBSTITUTE(E31,"%",""),",",".")/100,E31)-IF(ISTEXT(D31),_xlfn.NUMBERVALUE(SUBSTITUTE(D31,"%",""),",",".")/100,D31)>=0,"▲","▼")&TEXT(ABS(IF(ISTEXT(E31),_xlfn.NUMBERVALUE(SUBSTITUTE(E31,"%",""),",",".")/100,E31)-IF(ISTEXT(D31),_xlfn.NUMBERVALUE(SUBSTITUTE(D31,"%",""),",",".")/100,D31))*100,"0,0")&" pp","NM") -> ▲0,0 pp | K31: =IFERROR(IF(IF(ISTEXT(F31),_xlfn.NUMBERVALUE(SUBSTITUTE(F31,"%",""),",",".")/100,F31)-IF(ISTEXT(E31),_xlfn.NUMBERVALUE(SUBSTITUTE(E31,"%",""),",",".")/100,E31)>=0,"▲","▼")&TEXT(ABS(IF(ISTEXT(F31),_xlfn.NUMBERVALUE(SUBSTITUTE(F31,"%",""),",",".")/100,F31)-IF(ISTEXT(E31),_xlfn.NUMBERVALUE(SUBSTITUTE(E31,"%",""),",",".")/100,E31))*100,"0,0")&" pp","NM") -> ▼0,5 pp | L31: =IFERROR(IF(IF(ISTEXT(G31),_xlfn.NUMBERVALUE(SUBSTITUTE(G31,"%",""),",",".")/100,G31)-IF(ISTEXT(F31),_xlfn.NUMBERVALUE(SUBSTITUTE(F31,"%",""),",",".")/100,F31)>=0,"▲","▼")&TEXT(ABS(IF(ISTEXT(G31),_xlfn.NUMBERVALUE(SUBSTITUTE(G31,"%",""),",",".")/100,G31)-IF(ISTEXT(F31),_xlfn.NUMBERVALUE(SUBSTITUTE(F31,"%",""),",",".")/100,F31))*100,"0,0")&" pp","NM") -> ▼0,8 pp | U31: COS to Revenue | V31: 29,0% | W31: 0.262 | X31: 25,7% | Y31: 0.257 | Z31: 25,2% | AA31: 24,4% | AB31: =IFERROR(IF(IF(ISTEXT(W31),_xlfn.NUMBERVALUE(SUBSTITUTE(W31,"%",""),",",".")/100,W31)-IF(ISTEXT(V31),_xlfn.NUMBERVALUE(SUBSTITUTE(V31,"%",""),",",".")/100,V31)>=0,"▲","▼")&TEXT(ABS(IF(ISTEXT(W31),_xlfn.NUMBERVALUE(SUBSTITUTE(W31,"%",""),",",".")/100,W31)-IF(ISTEXT(V31),_xlfn.NUMBERVALUE(SUBSTITUTE(V31,"%",""),",",".")/100,V31))*100,"0,0")&" pp","NM") -> ▼2,8 pp | AC31: =IFERROR(IF(IF(ISTEXT(Y31),_xlfn.NUMBERVALUE(SUBSTITUTE(Y31,"%",""),",",".")/100,Y31)-IF(ISTEXT(W31),_xlfn.NUMBERVALUE(SUBSTITUTE(W31,"%",""),",",".")/100,W31)>=0,"▲","▼")&TEXT(ABS(IF(ISTEXT(Y31),_xlfn.NUMBERVALUE(SUBSTITUTE(Y31,"%",""),",",".")/100,Y31)-IF(ISTEXT(W31),_xlfn.NUMBERVALUE(SUBSTITUTE(W31,"%",""),",",".")/100,W31))*100,"0,0")&" pp","NM") -> ▼0,5 pp | AD31: =IFERROR(IF(IF(ISTEXT(Y31),_xlfn.NUMBERVALUE(SUBSTITUTE(Y31,"%",""),",",".")/100,Y31)-IF(ISTEXT(X31),_xlfn.NUMBERVALUE(SUBSTITUTE(X31,"%",""),",",".")/100,X31)>=0,"▲","▼")&TEXT(ABS(IF(ISTEXT(Y31),_xlfn.NUMBERVALUE(SUBSTITUTE(Y31,"%",""),",",".")/100,Y31)-IF(ISTEXT(X31),_xlfn.NUMBERVALUE(SUBSTITUTE(X31,"%",""),",",".")/100,X31))*100,"0,0")&" pp","NM") -> ▲0,0 pp | AE31: =IFERROR(IF(IF(ISTEXT(Z31),_xlfn.NUMBERVALUE(SUBSTITUTE(Z31,"%",""),",",".")/100,Z31)-IF(ISTEXT(Y31),_xlfn.NUMBERVALUE(SUBSTITUTE(Y31,"%",""),",",".")/100,Y31)>=0,"▲","▼")&TEXT(ABS(IF(ISTEXT(Z31),_xlfn.NUMBERVALUE(SUBSTITUTE(Z31,"%",""),",",".")/100,Z31)-IF(ISTEXT(Y31),_xlfn.NUMBERVALUE(SUBSTITUTE(Y31,"%",""),",",".")/100,Y31))*100,"0,0")&" pp","NM") -> ▼0,5 pp | AF31: =IFERROR(IF(IF(ISTEXT(AA31),_xlfn.NUMBERVALUE(SUBSTITUTE(AA31,"%",""),",",".")/100,AA31)-IF(ISTEXT(Z31),_xlfn.NUMBERVALUE(SUBSTITUTE(Z31,"%",""),",",".")/100,Z31)>=0,"▲","▼")&TEXT(ABS(IF(ISTEXT(AA31),_xlfn.NUMBERVALUE(SUBSTITUTE(AA31,"%",""),",",".")/100,AA31)-IF(ISTEXT(Z31),_xlfn.NUMBERVALUE(SUBSTITUTE(Z31,"%",""),",",".")/100,Z31))*100,"0,0")&" pp","NM") -> ▼0,8 pp
A32: Opex to Revenue | B32: 32,8% | C32: 0.322 | D32: 31,4% | E32: 0.295 | F32: 29,9% | G32: 28,6% | H32: =IFERROR(IF(IF(ISTEXT(C32),_xlfn.NUMBERVALUE(SUBSTITUTE(C32,"%",""),",",".")/100,C32)-IF(ISTEXT(B32),_xlfn.NUMBERVALUE(SUBSTITUTE(B32,"%",""),",",".")/100,B32)>=0,"▲","▼")&TEXT(ABS(IF(ISTEXT(C32),_xlfn.NUMBERVALUE(SUBSTITUTE(C32,"%",""),",",".")/100,C32)-IF(ISTEXT(B32),_xlfn.NUMBERVALUE(SUBSTITUTE(B32,"%",""),",",".")/100,B32))*100,"0,0")&" pp","NM") -> ▼0,6 pp | I32: =IFERROR(IF(IF(ISTEXT(E32),_xlfn.NUMBERVALUE(SUBSTITUTE(E32,"%",""),",",".")/100,E32)-IF(ISTEXT(C32),_xlfn.NUMBERVALUE(SUBSTITUTE(C32,"%",""),",",".")/100,C32)>=0,"▲","▼")&TEXT(ABS(IF(ISTEXT(E32),_xlfn.NUMBERVALUE(SUBSTITUTE(E32,"%",""),",",".")/100,E32)-IF(ISTEXT(C32),_xlfn.NUMBERVALUE(SUBSTITUTE(C32,"%",""),",",".")/100,C32))*100,"0,0")&" pp","NM") -> ▼2,7 pp | J32: =IFERROR(IF(IF(ISTEXT(E32),_xlfn.NUMBERVALUE(SUBSTITUTE(E32,"%",""),",",".")/100,E32)-IF(ISTEXT(D32),_xlfn.NUMBERVALUE(SUBSTITUTE(D32,"%",""),",",".")/100,D32)>=0,"▲","▼")&TEXT(ABS(IF(ISTEXT(E32),_xlfn.NUMBERVALUE(SUBSTITUTE(E32,"%",""),",",".")/100,E32)-IF(ISTEXT(D32),_xlfn.NUMBERVALUE(SUBSTITUTE(D32,"%",""),",",".")/100,D32))*100,"0,0")&" pp","NM") -> ▼1,9 pp | K32: =IFERROR(IF(IF(ISTEXT(F32),_xlfn.NUMBERVALUE(SUBSTITUTE(F32,"%",""),",",".")/100,F32)-IF(ISTEXT(E32),_xlfn.NUMBERVALUE(SUBSTITUTE(E32,"%",""),",",".")/100,E32)>=0,"▲","▼")&TEXT(ABS(IF(ISTEXT(F32),_xlfn.NUMBERVALUE(SUBSTITUTE(F32,"%",""),",",".")/100,F32)-IF(ISTEXT(E32),_xlfn.NUMBERVALUE(SUBSTITUTE(E32,"%",""),",",".")/100,E32))*100,"0,0")&" pp","NM") -> ▲0,4 pp | L32: =IFERROR(IF(IF(ISTEXT(G32),_xlfn.NUMBERVALUE(SUBSTITUTE(G32,"%",""),",",".")/100,G32)-IF(ISTEXT(F32),_xlfn.NUMBERVALUE(SUBSTITUTE(F32,"%",""),",",".")/100,F32)>=0,"▲","▼")&TEXT(ABS(IF(ISTEXT(G32),_xlfn.NUMBERVALUE(SUBSTITUTE(G32,"%",""),",",".")/100,G32)-IF(ISTEXT(F32),_xlfn.NUMBERVALUE(SUBSTITUTE(F32,"%",""),",",".")/100,F32))*100,"0,0")&" pp","NM") -> ▼1,3 pp | U32: Opex to Revenue | V32: 32,8% | W32: 0.322 | X32: 31,4% | Y32: 0.295 | Z32: 29,9% | AA32: 28,6% | AB32: =IFERROR(IF(IF(ISTEXT(W32),_xlfn.NUMBERVALUE(SUBSTITUTE(W32,"%",""),",",".")/100,W32)-IF(ISTEXT(V32),_xlfn.NUMBERVALUE(SUBSTITUTE(V32,"%",""),",",".")/100,V32)>=0,"▲","▼")&TEXT(ABS(IF(ISTEXT(W32),_xlfn.NUMBERVALUE(SUBSTITUTE(W32,"%",""),",",".")/100,W32)-IF(ISTEXT(V32),_xlfn.NUMBERVALUE(SUBSTITUTE(V32,"%",""),",",".")/100,V32))*100,"0,0")&" pp","NM") -> ▼0,6 pp | AC32: =IFERROR(IF(IF(ISTEXT(Y32),_xlfn.NUMBERVALUE(SUBSTITUTE(Y32,"%",""),",",".")/100,Y32)-IF(ISTEXT(W32),_xlfn.NUMBERVALUE(SUBSTITUTE(W32,"%",""),",",".")/100,W32)>=0,"▲","▼")&TEXT(ABS(IF(ISTEXT(Y32),_xlfn.NUMBERVALUE(SUBSTITUTE(Y32,"%",""),",",".")/100,Y32)-IF(ISTEXT(W32),_xlfn.NUMBERVALUE(SUBSTITUTE(W32,"%",""),",",".")/100,W32))*100,"0,0")&" pp","NM") -> ▼2,7 pp | AD32: =IFERROR(IF(IF(ISTEXT(Y32),_xlfn.NUMBERVALUE(SUBSTITUTE(Y32,"%",""),",",".")/100,Y32)-IF(ISTEXT(X32),_xlfn.NUMBERVALUE(SUBSTITUTE(X32,"%",""),",",".")/100,X32)>=0,"▲","▼")&TEXT(ABS(IF(ISTEXT(Y32),_xlfn.NUMBERVALUE(SUBSTITUTE(Y32,"%",""),",",".")/100,Y32)-IF(ISTEXT(X32),_xlfn.NUMBERVALUE(SUBSTITUTE(X32,"%",""),",",".")/100,X32))*100,"0,0")&" pp","NM") -> ▼1,9 pp | AE32: =IFERROR(IF(IF(ISTEXT(Z32),_xlfn.NUMBERVALUE(SUBSTITUTE(Z32,"%",""),",",".")/100,Z32)-IF(ISTEXT(Y32),_xlfn.NUMBERVALUE(SUBSTITUTE(Y32,"%",""),",",".")/100,Y32)>=0,"▲","▼")&TEXT(ABS(IF(ISTEXT(Z32),_xlfn.NUMBERVALUE(SUBSTITUTE(Z32,"%",""),",",".")/100,Z32)-IF(ISTEXT(Y32),_xlfn.NUMBERVALUE(SUBSTITUTE(Y32,"%",""),",",".")/100,Y32))*100,"0,0")&" pp","NM") -> ▲0,4 pp | AF32: =IFERROR(IF(IF(ISTEXT(AA32),_xlfn.NUMBERVALUE(SUBSTITUTE(AA32,"%",""),",",".")/100,AA32)-IF(ISTEXT(Z32),_xlfn.NUMBERVALUE(SUBSTITUTE(Z32,"%",""),",",".")/100,Z32)>=0,"▲","▼")&TEXT(ABS(IF(ISTEXT(AA32),_xlfn.NUMBERVALUE(SUBSTITUTE(AA32,"%",""),",",".")/100,AA32)-IF(ISTEXT(Z32),_xlfn.NUMBERVALUE(SUBSTITUTE(Z32,"%",""),",",".")/100,Z32))*100,"0,0")&" pp","NM") -> ▼1,3 pp
A33: Total Cost to Revenue | B33: 61,8% | C33: 0.584 | D33: 57,0% | E33: 0.552 | F33: 55,1% | G33: 53,0% | H33: =IFERROR(IF(IF(ISTEXT(C33),_xlfn.NUMBERVALUE(SUBSTITUTE(C33,"%",""),",",".")/100,C33)-IF(ISTEXT(B33),_xlfn.NUMBERVALUE(SUBSTITUTE(B33,"%",""),",",".")/100,B33)>=0,"▲","▼")&TEXT(ABS(IF(ISTEXT(C33),_xlfn.NUMBERVALUE(SUBSTITUTE(C33,"%",""),",",".")/100,C33)-IF(ISTEXT(B33),_xlfn.NUMBERVALUE(SUBSTITUTE(B33,"%",""),",",".")/100,B33))*100,"0,0")&" pp","NM") -> ▼3,4 pp | I33: =IFERROR(IF(IF(ISTEXT(E33),_xlfn.NUMBERVALUE(SUBSTITUTE(E33,"%",""),",",".")/100,E33)-IF(ISTEXT(C33),_xlfn.NUMBERVALUE(SUBSTITUTE(C33,"%",""),",",".")/100,C33)>=0,"▲","▼")&TEXT(ABS(IF(ISTEXT(E33),_xlfn.NUMBERVALUE(SUBSTITUTE(E33,"%",""),",",".")/100,E33)-IF(ISTEXT(C33),_xlfn.NUMBERVALUE(SUBSTITUTE(C33,"%",""),",",".")/100,C33))*100,"0,0")&" pp","NM") -> ▼3,2 pp | J33: =IFERROR(IF(IF(ISTEXT(E33),_xlfn.NUMBERVALUE(SUBSTITUTE(E33,"%",""),",",".")/100,E33)-IF(ISTEXT(D33),_xlfn.NUMBERVALUE(SUBSTITUTE(D33,"%",""),",",".")/100,D33)>=0,"▲","▼")&TEXT(ABS(IF(ISTEXT(E33),_xlfn.NUMBERVALUE(SUBSTITUTE(E33,"%",""),",",".")/100,E33)-IF(ISTEXT(D33),_xlfn.NUMBERVALUE(SUBSTITUTE(D33,"%",""),",",".")/100,D33))*100,"0,0")&" pp","NM") -> ▼1,8 pp | K33: =IFERROR(IF(IF(ISTEXT(F33),_xlfn.NUMBERVALUE(SUBSTITUTE(F33,"%",""),",",".")/100,F33)-IF(ISTEXT(E33),_xlfn.NUMBERVALUE(SUBSTITUTE(E33,"%",""),",",".")/100,E33)>=0,"▲","▼")&TEXT(ABS(IF(ISTEXT(F33),_xlfn.NUMBERVALUE(SUBSTITUTE(F33,"%",""),",",".")/100,F33)-IF(ISTEXT(E33),_xlfn.NUMBERVALUE(SUBSTITUTE(E33,"%",""),",",".")/100,E33))*100,"0,0")&" pp","NM") -> ▼0,1 pp | L33: =IFERROR(IF(IF(ISTEXT(G33),_xlfn.NUMBERVALUE(SUBSTITUTE(G33,"%",""),",",".")/100,G33)-IF(ISTEXT(F33),_xlfn.NUMBERVALUE(SUBSTITUTE(F33,"%",""),",",".")/100,F33)>=0,"▲","▼")&TEXT(ABS(IF(ISTEXT(G33),_xlfn.NUMBERVALUE(SUBSTITUTE(G33,"%",""),",",".")/100,G33)-IF(ISTEXT(F33),_xlfn.NUMBERVALUE(SUBSTITUTE(F33,"%",""),",",".")/100,F33))*100,"0,0")&" pp","NM") -> ▼2,1 pp | U33: Total Cost to Revenue | V33: 61,8% | W33: 0.584 | X33: 57,0% | Y33: 0.552 | Z33: 55,1% | AA33: 53,0% | AB33: =IFERROR(IF(IF(ISTEXT(W33),_xlfn.NUMBERVALUE(SUBSTITUTE(W33,"%",""),",",".")/100,W33)-IF(ISTEXT(V33),_xlfn.NUMBERVALUE(SUBSTITUTE(V33,"%",""),",",".")/100,V33)>=0,"▲","▼")&TEXT(ABS(IF(ISTEXT(W33),_xlfn.NUMBERVALUE(SUBSTITUTE(W33,"%",""),",",".")/100,W33)-IF(ISTEXT(V33),_xlfn.NUMBERVALUE(SUBSTITUTE(V33,"%",""),",",".")/100,V33))*100,"0,0")&" pp","NM") -> ▼3,4 pp | AC33: =IFERROR(IF(IF(ISTEXT(Y33),_xlfn.NUMBERVALUE(SUBSTITUTE(Y33,"%",""),",",".")/100,Y33)-IF(ISTEXT(W33),_xlfn.NUMBERVALUE(SUBSTITUTE(W33,"%",""),",",".")/100,W33)>=0,"▲","▼")&TEXT(ABS(IF(ISTEXT(Y33),_xlfn.NUMBERVALUE(SUBSTITUTE(Y33,"%",""),",",".")/100,Y33)-IF(ISTEXT(W33),_xlfn.NUMBERVALUE(SUBSTITUTE(W33,"%",""),",",".")/100,W33))*100,"0,0")&" pp","NM") -> ▼3,2 pp | AD33: =IFERROR(IF(IF(ISTEXT(Y33),_xlfn.NUMBERVALUE(SUBSTITUTE(Y33,"%",""),",",".")/100,Y33)-IF(ISTEXT(X33),_xlfn.NUMBERVALUE(SUBSTITUTE(X33,"%",""),",",".")/100,X33)>=0,"▲","▼")&TEXT(ABS(IF(ISTEXT(Y33),_xlfn.NUMBERVALUE(SUBSTITUTE(Y33,"%",""),",",".")/100,Y33)-IF(ISTEXT(X33),_xlfn.NUMBERVALUE(SUBSTITUTE(X33,"%",""),",",".")/100,X33))*100,"0,0")&" pp","NM") -> ▼1,8 pp | AE33: =IFERROR(IF(IF(ISTEXT(Z33),_xlfn.NUMBERVALUE(SUBSTITUTE(Z33,"%",""),",",".")/100,Z33)-IF(ISTEXT(Y33),_xlfn.NUMBERVALUE(SUBSTITUTE(Y33,"%",""),",",".")/100,Y33)>=0,"▲","▼")&TEXT(ABS(IF(ISTEXT(Z33),_xlfn.NUMBERVALUE(SUBSTITUTE(Z33,"%",""),",",".")/100,Z33)-IF(ISTEXT(Y33),_xlfn.NUMBERVALUE(SUBSTITUTE(Y33,"%",""),",",".")/100,Y33))*100,"0,0")&" pp","NM") -> ▼0,1 pp | AF33: =IFERROR(IF(IF(ISTEXT(AA33),_xlfn.NUMBERVALUE(SUBSTITUTE(AA33,"%",""),",",".")/100,AA33)-IF(ISTEXT(Z33),_xlfn.NUMBERVALUE(SUBSTITUTE(Z33,"%",""),",",".")/100,Z33)>=0,"▲","▼")&TEXT(ABS(IF(ISTEXT(AA33),_xlfn.NUMBERVALUE(SUBSTITUTE(AA33,"%",""),",",".")/100,AA33)-IF(ISTEXT(Z33),_xlfn.NUMBERVALUE(SUBSTITUTE(Z33,"%",""),",",".")/100,Z33))*100,"0,0")&" pp","NM") -> ▼2,1 pp
A34: EBITDA Margin | B34: 38,3% | C34: 0.416 | D34: 43,0% | E34: 0.448 | F34: 44,9% | G34: 47,0% | H34: =IFERROR(IF(IF(ISTEXT(C34),_xlfn.NUMBERVALUE(SUBSTITUTE(C34,"%",""),",",".")/100,C34)-IF(ISTEXT(B34),_xlfn.NUMBERVALUE(SUBSTITUTE(B34,"%",""),",",".")/100,B34)>=0,"▲","▼")&TEXT(ABS(IF(ISTEXT(C34),_xlfn.NUMBERVALUE(SUBSTITUTE(C34,"%",""),",",".")/100,C34)-IF(ISTEXT(B34),_xlfn.NUMBERVALUE(SUBSTITUTE(B34,"%",""),",",".")/100,B34))*100,"0,0")&" pp","NM") -> ▲3,3 pp | I34: =IFERROR(IF(IF(ISTEXT(E34),_xlfn.NUMBERVALUE(SUBSTITUTE(E34,"%",""),",",".")/100,E34)-IF(ISTEXT(C34),_xlfn.NUMBERVALUE(SUBSTITUTE(C34,"%",""),",",".")/100,C34)>=0,"▲","▼")&TEXT(ABS(IF(ISTEXT(E34),_xlfn.NUMBERVALUE(SUBSTITUTE(E34,"%",""),",",".")/100,E34)-IF(ISTEXT(C34),_xlfn.NUMBERVALUE(SUBSTITUTE(C34,"%",""),",",".")/100,C34))*100,"0,0")&" pp","NM") -> ▲3,2 pp | J34: =IFERROR(IF(IF(ISTEXT(E34),_xlfn.NUMBERVALUE(SUBSTITUTE(E34,"%",""),",",".")/100,E34)-IF(ISTEXT(D34),_xlfn.NUMBERVALUE(SUBSTITUTE(D34,"%",""),",",".")/100,D34)>=0,"▲","▼")&TEXT(ABS(IF(ISTEXT(E34),_xlfn.NUMBERVALUE(SUBSTITUTE(E34,"%",""),",",".")/100,E34)-IF(ISTEXT(D34),_xlfn.NUMBERVALUE(SUBSTITUTE(D34,"%",""),",",".")/100,D34))*100,"0,0")&" pp","NM") -> ▲1,8 pp | K34: =IFERROR(IF(IF(ISTEXT(F34),_xlfn.NUMBERVALUE(SUBSTITUTE(F34,"%",""),",",".")/100,F34)-IF(ISTEXT(E34),_xlfn.NUMBERVALUE(SUBSTITUTE(E34,"%",""),",",".")/100,E34)>=0,"▲","▼")&TEXT(ABS(IF(ISTEXT(F34),_xlfn.NUMBERVALUE(SUBSTITUTE(F34,"%",""),",",".")/100,F34)-IF(ISTEXT(E34),_xlfn.NUMBERVALUE(SUBSTITUTE(E34,"%",""),",",".")/100,E34))*100,"0,0")&" pp","NM") -> ▲0,1 pp | L34: =IFERROR(IF(IF(ISTEXT(G34),_xlfn.NUMBERVALUE(SUBSTITUTE(G34,"%",""),",",".")/100,G34)-IF(ISTEXT(F34),_xlfn.NUMBERVALUE(SUBSTITUTE(F34,"%",""),",",".")/100,F34)>=0,"▲","▼")&TEXT(ABS(IF(ISTEXT(G34),_xlfn.NUMBERVALUE(SUBSTITUTE(G34,"%",""),",",".")/100,G34)-IF(ISTEXT(F34),_xlfn.NUMBERVALUE(SUBSTITUTE(F34,"%",""),",",".")/100,F34))*100,"0,0")&" pp","NM") -> ▲2,1 pp | U34: EBITDA Margin | V34: 38,3% | W34: 0.416 | X34: 43,0% | Y34: 0.448 | Z34: 44,9% | AA34: 47,0% | AB34: =IFERROR(IF(IF(ISTEXT(W34),_xlfn.NUMBERVALUE(SUBSTITUTE(W34,"%",""),",",".")/100,W34)-IF(ISTEXT(V34),_xlfn.NUMBERVALUE(SUBSTITUTE(V34,"%",""),",",".")/100,V34)>=0,"▲","▼")&TEXT(ABS(IF(ISTEXT(W34),_xlfn.NUMBERVALUE(SUBSTITUTE(W34,"%",""),",",".")/100,W34)-IF(ISTEXT(V34),_xlfn.NUMBERVALUE(SUBSTITUTE(V34,"%",""),",",".")/100,V34))*100,"0,0")&" pp","NM") -> ▲3,3 pp | AC34: =IFERROR(IF(IF(ISTEXT(Y34),_xlfn.NUMBERVALUE(SUBSTITUTE(Y34,"%",""),",",".")/100,Y34)-IF(ISTEXT(W34),_xlfn.NUMBERVALUE(SUBSTITUTE(W34,"%",""),",",".")/100,W34)>=0,"▲","▼")&TEXT(ABS(IF(ISTEXT(Y34),_xlfn.NUMBERVALUE(SUBSTITUTE(Y34,"%",""),",",".")/100,Y34)-IF(ISTEXT(W34),_xlfn.NUMBERVALUE(SUBSTITUTE(W34,"%",""),",",".")/100,W34))*100,"0,0")&" pp","NM") -> ▲3,2 pp | AD34: =IFERROR(IF(IF(ISTEXT(Y34),_xlfn.NUMBERVALUE(SUBSTITUTE(Y34,"%",""),",",".")/100,Y34)-IF(ISTEXT(X34),_xlfn.NUMBERVALUE(SUBSTITUTE(X34,"%",""),",",".")/100,X34)>=0,"▲","▼")&TEXT(ABS(IF(ISTEXT(Y34),_xlfn.NUMBERVALUE(SUBSTITUTE(Y34,"%",""),",",".")/100,Y34)-IF(ISTEXT(X34),_xlfn.NUMBERVALUE(SUBSTITUTE(X34,"%",""),",",".")/100,X34))*100,"0,0")&" pp","NM") -> ▲1,8 pp | AE34: =IFERROR(IF(IF(ISTEXT(Z34),_xlfn.NUMBERVALUE(SUBSTITUTE(Z34,"%",""),",",".")/100,Z34)-IF(ISTEXT(Y34),_xlfn.NUMBERVALUE(SUBSTITUTE(Y34,"%",""),",",".")/100,Y34)>=0,"▲","▼")&TEXT(ABS(IF(ISTEXT(Z34),_xlfn.NUMBERVALUE(SUBSTITUTE(Z34,"%",""),",",".")/100,Z34)-IF(ISTEXT(Y34),_xlfn.NUMBERVALUE(SUBSTITUTE(Y34,"%",""),",",".")/100,Y34))*100,"0,0")&" pp","NM") -> ▲0,1 pp | AF34: =IFERROR(IF(IF(ISTEXT(AA34),_xlfn.NUMBERVALUE(SUBSTITUTE(AA34,"%",""),",",".")/100,AA34)-IF(ISTEXT(Z34),_xlfn.NUMBERVALUE(SUBSTITUTE(Z34,"%",""),",",".")/100,Z34)>=0,"▲","▼")&TEXT(ABS(IF(ISTEXT(AA34),_xlfn.NUMBERVALUE(SUBSTITUTE(AA34,"%",""),",",".")/100,AA34)-IF(ISTEXT(Z34),_xlfn.NUMBERVALUE(SUBSTITUTE(Z34,"%",""),",",".")/100,Z34))*100,"0,0")&" pp","NM") -> ▲2,1 pp
A35: EBIT Margin | B35: 12,3% | C35: 0.164 | D35: 18,3% | E35: 0.216 | F35: 18,7% | G35: 19,4% | H35: =IFERROR(IF(IF(ISTEXT(C35),_xlfn.NUMBERVALUE(SUBSTITUTE(C35,"%",""),",",".")/100,C35)-IF(ISTEXT(B35),_xlfn.NUMBERVALUE(SUBSTITUTE(B35,"%",""),",",".")/100,B35)>=0,"▲","▼")&TEXT(ABS(IF(ISTEXT(C35),_xlfn.NUMBERVALUE(SUBSTITUTE(C35,"%",""),",",".")/100,C35)-IF(ISTEXT(B35),_xlfn.NUMBERVALUE(SUBSTITUTE(B35,"%",""),",",".")/100,B35))*100,"0,0")&" pp","NM") -> ▲4,1 pp | I35: =IFERROR(IF(IF(ISTEXT(E35),_xlfn.NUMBERVALUE(SUBSTITUTE(E35,"%",""),",",".")/100,E35)-IF(ISTEXT(C35),_xlfn.NUMBERVALUE(SUBSTITUTE(C35,"%",""),",",".")/100,C35)>=0,"▲","▼")&TEXT(ABS(IF(ISTEXT(E35),_xlfn.NUMBERVALUE(SUBSTITUTE(E35,"%",""),",",".")/100,E35)-IF(ISTEXT(C35),_xlfn.NUMBERVALUE(SUBSTITUTE(C35,"%",""),",",".")/100,C35))*100,"0,0")&" pp","NM") -> ▲5,2 pp | J35: =IFERROR(IF(IF(ISTEXT(E35),_xlfn.NUMBERVALUE(SUBSTITUTE(E35,"%",""),",",".")/100,E35)-IF(ISTEXT(D35),_xlfn.NUMBERVALUE(SUBSTITUTE(D35,"%",""),",",".")/100,D35)>=0,"▲","▼")&TEXT(ABS(IF(ISTEXT(E35),_xlfn.NUMBERVALUE(SUBSTITUTE(E35,"%",""),",",".")/100,E35)-IF(ISTEXT(D35),_xlfn.NUMBERVALUE(SUBSTITUTE(D35,"%",""),",",".")/100,D35))*100,"0,0")&" pp","NM") -> ▲3,3 pp | K35: =IFERROR(IF(IF(ISTEXT(F35),_xlfn.NUMBERVALUE(SUBSTITUTE(F35,"%",""),",",".")/100,F35)-IF(ISTEXT(E35),_xlfn.NUMBERVALUE(SUBSTITUTE(E35,"%",""),",",".")/100,E35)>=0,"▲","▼")&TEXT(ABS(IF(ISTEXT(F35),_xlfn.NUMBERVALUE(SUBSTITUTE(F35,"%",""),",",".")/100,F35)-IF(ISTEXT(E35),_xlfn.NUMBERVALUE(SUBSTITUTE(E35,"%",""),",",".")/100,E35))*100,"0,0")&" pp","NM") -> ▼2,9 pp | L35: =IFERROR(IF(IF(ISTEXT(G35),_xlfn.NUMBERVALUE(SUBSTITUTE(G35,"%",""),",",".")/100,G35)-IF(ISTEXT(F35),_xlfn.NUMBERVALUE(SUBSTITUTE(F35,"%",""),",",".")/100,F35)>=0,"▲","▼")&TEXT(ABS(IF(ISTEXT(G35),_xlfn.NUMBERVALUE(SUBSTITUTE(G35,"%",""),",",".")/100,G35)-IF(ISTEXT(F35),_xlfn.NUMBERVALUE(SUBSTITUTE(F35,"%",""),",",".")/100,F35))*100,"0,0")&" pp","NM") -> ▲0,7 pp | U35: EBIT Margin | V35: 12,3% | W35: 0.164 | X35: 18,3% | Y35: 0.216 | Z35: 18,7% | AA35: 19,4% | AB35: =IFERROR(IF(IF(ISTEXT(W35),_xlfn.NUMBERVALUE(SUBSTITUTE(W35,"%",""),",",".")/100,W35)-IF(ISTEXT(V35),_xlfn.NUMBERVALUE(SUBSTITUTE(V35,"%",""),",",".")/100,V35)>=0,"▲","▼")&TEXT(ABS(IF(ISTEXT(W35),_xlfn.NUMBERVALUE(SUBSTITUTE(W35,"%",""),",",".")/100,W35)-IF(ISTEXT(V35),_xlfn.NUMBERVALUE(SUBSTITUTE(V35,"%",""),",",".")/100,V35))*100,"0,0")&" pp","NM") -> ▲4,1 pp | AC35: =IFERROR(IF(IF(ISTEXT(Y35),_xlfn.NUMBERVALUE(SUBSTITUTE(Y35,"%",""),",",".")/100,Y35)-IF(ISTEXT(W35),_xlfn.NUMBERVALUE(SUBSTITUTE(W35,"%",""),",",".")/100,W35)>=0,"▲","▼")&TEXT(ABS(IF(ISTEXT(Y35),_xlfn.NUMBERVALUE(SUBSTITUTE(Y35,"%",""),",",".")/100,Y35)-IF(ISTEXT(W35),_xlfn.NUMBERVALUE(SUBSTITUTE(W35,"%",""),",",".")/100,W35))*100,"0,0")&" pp","NM") -> ▲5,2 pp | AD35: =IFERROR(IF(IF(ISTEXT(Y35),_xlfn.NUMBERVALUE(SUBSTITUTE(Y35,"%",""),",",".")/100,Y35)-IF(ISTEXT(X35),_xlfn.NUMBERVALUE(SUBSTITUTE(X35,"%",""),",",".")/100,X35)>=0,"▲","▼")&TEXT(ABS(IF(ISTEXT(Y35),_xlfn.NUMBERVALUE(SUBSTITUTE(Y35,"%",""),",",".")/100,Y35)-IF(ISTEXT(X35),_xlfn.NUMBERVALUE(SUBSTITUTE(X35,"%",""),",",".")/100,X35))*100,"0,0")&" pp","NM") -> ▲3,3 pp | AE35: =IFERROR(IF(IF(ISTEXT(Z35),_xlfn.NUMBERVALUE(SUBSTITUTE(Z35,"%",""),",",".")/100,Z35)-IF(ISTEXT(Y35),_xlfn.NUMBERVALUE(SUBSTITUTE(Y35,"%",""),",",".")/100,Y35)>=0,"▲","▼")&TEXT(ABS(IF(ISTEXT(Z35),_xlfn.NUMBERVALUE(SUBSTITUTE(Z35,"%",""),",",".")/100,Z35)-IF(ISTEXT(Y35),_xlfn.NUMBERVALUE(SUBSTITUTE(Y35,"%",""),",",".")/100,Y35))*100,"0,0")&" pp","NM") -> ▼2,9 pp | AF35: =IFERROR(IF(IF(ISTEXT(AA35),_xlfn.NUMBERVALUE(SUBSTITUTE(AA35,"%",""),",",".")/100,AA35)-IF(ISTEXT(Z35),_xlfn.NUMBERVALUE(SUBSTITUTE(Z35,"%",""),",",".")/100,Z35)>=0,"▲","▼")&TEXT(ABS(IF(ISTEXT(AA35),_xlfn.NUMBERVALUE(SUBSTITUTE(AA35,"%",""),",",".")/100,AA35)-IF(ISTEXT(Z35),_xlfn.NUMBERVALUE(SUBSTITUTE(Z35,"%",""),",",".")/100,Z35))*100,"0,0")&" pp","NM") -> ▲0,7 pp
A36: PAT Margin | B36: 3,2% | C36: 0.075 | D36: 7,5% | E36: 0.103 | F36: 8,4% | G36: 9,6% | H36: =IFERROR(IF(IF(ISTEXT(C36),_xlfn.NUMBERVALUE(SUBSTITUTE(C36,"%",""),",",".")/100,C36)-IF(ISTEXT(B36),_xlfn.NUMBERVALUE(SUBSTITUTE(B36,"%",""),",",".")/100,B36)>=0,"▲","▼")&TEXT(ABS(IF(ISTEXT(C36),_xlfn.NUMBERVALUE(SUBSTITUTE(C36,"%",""),",",".")/100,C36)-IF(ISTEXT(B36),_xlfn.NUMBERVALUE(SUBSTITUTE(B36,"%",""),",",".")/100,B36))*100,"0,0")&" pp","NM") -> ▲4,3 pp | I36: =IFERROR(IF(IF(ISTEXT(E36),_xlfn.NUMBERVALUE(SUBSTITUTE(E36,"%",""),",",".")/100,E36)-IF(ISTEXT(C36),_xlfn.NUMBERVALUE(SUBSTITUTE(C36,"%",""),",",".")/100,C36)>=0,"▲","▼")&TEXT(ABS(IF(ISTEXT(E36),_xlfn.NUMBERVALUE(SUBSTITUTE(E36,"%",""),",",".")/100,E36)-IF(ISTEXT(C36),_xlfn.NUMBERVALUE(SUBSTITUTE(C36,"%",""),",",".")/100,C36))*100,"0,0")&" pp","NM") -> ▲2,8 pp | J36: =IFERROR(IF(IF(ISTEXT(E36),_xlfn.NUMBERVALUE(SUBSTITUTE(E36,"%",""),",",".")/100,E36)-IF(ISTEXT(D36),_xlfn.NUMBERVALUE(SUBSTITUTE(D36,"%",""),",",".")/100,D36)>=0,"▲","▼")&TEXT(ABS(IF(ISTEXT(E36),_xlfn.NUMBERVALUE(SUBSTITUTE(E36,"%",""),",",".")/100,E36)-IF(ISTEXT(D36),_xlfn.NUMBERVALUE(SUBSTITUTE(D36,"%",""),",",".")/100,D36))*100,"0,0")&" pp","NM") -> ▲2,8 pp | K36: =IFERROR(IF(IF(ISTEXT(F36),_xlfn.NUMBERVALUE(SUBSTITUTE(F36,"%",""),",",".")/100,F36)-IF(ISTEXT(E36),_xlfn.NUMBERVALUE(SUBSTITUTE(E36,"%",""),",",".")/100,E36)>=0,"▲","▼")&TEXT(ABS(IF(ISTEXT(F36),_xlfn.NUMBERVALUE(SUBSTITUTE(F36,"%",""),",",".")/100,F36)-IF(ISTEXT(E36),_xlfn.NUMBERVALUE(SUBSTITUTE(E36,"%",""),",",".")/100,E36))*100,"0,0")&" pp","NM") -> ▼1,9 pp | L36: =IFERROR(IF(IF(ISTEXT(G36),_xlfn.NUMBERVALUE(SUBSTITUTE(G36,"%",""),",",".")/100,G36)-IF(ISTEXT(F36),_xlfn.NUMBERVALUE(SUBSTITUTE(F36,"%",""),",",".")/100,F36)>=0,"▲","▼")&TEXT(ABS(IF(ISTEXT(G36),_xlfn.NUMBERVALUE(SUBSTITUTE(G36,"%",""),",",".")/100,G36)-IF(ISTEXT(F36),_xlfn.NUMBERVALUE(SUBSTITUTE(F36,"%",""),",",".")/100,F36))*100,"0,0")&" pp","NM") -> ▲1,2 pp | U36: PAT Margin | V36: 3,2% | W36: 0.075 | X36: 7,5% | Y36: 0.103 | Z36: 8,4% | AA36: 9,6% | AB36: =IFERROR(IF(IF(ISTEXT(W36),_xlfn.NUMBERVALUE(SUBSTITUTE(W36,"%",""),",",".")/100,W36)-IF(ISTEXT(V36),_xlfn.NUMBERVALUE(SUBSTITUTE(V36,"%",""),",",".")/100,V36)>=0,"▲","▼")&TEXT(ABS(IF(ISTEXT(W36),_xlfn.NUMBERVALUE(SUBSTITUTE(W36,"%",""),",",".")/100,W36)-IF(ISTEXT(V36),_xlfn.NUMBERVALUE(SUBSTITUTE(V36,"%",""),",",".")/100,V36))*100,"0,0")&" pp","NM") -> ▲4,3 pp | AC36: =IFERROR(IF(IF(ISTEXT(Y36),_xlfn.NUMBERVALUE(SUBSTITUTE(Y36,"%",""),",",".")/100,Y36)-IF(ISTEXT(W36),_xlfn.NUMBERVALUE(SUBSTITUTE(W36,"%",""),",",".")/100,W36)>=0,"▲","▼")&TEXT(ABS(IF(ISTEXT(Y36),_xlfn.NUMBERVALUE(SUBSTITUTE(Y36,"%",""),",",".")/100,Y36)-IF(ISTEXT(W36),_xlfn.NUMBERVALUE(SUBSTITUTE(W36,"%",""),",",".")/100,W36))*100,"0,0")&" pp","NM") -> ▲2,8 pp | AD36: =IFERROR(IF(IF(ISTEXT(Y36),_xlfn.NUMBERVALUE(SUBSTITUTE(Y36,"%",""),",",".")/100,Y36)-IF(ISTEXT(X36),_xlfn.NUMBERVALUE(SUBSTITUTE(X36,"%",""),",",".")/100,X36)>=0,"▲","▼")&TEXT(ABS(IF(ISTEXT(Y36),_xlfn.NUMBERVALUE(SUBSTITUTE(Y36,"%",""),",",".")/100,Y36)-IF(ISTEXT(X36),_xlfn.NUMBERVALUE(SUBSTITUTE(X36,"%",""),",",".")/100,X36))*100,"0,0")&" pp","NM") -> ▲2,8 pp | AE36: =IFERROR(IF(IF(ISTEXT(Z36),_xlfn.NUMBERVALUE(SUBSTITUTE(Z36,"%",""),",",".")/100,Z36)-IF(ISTEXT(Y36),_xlfn.NUMBERVALUE(SUBSTITUTE(Y36,"%",""),",",".")/100,Y36)>=0,"▲","▼")&TEXT(ABS(IF(ISTEXT(Z36),_xlfn.NUMBERVALUE(SUBSTITUTE(Z36,"%",""),",",".")/100,Z36)-IF(ISTEXT(Y36),_xlfn.NUMBERVALUE(SUBSTITUTE(Y36,"%",""),",",".")/100,Y36))*100,"0,0")&" pp","NM") -> ▼1,9 pp | AF36: =IFERROR(IF(IF(ISTEXT(AA36),_xlfn.NUMBERVALUE(SUBSTITUTE(AA36,"%",""),",",".")/100,AA36)-IF(ISTEXT(Z36),_xlfn.NUMBERVALUE(SUBSTITUTE(Z36,"%",""),",",".")/100,Z36)>=0,"▲","▼")&TEXT(ABS(IF(ISTEXT(AA36),_xlfn.NUMBERVALUE(SUBSTITUTE(AA36,"%",""),",",".")/100,AA36)-IF(ISTEXT(Z36),_xlfn.NUMBERVALUE(SUBSTITUTE(Z36,"%",""),",",".")/100,Z36))*100,"0,0")&" pp","NM") -> ▲1,2 pp
A37: Capex Intensity | B37: 16,1% | C37: =C28/C7 -> 0.21538748 | D37: 26,4% | E37: =E28/E7 -> 0.30380896 | F37: 21,3% | G37: 18,2% | H37: =IFERROR(IF(IF(ISTEXT(C37),_xlfn.NUMBERVALUE(SUBSTITUTE(C37,"%",""),",",".")/100,C37)-IF(ISTEXT(B37),_xlfn.NUMBERVALUE(SUBSTITUTE(B37,"%",""),",",".")/100,B37)>=0,"▲","▼")&TEXT(ABS(IF(ISTEXT(C37),_xlfn.NUMBERVALUE(SUBSTITUTE(C37,"%",""),",",".")/100,C37)-IF(ISTEXT(B37),_xlfn.NUMBERVALUE(SUBSTITUTE(B37,"%",""),",",".")/100,B37))*100,"0,0")&" pp","NM") -> ▲5,4 pp | I37: =IFERROR(IF(IF(ISTEXT(E37),_xlfn.NUMBERVALUE(SUBSTITUTE(E37,"%",""),",",".")/100,E37)-IF(ISTEXT(C37),_xlfn.NUMBERVALUE(SUBSTITUTE(C37,"%",""),",",".")/100,C37)>=0,"▲","▼")&TEXT(ABS(IF(ISTEXT(E37),_xlfn.NUMBERVALUE(SUBSTITUTE(E37,"%",""),",",".")/100,E37)-IF(ISTEXT(C37),_xlfn.NUMBERVALUE(SUBSTITUTE(C37,"%",""),",",".")/100,C37))*100,"0,0")&" pp","NM") -> ▲8,8 pp | J37: =IFERROR(IF(IF(ISTEXT(E37),_xlfn.NUMBERVALUE(SUBSTITUTE(E37,"%",""),",",".")/100,E37)-IF(ISTEXT(D37),_xlfn.NUMBERVALUE(SUBSTITUTE(D37,"%",""),",",".")/100,D37)>=0,"▲","▼")&TEXT(ABS(IF(ISTEXT(E37),_xlfn.NUMBERVALUE(SUBSTITUTE(E37,"%",""),",",".")/100,E37)-IF(ISTEXT(D37),_xlfn.NUMBERVALUE(SUBSTITUTE(D37,"%",""),",",".")/100,D37))*100,"0,0")&" pp","NM") -> ▲4,0 pp | K37: =IFERROR(IF(IF(ISTEXT(F37),_xlfn.NUMBERVALUE(SUBSTITUTE(F37,"%",""),",",".")/100,F37)-IF(ISTEXT(E37),_xlfn.NUMBERVALUE(SUBSTITUTE(E37,"%",""),",",".")/100,E37)>=0,"▲","▼")&TEXT(ABS(IF(ISTEXT(F37),_xlfn.NUMBERVALUE(SUBSTITUTE(F37,"%",""),",",".")/100,F37)-IF(ISTEXT(E37),_xlfn.NUMBERVALUE(SUBSTITUTE(E37,"%",""),",",".")/100,E37))*100,"0,0")&" pp","NM") -> ▼9,1 pp | L37: =IFERROR(IF(IF(ISTEXT(G37),_xlfn.NUMBERVALUE(SUBSTITUTE(G37,"%",""),",",".")/100,G37)-IF(ISTEXT(F37),_xlfn.NUMBERVALUE(SUBSTITUTE(F37,"%",""),",",".")/100,F37)>=0,"▲","▼")&TEXT(ABS(IF(ISTEXT(G37),_xlfn.NUMBERVALUE(SUBSTITUTE(G37,"%",""),",",".")/100,G37)-IF(ISTEXT(F37),_xlfn.NUMBERVALUE(SUBSTITUTE(F37,"%",""),",",".")/100,F37))*100,"0,0")&" pp","NM") -> ▼3,1 pp | U37: Capex Intensity | V37: 16,1% | W37: =W28/W7 -> 0.2152168 | X37: 26,4% | Y37: =Y28/Y7 -> 0.30356684 | Z37: 21,3% | AA37: 18,2% | AB37: =IFERROR(IF(IF(ISTEXT(W37),_xlfn.NUMBERVALUE(SUBSTITUTE(W37,"%",""),",",".")/100,W37)-IF(ISTEXT(V37),_xlfn.NUMBERVALUE(SUBSTITUTE(V37,"%",""),",",".")/100,V37)>=0,"▲","▼")&TEXT(ABS(IF(ISTEXT(W37),_xlfn.NUMBERVALUE(SUBSTITUTE(W37,"%",""),",",".")/100,W37)-IF(ISTEXT(V37),_xlfn.NUMBERVALUE(SUBSTITUTE(V37,"%",""),",",".")/100,V37))*100,"0,0")&" pp","NM") -> ▲5,4 pp | AC37: =IFERROR(IF(IF(ISTEXT(Y37),_xlfn.NUMBERVALUE(SUBSTITUTE(Y37,"%",""),",",".")/100,Y37)-IF(ISTEXT(W37),_xlfn.NUMBERVALUE(SUBSTITUTE(W37,"%",""),",",".")/100,W37)>=0,"▲","▼")&TEXT(ABS(IF(ISTEXT(Y37),_xlfn.NUMBERVALUE(SUBSTITUTE(Y37,"%",""),",",".")/100,Y37)-IF(ISTEXT(W37),_xlfn.NUMBERVALUE(SUBSTITUTE(W37,"%",""),",",".")/100,W37))*100,"0,0")&" pp","NM") -> ▲8,8 pp | AD37: =IFERROR(IF(IF(ISTEXT(Y37),_xlfn.NUMBERVALUE(SUBSTITUTE(Y37,"%",""),",",".")/100,Y37)-IF(ISTEXT(X37),_xlfn.NUMBERVALUE(SUBSTITUTE(X37,"%",""),",",".")/100,X37)>=0,"▲","▼")&TEXT(ABS(IF(ISTEXT(Y37),_xlfn.NUMBERVALUE(SUBSTITUTE(Y37,"%",""),",",".")/100,Y37)-IF(ISTEXT(X37),_xlfn.NUMBERVALUE(SUBSTITUTE(X37,"%",""),",",".")/100,X37))*100,"0,0")&" pp","NM") -> ▲4,0 pp | AE37: =IFERROR(IF(IF(ISTEXT(Z37),_xlfn.NUMBERVALUE(SUBSTITUTE(Z37,"%",""),",",".")/100,Z37)-IF(ISTEXT(Y37),_xlfn.NUMBERVALUE(SUBSTITUTE(Y37,"%",""),",",".")/100,Y37)>=0,"▲","▼")&TEXT(ABS(IF(ISTEXT(Z37),_xlfn.NUMBERVALUE(SUBSTITUTE(Z37,"%",""),",",".")/100,Z37)-IF(ISTEXT(Y37),_xlfn.NUMBERVALUE(SUBSTITUTE(Y37,"%",""),",",".")/100,Y37))*100,"0,0")&" pp","NM") -> ▼9,1 pp | AF37: =IFERROR(IF(IF(ISTEXT(AA37),_xlfn.NUMBERVALUE(SUBSTITUTE(AA37,"%",""),",",".")/100,AA37)-IF(ISTEXT(Z37),_xlfn.NUMBERVALUE(SUBSTITUTE(Z37,"%",""),",",".")/100,Z37)>=0,"▲","▼")&TEXT(ABS(IF(ISTEXT(AA37),_xlfn.NUMBERVALUE(SUBSTITUTE(AA37,"%",""),",",".")/100,AA37)-IF(ISTEXT(Z37),_xlfn.NUMBERVALUE(SUBSTITUTE(Z37,"%",""),",",".")/100,Z37))*100,"0,0")&" pp","NM") -> ▼3,1 pp
A39: 53

Sheet Conso
A1: Performance Summary | Consolidated (vs targets)
A3: Financials | B3: Full Year
A4: LC (Million) | B4: Act'24 | C4: Bud'25 | D4: 5+7 FC | E4: 8+4 FC | F4: Bud'26 | G4: Bud'27 | H4: Bud'28 | I4: 5+7 FC vs Act'24 | J4: 8+4 FC vs Act'24 | K4: 8+4 FC vs Bud'25 | L4: Bud'26 vs 8+4 FC | M4: Bud'27 vs Bud'26 | N4: Bud'28 vs Bud'27
A5: Total Revenue | B5: 310702 | C5: 338232 | D5: 326776 | E5: 322052 | F5: 357822 | G5: 407331 | H5: 466265 | I5: =D5/B5-1 -> 0.051734459 | J5: =E5/B5-1 -> 0.03653018 | K5: =E5/C5-1 -> -0.047836988 | L5: =F5/E5-1 -> 0.11106902 | M5: =G5/F5-1 -> 0.13836209 | N5: =H5/G5-1 -> 0.14468332
A6: Service Revenue | B6: 309987 | C6: 336047 | D6: 326187 | E6: 321295 | F6: 355649 | G6: 404453 | H6: 463320 | I6: =D6/B6-1 -> 0.052260256 | J6: =E6/B6-1 -> 0.036478949 | K6: =E6/C6-1 -> -0.043898621 | L6: =F6/E6-1 -> 0.10692354 | M6: =G6/F6-1 -> 0.13722519 | N6: =H6/G6-1 -> 0.1455472
A7: Total Voice Revenue | B7: 129748 | C7: 123813 | D7: 128584 | E7: 124651 | F7: 120217 | G7: 115792 | H7: 111780 | I7: =D7/B7-1 -> -0.0089712366 | J7: =E7/B7-1 -> -0.039283843 | K7: =E7/C7-1 -> 0.0067682715 | L7: =F7/E7-1 -> -0.035571315 | M7: =G7/F7-1 -> -0.036808438 | N7: =H7/G7-1 -> -0.034648335
A8: Total Data Revenue | B8: 109803 | C8: 134308 | D8: 127371 | E8: 132376 | F8: 162282 | G8: 201230 | H8: 245526 | I8: =D8/B8-1 -> 0.15999563 | J8: =E8/B8-1 -> 0.20557726 | K8: =E8/C8-1 -> -0.014384847 | L8: =F8/E8-1 -> 0.22591708 | M8: =G8/F8-1 -> 0.24000197 | N8: =H8/G8-1 -> 0.22012622
A9: Digital Revenue | B9: 8305 | C9: 10797 | D9: 5999 | E9: 5833 | F9: 6469 | G9: 7452 | H9: 8582 | I9: =D9/B9-1 -> -0.27766406 | J9: =E9/B9-1 -> -0.29765202 | K9: =E9/C9-1 -> -0.45975734 | L9: =F9/E9-1 -> 0.1090348 | M9: =G9/F9-1 -> 0.15195548 | N9: =H9/G9-1 -> 0.15163714
A10: FinTech | B10: 30080 | C10: 34258 | D10: 32511 | E10: 27202 | F10: 29489 | G10: 34978 | H10: 41837 | I10: =D10/B10-1 -> 0.080817819 | J10: =E10/B10-1 -> -0.095678191 | K10: =E10/C10-1 -> -0.20596649 | L10: =F10/E10-1 -> 0.0840747 | M10: =G10/F10-1 -> 0.1861372 | N10: =H10/G10-1 -> 0.19609469
A11: SMS Revenue | B11: 3405 | C11: 3346 | D11: 2302 | E11: 2858 | F11: 2552 | G11: 2257 | H11: 1981 | I11: =D11/B11-1 -> -0.32393539 | J11: =E11/B11-1 -> -0.16064611 | K11: =E11/C11-1 -> -0.14584579 | L11: =F11/E11-1 -> -0.10706788 | M11: =G11/F11-1 -> -0.11559561 | N11: =H11/G11-1 -> -0.12228622
A12: Total Wholesale | B12: 6140 | C12: 6234 | D12: 8400 | E12: 6413 | F12: 6610 | G12: 7111 | H12: 7844 | I12: =D12/B12-1 -> 0.36807818 | J12: =E12/B12-1 -> 0.044462541 | K12: =E12/C12-1 -> 0.028713507 | L12: =F12/E12-1 -> 0.030718852 | M12: =G12/F12-1 -> 0.075794251 | N12: =H12/G12-1 -> 0.10307974
A13: Fixed Connectivity | B13: 14624 | C13: 16268 | D13: 14669 | E13: 14534 | F13: 17895 | G13: 22369 | H13: 28409 | I13: =D13/B13-1 -> 0.0030771335 | J13: =E13/B13-1 -> -0.006154267 | K13: =E13/C13-1 -> -0.10658962 | L13: =F13/E13-1 -> 0.23125086 | M13: =G13/F13-1 -> 0.25001397 | N13: =H13/G13-1 -> 0.27001654
A14: Converged Service Revenue | B14: 6538 | C14: 7023 | D14: 7044 | E14: 7349 | F14: 10134 | G14: 13264 | H14: 17362 | I14: =D14/B14-1 -> 0.077393698 | J14: =E14/B14-1 -> 0.12404405 | K14: =E14/C14-1 -> 0.046418909 | L14: =F14/E14-1 -> 0.37896312 | M14: =G14/F14-1 -> 0.30886126 | N14: =H14/G14-1 -> 0.30895657
A15: Non-service revenue | B15: 715 | C15: 2185 | D15: 590 | E15: 757 | F15: 2173 | G15: 2878 | H15: 2945 | I15: =D15/B15-1 -> -0.17482517 | J15: =E15/B15-1 -> 0.058741259 | K15: =E15/C15-1 -> -0.65354691 | L15: =F15/E15-1 -> 1.8705416 | M15: =G15/F15-1 -> 0.32443626 | N15: =H15/G15-1 -> 0.023280056
A16: Cost of Sales | B16: 108619 | C16: 105330 | D16: 102831 | E16: 101212 | F16: 106946 | G16: 119629 | H16: 131739 | I16: =D16/B16-1 -> -0.053287178 | J16: =E16/B16-1 -> -0.068192489 | K16: =E16/C16-1 -> -0.039096174 | L16: =F16/E16-1 -> 0.056653361 | M16: =G16/F16-1 -> 0.11859256 | N16: =H16/G16-1 -> 0.10122963
... A19: EBITDA | B19: 102173 | C19: 127724 | D19: 120773 | E19: 116930 | F19: 139711 | G19: 167551 | H19: 203847 | I19: =D19/B19-1 -> 0.18204418 | J19: =E19/B19-1 -> 0.1444315 | K19: =E19/C19-1 -> -0.08451035 | L19: =F19/E19-1 -> 0.19482596 | M19: =G19/F19-1 -> 0.19926849 | N19: =H19/G19-1 -> 0.21662658
A20: Depreciation & Amortisation | B20: 73955 | C20: 77129 | D20: 78028 | E20: 76999 | F20: 82358 | G20: 99604 | H20: 119524 | I20: 0 | J20: =E20/B20-1 -> 0.041160165 | K20: =E20/C20-1 -> -0.0016854879 | L20: =F20/E20-1 -> 0.069598306 | M20: =G20/F20-1 -> 0.20940285 | N20: =H20/G20-1 -> 0.19999197
A21: EBIT | B21: 28218 | C21: 50595 | D21: 42745 | E21: 39931 | F21: 57354 | G21: 67948 | H21: 84323 | I21: 0 | J21: =E21/B21-1 -> 0.41508966 | K21: =E21/C21-1 -> -0.21077182 | L21: =F21/E21-1 -> 0.43632767 | M21: =G21/F21-1 -> 0.18471249 | N21: =H21/G21-1 -> 0.24099311
A22: Finance Costs | B22: 18579 | C22: 19052 | D22: 19941 | E22: 20523 | F22: 22251 | G22: 21258 | H22: 19623 | I22: 0 | J22: =E22/B22-1 -> 0.10463426 | K22: =E22/C22-1 -> 0.077209742 | L22: =F22/E22-1 -> 0.084198217 | M22: =G22/F22-1 -> -0.044627208 | N22: =H22/G22-1 -> -0.076912221
A23: Taxation | B23: 5084 | C23: 11161 | D23: 8256 | E23: 6674 | F23: 12751 | G23: 16868 | H23: 23089 | I23: 0 | J23: =E23/B23-1 -> 0.31274587 | K23: =E23/C23-1 -> -0.40202491 | L23: =F23/E23-1 -> 0.9105484 | M23: =G23/F23-1 -> 0.32287664 | N23: =H23/G23-1 -> 0.36880484
A24: Profit (Loss) after taxation | B24: 4556 | C24: 20382 | D24: 14549 | E24: 12733 | F24: 22352 | G24: 29821 | H24: 41611 | I24: 0 | J24: =E24/B24-1 -> 1.7947761 | K24: =E24/C24-1 -> -0.37528211 | L24: =F24/E24-1 -> 0.75543862 | M24: =G24/F24-1 -> 0.33415354 | N24: =H24/G24-1 -> 0.39535898
A25: Capex LC | B25: 46278 | C25: 52422 | D25: 66216 | E25: 66216 | F25: 87858 | G25: 80533 | H25: 79002 | I25: 0 | J25: =E25/B25-1 -> 0.43083106 | K25: =E25/C25-1 -> 0.2631338 | L25: =F25/E25-1 -> 0.32683943 | M25: =G25/F25-1 -> -0.08337317 | N25: =H25/G25-1 -> -0.01901084
A27: Contribution Margin | B27: =B17/B5 -> 0.65040779 | C27: =C17/C5 -> 0.68858653 | D27: =D17/D5 -> 0.68531655 | E27: =E17/E5 -> 0.68572467 | F27: =F17/F5 -> 0.70112235 | G27: =G17/G5 -> 0.7063101 | H27: =H17/H5 -> 0.7174611 | I27: =(D27-B27)*100 -> 3.4908761 | J27: =(E27-B27)*100 -> 3.5316879 | K27: =(E27-C27)*100 -> -0.28618667 | L27: =(F27-E27)*100 -> 1.539768 | M27: =(G27-F27)*100 -> 0.51877559 | N27: =(H27-G27)*100 -> 1.1150999
A28: COS to Revenue | B28: =B16/B5 -> 0.34959221 | C28: =C16/C5 -> 0.31141347 | D28: =D16/D5 -> 0.31468345 | E28: =E16/E5 -> 0.31427223 | F28: =F16/F5 -> 0.29888045 | G28: =G16/G5 -> 0.2936899 | H28: =H16/H5 -> 0.28254104 | I28: =(D28-B28)*100 -> -3.4908761 | J28: =(E28-B28)*100 -> -3.5319984 | K28: =(E28-C28)*100 -> 0.28587617 | L28: =(F28-E28)*100 -> -1.539178 | M28: =(G28-F28)*100 -> -0.51905506 | N28: =(H28-G28)*100 -> -1.1148854
A29: Opex to Revenue | B29: =B18/B5 -> 0.32163938 | C29: =C18/C5 -> 0.31193678 | D29: =D18/D5 -> 0.31474466 | E29: =E18/E5 -> 0.32268391 | F29: =F18/F5 -> 0.31067123 | G29: =G18/G5 -> 0.29496896 | H29: =H18/H5 -> 0.28026766 | I29: =(D29-B29)*100 -> -0.68947275 | J29: =(E29-B29)*100 -> 0.104453 | K29: =(E29-C29)*100 -> 1.0747137 | L29: =(F29-E29)*100 -> -1.2012687 | M29: =(G29-F29)*100 -> -1.5702271 | N29: =(H29-G29)*100 -> -1.4701298
A30: Total Cost to Revenue | B30: =(B16+B18)/B5 -> 0.6712316 | C30: =(C16+C18)/C5 -> 0.62335024 | D30: =(D16+D18)/D5 -> 0.62942811 | E30: =(E16+E18)/E5 -> 0.63695614 | F30: =(F16+F18)/F5 -> 0.60955168 | G30: =(G16+G18)/G5 -> 0.58865885 | H30: =(H16+H18)/H5 -> 0.5628087 | I30: =(D30-B30)*100 -> -4.1803488 | J30: =(E30-B30)*100 -> -3.4275454 | K30: =(E30-C30)*100 -> 1.3605899 | L30: =(F30-E30)*100 -> -2.7404467 | M30: =(G30-F30)*100 -> -2.0892822 | N30: =(H30-G30)*100 -> -2.5850152
A31: EBITDA Margin | B31: =B19/B5 -> 0.32884565 | C31: =C19/C5 -> 0.37762246 | D31: =D19/D5 -> 0.36958957 | E31: =E19/E5 -> 0.36307801 | F31: =F19/F5 -> 0.39044832 | G31: =G19/G5 -> 0.41133869 | H31: =H19/H5 -> 0.4371913 | I31: =(D31-B31)*100 -> 4.074392 | J31: =(E31-B31)*100 -> 3.4232366 | K31: =(E31-C31)*100 -> -1.4544448 | L31: =(F31-E31)*100 -> 2.7370311 | M31: =(G31-F31)*100 -> 2.0890367 | N31: =(H31-G31)*100 -> 2.5852607
A32: EBIT Margin | B32: =B21/B5 -> 0.090820143 | C32: =C21/C5 -> 0.14958667 | D32: =D21/D5 -> 0.13080826 | E32: =E21/E5 -> 0.12398929 | F32: =F21/F5 -> 0.1602864 | G32: =G21/G5 -> 0.16681274 | H32: =H21/H5 -> 0.1808478 | I32: 0 | J32: =(E32-B32)*100 -> 3.3169151 | K32: =(E32-C32)*100 -> -2.5597381 | L32: =(F32-E32)*100 -> 3.6297106 | M32: =(G32-F32)*100 -> 0.65263401 | N32: =(H32-G32)*100 -> 1.4035062
A33: PAT Margin | B33: =B24/B5 -> 0.014663568 | C33: =C24/C5 -> 0.060260413 | D33: =D24/D5 -> 0.044522854 | E33: =E24/E5 -> 0.039537093 | F33: =F24/F5 -> 0.062466813 | G33: =G24/G5 -> 0.07321073 | H33: =H24/H5 -> 0.089243242 | I33: 0 | J33: =(E33-B33)*100 -> 2.4873525 | K33: =(E33-C33)*100 -> -2.072332 | L33: =(F33-E33)*100 -> 2.292972 | M33: =(G33-F33)*100 -> 1.0743917 | N33: =(H33-G33)*100 -> 1.6032511

Sheet Adjustments
E1: ▲17,2% | G1: ▲6,3% | H1: ▲14,0%
B2: Key Assumptions
C3: 2024 | D3: 2025 | E3: 2026 | G3: 2027 | H3: 2028
B4: CA
B6: Remise | C6: -2382.5743 | D6: -38.750226 | E6: 0 | G6: 0 | H6: 0
B7: Comm Staff | C7: 298.612 | D7: 295.369 | E7: 0 | G7: 0 | H7: 0
B8: IFRS 15 & Others | C8: 30.047 | D8: -17.802 | E8: 0 | G8: 0 | H8: 0
A9: Rev | B9: CA | C9: -2053.9153 | D9: =(SUM(D6:D8)) -> 238.81677 | E9: =(+D9*1.17) -> 279.41563 | F9: 279.41563 | G9: =(E9*(1+6.9%)) -> 298.6953 | H9: =(G9*(1+14%)) -> 340.51265
A10: COS | B10: Remise | C10: 2382.5743 | D10: 38.750226 | E10: =+D10 -> 38.750226 | F10: 38.750226 | G10: =+E10 -> 38.750226 | H10: =+G10 -> 38.750226
A11: Opex | B11: IFRS 16 | C11: -26869.075 | D11: -25941.961 | E11: -25941.961 | F11: -25941.961 | G11: -25941.961 | H11: -25941.961
A12: COS | B12: IFRS 15 | C12: 1763.351 | D12: 2123.0762 | E12: =(D12) -> 2123.0762 | F12: 2123.0762 | G12: =(E12*(1+6.3%)) -> 2256.83 | H12: =(G12*(1+14%)) -> 2572.7862
A13: Opex | B13: Exchange | C13: -242.96996 | D13: 329.86193 | E13: 329.86193 | F13: 329.86193 | G13: 329.86193 | H13: 329.86193
A14: Opex | B14: IFRS 9 | C14: 137.44138 | D14: -216.39435 | E14: -216.39435 | F14: -216.39435 | G14: -216.39435 | H14: -216.39435
B15: EBITDA | C15: -24882.594 | D15: =(+D9+D10+D11+D12+D13+D14) -> -23427.85 | E15: =(+E9+E10+E11+E12+E13+E14) -> -23387.252 | F15: -23387.252 | G15: =(+G9+G10+G11+G12+G13+G14) -> -23234.218 | H15: =(+H9+H10+H11+H12+H13+H14) -> -22876.444
A16: Dep | B16: IFRS 16-Amort | C16: 19232.259 | D16: 18884.43 | E16: 18884.43 | F16: 18884.43 | G16: 18884.43 | H16: 18884.43
A17: Dep | B17: Depreciation | C17: 306.93946 | D17: 875.2456 | E17: 875.2456 | F17: 875.2456 | G17: 875.2456 | H17: 875.2456
A18: Dep | B18: IFRS 15 | C18: -1763.351 | D18: =(-D12) -> -2123.0762 | E18: =-E12 -> -2123.0762 | F18: -2123.0762 | G18: =-G12 -> -2256.83 | H18: =-H12 -> -2572.7862
B19: EBIT | C19: =(+C15+C16+C17+C18) -> -7106.7458 | D19: =(+D15+D16+D17+D18) -> -5791.2505 | E19: =(+E15+E16+E17+E18) -> -5750.6517 | F19: -5750.6517 | G19: =(+G15+G16+G17+G18) -> -5731.372 | H19: =(+H15+H16+H17+H18) -> -5689.5547
B20: IFRS 16-interest | C20: 10948.812 | D20: 8832.6109 | E20: =+D20 -> 8832.6109 | F20: 8832.6109 | G20: =+E20 -> 8832.6109 | H20: =+G20 -> 8832.6109
B21: PBT | C21: 3842.0661 | D21: =(+D19+D20) -> 3041.3604 | E21: =(+E19+E20) -> 3081.9592 | F21: 3081.9592 | G21: =(+G19+G20) -> 3101.2389 | H21: =(+H19+H20) -> 3143.0562
A22: Tax | B22: Tax ( Deffered tax) | C22: -595.22915 | D22: -1368.8821 | E22: -1000 | F22: -1000 | G22: -1000 | H22: -1000
B23: PAT | C23: 3246.8369 | D23: =(D21+D22) -> 1672.4782 | E23: =(E21+E22) -> 2081.9592 | F23: 2081.9592 | G23: =(G21+G22) -> 2101.2389 | H23: =(H21+H22) -> 2143.0562
A26: Rev | C26: =+C9 -> -2053.9153 | D26: =+D9 -> 238.81677 | E26: =+E9 -> 279.41563 | F26: 279.41563 | G26: =+G9 -> 298.6953 | H26: =+H9 -> 340.51265
A27: Cos | C27: =+C10+C12 -> 4145.9253 | D27: =+D10+D12 -> 2161.8265 | E27: =+E10+E12 -> 2161.8265 | F27: 2161.8265 | G27: =+G10+G12 -> 2295.5803 | H27: =+H10+H12 -> 2611.5365
A28: Opex | C28: =+C11+C13+C14 -> -26974.604 | D28: =+D11+D13+D14 -> -25828.494 | E28: =+E11+E13+E14 -> -25828.494 | F28: -25828.494 | G28: =+G11+G13+G14 -> -25828.494 | H28: =+H11+H13+H14 -> -25828.494
A30: Dep | C30: =+C16+C17+C18 -> 17775.848 | D30: =+D16+D17+D18 -> 17636.6 | E30: =+E16+E17+E18 -> 17636.6 | F30: 17636.6 | G30: =+G16+G17+G18 -> 17502.846 | H30: =+H16+H17+H18 -> 17186.89
A31: Inter | C31: =+C20 -> 10948.812 | D31: =+D20 -> 8832.6109 | E31: =+E20 -> 8832.6109 | F31: =+F20 -> 8832.6109 | G31: =+G20 -> 8832.6109 | H31: =+H20 -> 8832.6109
A33: Tax | C33: =+C22 -> -595.22915 | D33: =+D22 -> -1368.8821 | E33: =+E22 -> -1000 | F33: =+F22 -> -1000 | G33: =+G22 -> -1000 | H33: =+H22 -> -1000

Sheet 2023
A2: OHADA | B2: IFRS | C2: OHADA | D2: IFRS | E2: GAP
A3: CHIFFRE D'AFFAIRES | B3: CHIFFRE D'AFFAIRES | C3: 3.1171271e+08 | D3: 314257662 | E3: =+C3-D3 -> -2544953.3
A4: EXCEDENT BRUT D'EXPLOITATION | B4: EBITDA | C4: 94675316 | D4: 117512803 | E4: =+C4-D4 -> -22837487
A5: RESULTAT D'EXPLOITATION | B5: EBIT | C5: 38472637 | D5: 48136780 | E5: =+C5-D5 -> -9664143.3 | F5: Bénéfice Avant Intérêts et Impôts
A6: RESULTAT AVANT IMPOT | B6: PBT | C6: 31992367 | D6: 32676459 | E6: =+C6-D6 -> -684092.14
A7: RESULTAT NET | B7: PAT | C7: 22354656 | D7: 20413229 | E7: =+C7-D7 -> 1941426.5
D10: Remise | E10: -2864837.6 | I10: 42
D11: Comm Staff | E11: 284427.91 | I11: 0.37 | J11: 0.63
D12: IFRS 15 & others | E12: 35456 | I12: =I10*I11 -> 15.54 | J12: =I10-I12 -> 26.46
D13: CA | E13: =SUM(E10:E12) -> -2544953.7
D14: Remise | E14: =-E10 -> 2864837.6
D15: IFRS 16 | E15: -27916179
D16: IFRS 15 | E16: 3410093.5
D17: Exchange | E17: 120723.27 | I17: 42 | J17: 15.54
D18: IFRS 9 | E18: 1227991.9
D19: EBITDA | E19: =+E13+E14+E15+E16+E17+E18 -> -22837487
D20: IFRS 16-Amort | E20: 19196109
D21: Depreciation | E21: -2612672.2
D22: IFRS 15 | E22: =-E16 -> -3410093.5
D23: EBIT | E23: =+E19+E20+E21+E22 -> -9664142.8
D24: IFRS 16-interest | E24: 8980050.9
D25: PBT | E25: =+E23+E24 -> -684091.92
D26: Tax ( Deffered tax) | E26: 2625519.5
D27: PAT | E27: =E25+E26 -> 1941427.5

Sheet 2024
A2: OHADA | B2: IFRS | C2: OHADA | D2: IFRS | E2: GAP
A3: CHIFFRE D'AFFAIRES | B3: CHIFFRE D'AFFAIRES | C3: =281395110530/1000 -> 2.8139511e+08 | D3: 2.8344903e+08 | E3: =+C3-D3 -> -2053914.9 | V3: =+D3-U3 -> 2.8344903e+08 | X3: 285257856
A4: EXCEDENT BRUT D'EXPLOITATION | B4: EBITDA | C4: =83997785550/1000 -> 83997786 | D4: 1.0888038e+08 | E4: =+C4-D4 -> -24882594 | V4: =+D4-U4 -> 1.0888038e+08 | X4: 108470871
A5: RESULTAT D'EXPLOITATION | B5: EBIT | C5: =28896986951/1000 -> 28896987 | D5: 36003732 | E5: =+C5-D5 -> -7106745.4 | T5: Bénéfice Avant Intérêts et Impôts | V5: =+D5-U5 -> 36003732 | X5: 35594224
A6: RESULTAT AVANT IMPOT | B6: PBT | C6: =21593377216/1000 -> 21593377 | D6: 17751311 | E6: =+C6-D6 -> 3842066.5 | V6: =+D6-U6 -> 17751311 | X6: 17260163
A7: RESULTAT NET | B7: PAT | C7: =13842001007/1000 -> 13842001 | D7: 10595164 | E7: =+C7-D7 -> 3246837.3 | V7: =+D7-U7 -> 10595164 | X7: 10104016
D10: Remise | E10: -2382574.3 | G10: 300000
D11: Comm Staff | E11: 298612 | G11: 153000
D12: IFRS 15 & Others | E12: 30047 | G12: =G10-G11 -> 147000
D13: CA | E13: =SUM(E10:E12) -> -2053915.3
D14: Remise | E14: 2382574.3
D15: IFRS 16 | E15: -26869075
D16: IFRS 15 | E16: 1763351
D17: Exchange | E17: -242969.96
D18: IFRS 9 | E18: 137441.38
D19: EBITDA | E19: =+E13+E14+E15+E16+E17+E18 -> -24882594
D20: IFRS 16-Amort | E20: 19232259
D21: Depreciation | E21: 306939.46
D22: IFRS 15 | E22: =-E16 -> -1763351
D23: EBIT | E23: =+E19+E20+E21+E22 -> -7106745.8
D24: IFRS 16-interest | E24: 10948812
D25: PBT | E25: =+E23+E24 -> 3842066.1
D26: Tax ( Deffered tax) | E26: -595229.15
D27: PAT | E27: =E25+E26 -> 3246836.9
E33: IFRS 16 Interest | F33: 1.0033453e+10

Sheet 2025
B2: OHADA | C2: IFRS | D2: OHADA | E2: IFRS | F2: GAP | G2: Comments
B3: CHIFFRE D'AFFAIRES | C3: CHIFFRE D'AFFAIRES | D3: 3.0138019e+08 | E3: 301141375 | F3: =+D3-E3 -> 238817.27 | G3: 1)- Difference provenant de la gratuité au Staff/ Personnel/ Administrateur ( livraison a soi meme) qui troune autour de XOF 300 Mn: Impact diminution du revenue IFRS car c'est pas considéré comme du revenue, en OHADA passé en charges 2)- Remise sur vente ( recharges physique, appareil, sur les devices) pas tres significatif depuis Mars 2024 avec le changement de mode de vente par Momo.* Diminution du revenue OHADA car Remises viennent en diminution du revenue et en IFRS en commissions ( XOF 38mn) 3)- IFRS 15 ( Offre dans lesquel on a des telephones gratuitement), IFRS revenue est superieur à OHADA car le revenue du device est passé automatiquemeny alors que en OHADA c'est zero. En moyenne nous sommes à XOF 30 mn par an
B4: EXCEDENT BRUT D'EXPLOITATION | C4: EBITDA | D4: 99688089 | E4: 123115939 | F4: =+D4-E4 -> -23427850 | G4: 1)- IFRS 16 : Loyer IHS, Loyer Bureau, Site traité en charges en OHADA mais en IFRS, en application 2)- Remise sur vente (XOF 38 mn) venant neutraliser l'ecart sur le Revenue 3)- IFRS 15 4)-IFRS 9
B5: RESULTAT D'EXPLOITATION | C5: EBIT | D5: 42012964 | E5: 47804215 | F5: =+D5-E5 -> -5791250.7
B6: RESULTAT AVANT IMPOT | C6: PBT | D6: 31899308 | E6: 28857948 | F6: =+D6-E6 -> 3041359.8
B7: RESULTAT NET | C7: PAT | D7: 22713124 | E7: 21040646 | F7: =+D7-E7 -> 1672478.2
E11: Remise | F11: -38750.226 | G11: -2382574.3 | H11: -2864837.6
E12: Comm Staff | F12: 295369 | G12: 298612 | H12: 284427.91
E13: IFRS 15 & Others | F13: -17802 | G13: 30047 | H13: 35456
E14: CA | F14: =SUM(F11:F13) -> 238816.77 | G14: -2053915.3 | H14: =SUM(H11:H13) -> -2544953.7 | J14: =+AVERAGE(F14:H14) -> -1453350.7
E15: Remise | F15: 38750.226 | G15: 2382574.3 | H15: =-H11 -> 2864837.6 | J15: =+AVERAGE(F15:H15) -> 1762054
E16: IFRS 16 | F16: -25941961 | G16: -26869075 | H16: -27916179 | J16: =+AVERAGE(F16:H16) -> -26909072
E17: IFRS 15 | F17: 2123076.2 | G17: 1763351 | H17: 3410093.5 | J17: =+AVERAGE(F17:H17) -> 2432173.6
E18: Exchange | F18: 329861.93 | G18: -242969.96 | H18: 120723.27 | J18: =+AVERAGE(F18:H18) -> 69205.078
E19: IFRS 9 | F19: -216394.35 | G19: 137441.38 | H19: 1227991.9 | J19: =+AVERAGE(F19:H19) -> 383012.98
E20: EBITDA | F20: =+F14+F15+F16+F17+F18+F19 -> -23427850 | G20: -24882594 | H20: =+H14+H15+H16+H17+H18+H19 -> -22837487 | J20: =+AVERAGE(F20:H20) -> -23715977
E21: IFRS 16-Amort | F21: 18884430 | G21: 19232259 | H21: 19196109
E22: Depreciation | F22: 875245.6 | G22: 306939.46 | H22: -2612672.2
E23: IFRS 15 | F23: =-F17 -> -2123076.2 | G23: -1763351 | H23: =-H17 -> -3410093.5
E24: EBIT | F24: =+F20+F21+F22+F23 -> -5791250.5 | G24: -7106745.8 | H24: =+H20+H21+H22+H23 -> -9664142.8 | J24: =+AVERAGE(F24:H24) -> -7520713.1
E25: IFRS 16-interest | F25: 8832610.9 | G25: 10948812 | H25: 8980050.9 | J25: =+AVERAGE(F25:H25) -> 9587157.9
E26: PBT | F26: =+F24+F25 -> 3041360.4 | G26: 3842066.1 | H26: =+H24+H25 -> -684091.92
E27: Tax ( Deffered tax) | F27: -1368882.1 | G27: -595229.15 | H27: 2625519.5
E28: PAT | F28: =F26+F27 -> 1672478.2 | G28: 3246836.9 | H28: =H26+H27 -> 1941427.5
