Workbook

Sheet Paramètres >

Sheet Plan SYSCOHADA
A1: Préfixe | B1: Ligne (Mapping) | C1: État
A2: 10 | B2: Capital | C2: Actif net
A3: 11 | B3: Réserves | C3: Actif net
A4: 12 | B4: Report à nouveau | C4: Actif net
A5: 13 | B5: Résultat en instance d'affectation | C5: Actif net
A6: 14 | B6: Subventions d'investissement et provisions réglementées | C6: Actif net
A7: 15 | B7: Subventions d'investissement et provisions réglementées | C7: Actif net
A8: 16 | B8: Emprunts et dettes financières | C8: Actif net
A9: 17 | B9: Dettes de location-acquisition | C9: Actif net
A10: 18 | B10: Emprunts et dettes financières | C10: Actif net
A11: 19 | B11: Provisions pour risques et charges | C11: Actif net
A12: 20 | B12: Immobilisations incorporelles | C12: Actif net
... A110: 89 | B110: Impôt sur le résultat | C110: Compte de résultat
A112: Un compte rejoint la ligne de son préfixe le plus long ; sans préfixe connu, celle de sa classe (2 : immobilisations corporelles, 3 : stocks, 4 : débiteurs et créditeurs divers, 5 : disponibilités, 6 : autres charges, 7 : autres produits, 8 : résultat HAO).

Sheet BG COMP
A1: Mapping | B1: C1 | C1: C2 | D1: C3 | E1: C4 | F1: NC | G1: LB | H1: FY21 | I1: FY22 | J1: FY23
A2: Capital | B2: =LEFT($F2,1) -> 1 | C2: =LEFT($F2,2) -> 10 | D2: =LEFT($F2,3) -> 101 | E2: =LEFT($F2,4) -> 1011 | F2: 101100 | G2: Capital Souscrit | H2: -2000000000 | I2: -2000000000 | J2: -2000000000
A3: Capital | B3: =LEFT($F3,1) -> 1 | C3: =LEFT($F3,2) -> 10 | D3: =LEFT($F3,3) -> 106 | E3: =LEFT($F3,4) -> 1062 | F3: 106200 | G3: Ecart de Reevaluation Libre | H3: -3988025341 | I3: -3988025341 | J3: -3988025341
A4: Report à nouveau | B4: =LEFT($F4,1) -> 1 | C4: =LEFT($F4,2) -> 12 | D4: =LEFT($F4,3) -> 121 | E4: =LEFT($F4,4) -> 1211 | F4: 121100 | G4: Report A Nouveau Crediteur | H4: 889045172 | I4: -409392982 | J4: -2650708629
A5: Emprunts et dettes financières | B5: =LEFT($F5,1) -> 1 | C5: =LEFT($F5,2) -> 16 | D5: =LEFT($F5,3) -> 161 | E5: =LEFT($F5,4) -> 1611 | F5: 161100 | G5: Emprunt Obligataire(SOGEBOURSE) | H5: -2996428399 | I5: -1803571207 | J5: -610714017
A6: Emprunts et dettes financières | B6: =LEFT($F6,1) -> 1 | C6: =LEFT($F6,2) -> 16 | D6: =LEFT($F6,3) -> 161 | E6: =LEFT($F6,4) -> 1612 | F6: 161200 | G6: Emprunts AGDEVCO | H6: -4722890400 | I6: -2361445200 | J6: -2361445200
A7: Emprunts et dettes financières | B7: =LEFT($F7,1) -> 1 | C7: =LEFT($F7,2) -> 16 | D7: =LEFT($F7,3) -> 161 | E7: =LEFT($F7,4) -> 1613 | F7: 161300 | G7: Emprunt Obligataire HUDSON & CIE | H7: -3930000000 | I7: -9930000000 | J7: -9930000000
A8: Emprunts et dettes financières | B8: =LEFT($F8,1) -> 1 | C8: =LEFT($F8,2) -> 16 | D8: =LEFT($F8,3) -> 162 | E8: =LEFT($F8,4) -> 1626 | F8: 162600 | G8: Emprunts BGFI | H8: -617290063 | I8: -466484731 | J8: -303163273
A9: Emprunts et dettes financières | B9: =LEFT($F9,1) -> 1 | C9: =LEFT($F9,2) -> 16 | D9: =LEFT($F9,3) -> 165 | E9: =LEFT($F9,4) -> 1652 | F9: 165200 | G9: CAUTIONNEMENTS REÇUS | H9: -3200000 | I9: -3200000 | J9: -3200000
A10: Emprunts et dettes financières | B10: =LEFT($F10,1) -> 1 | C10: =LEFT($F10,2) -> 16 | D10: =LEFT($F10,3) -> 166 | E10: =LEFT($F10,4) -> 1661 | F10: 166100 | G10: Interêt Courus Non échus /Emprunts | H10: -266932720 | I10: -508916932 | J10: -538281619
A11: Dettes de location-acquisition | B11: =LEFT($F11,1) -> 1 | C11: =LEFT($F11,2) -> 17 | D11: =LEFT($F11,3) -> 173 | E11: =LEFT($F11,4) -> 1732 | F11: 173200 | G11: AUTRES EMPRUNTS CREDITS BAIL MOBILIER | H11: -167798150 | I11: -81427230 | J11: 1
A12: Provisions pour risques et charges | B12: =LEFT($F12,1) -> 1 | C12: =LEFT($F12,2) -> 19 | D12: =LEFT($F12,3) -> 191 | E12: =LEFT($F12,4) -> 1910 | F12: 191000 | G12: PROVISIONS POUR LITIGES | H12: -30017736 | I12: -30017736 | J12: -30017736
A13: Provisions pour risques et charges | B13: =LEFT($F13,1) -> 1 | C13: =LEFT($F13,2) -> 19 | D13: =LEFT($F13,3) -> 196 | E13: =LEFT($F13,4) -> 1961 | F13: 196100 | G13: Provision pour Pension et Engagement de Retraite | H13: -210838607 | I13: -74839973 | J13: -54776571
... A684: Impôt sur le résultat | B684: =LEFT($F684,1) -> 8 | C684: =LEFT($F684,2) -> 89 | D684: =LEFT($F684,3) -> 899 | E684: =LEFT($F684,4) -> 8991 | F684: 899100 | G684: DEGREVEMENT D'IMPOTS | H684: 0 | I684: -55306290 | J684: 0

Sheet EFS >

Sheet P&L
A1: Compte de résultat — SYSCOHADA
A2: Montants en FCFA, construits depuis la feuille BG COMP (SUMIF sur la colonne Mapping).
A3: Mapping | B3: En FCFA | C3: FY21 | D3: FY22 | E3: FY23 | G3: TCAM
A4: Ventes de marchandises | B4: Ventes de marchandises | C4: =-SUMIF('BG COMP'!$A:$A,$A4,'BG COMP'!H:H) -> 0 | D4: =-SUMIF('BG COMP'!$A:$A,$A4,'BG COMP'!I:I) -> 0 | E4: =-SUMIF('BG COMP'!$A:$A,$A4,'BG COMP'!J:J) -> 0 | G4: =IFERROR((E4/C4)^(1/2)-1,"n.a") -> n.a
A5: Production vendue et services | B5: Production vendue et services | C5: =-SUMIF('BG COMP'!$A:$A,$A5,'BG COMP'!H:H) -> 24526890025 | D5: =-SUMIF('BG COMP'!$A:$A,$A5,'BG COMP'!I:I) -> 19979701999 | E5: =-SUMIF('BG COMP'!$A:$A,$A5,'BG COMP'!J:J) -> 24413824282 | G5: =IFERROR((E5/C5)^(1/2)-1,"n.a") -> -0.0023075969
B6: Chiffre d'affaires | C6: =C4+C5 -> 24526890025 | D6: =D4+D5 -> 19979701999 | E6: =E4+E5 -> 24413824282 | G6: =IFERROR((E6/C6)^(1/2)-1,"n.a") -> -0.0023075969
A7: Production stockée et immobilisée | B7: Production stockée et immobilisée | C7: =-SUMIF('BG COMP'!$A:$A,$A7,'BG COMP'!H:H) -> 247517534 | D7: =-SUMIF('BG COMP'!$A:$A,$A7,'BG COMP'!I:I) -> -141527251 | E7: =-SUMIF('BG COMP'!$A:$A,$A7,'BG COMP'!J:J) -> -127683793 | G7: =IFERROR((E7/C7)^(1/2)-1,"n.a") -> n.a
A8: Achats de marchandises et matières | B8: Achats de marchandises et matières | C8: =-SUMIF('BG COMP'!$A:$A,$A8,'BG COMP'!H:H) -> -14528621928 | D8: =-SUMIF('BG COMP'!$A:$A,$A8,'BG COMP'!I:I) -> -11560284709 | E8: =-SUMIF('BG COMP'!$A:$A,$A8,'BG COMP'!J:J) -> -15549114315 | G8: =IFERROR((E8/C8)^(1/2)-1,"n.a") -> 0.034524111
A9: Autres achats | B9: Autres achats | C9: =-SUMIF('BG COMP'!$A:$A,$A9,'BG COMP'!H:H) -> -1538283414 | D9: =-SUMIF('BG COMP'!$A:$A,$A9,'BG COMP'!I:I) -> -1166313837 | E9: =-SUMIF('BG COMP'!$A:$A,$A9,'BG COMP'!J:J) -> -1399980232 | G9: =IFERROR((E9/C9)^(1/2)-1,"n.a") -> -0.046012305
A10: Transports | B10: Transports | C10: =-SUMIF('BG COMP'!$A:$A,$A10,'BG COMP'!H:H) -> -34833289 | D10: =-SUMIF('BG COMP'!$A:$A,$A10,'BG COMP'!I:I) -> -119026416 | E10: =-SUMIF('BG COMP'!$A:$A,$A10,'BG COMP'!J:J) -> -172703093 | G10: =IFERROR((E10/C10)^(1/2)-1,"n.a") -> 1.2266544
A11: Sous-traitance générale | B11: Sous-traitance générale | C11: =-SUMIF('BG COMP'!$A:$A,$A11,'BG COMP'!H:H) -> 0 | D11: =-SUMIF('BG COMP'!$A:$A,$A11,'BG COMP'!I:I) -> 0 | E11: =-SUMIF('BG COMP'!$A:$A,$A11,'BG COMP'!J:J) -> 0 | G11: =IFERROR((E11/C11)^(1/2)-1,"n.a") -> n.a
A12: Locations et charges locatives | B12: Locations et charges locatives | C12: =-SUMIF('BG COMP'!$A:$A,$A12,'BG COMP'!H:H) -> -940331947 | D12: =-SUMIF('BG COMP'!$A:$A,$A12,'BG COMP'!I:I) -> -538325504 | E12: =-SUMIF('BG COMP'!$A:$A,$A12,'BG COMP'!J:J) -> -781196707 | G12: =IFERROR((E12/C12)^(1/2)-1,"n.a") -> -0.088535819
A13: Entretien, réparations et maintenance | B13: Entretien, réparations et maintenance | C13: =-SUMIF('BG COMP'!$A:$A,$A13,'BG COMP'!H:H) -> -511850731 | D13: =-SUMIF('BG COMP'!$A:$A,$A13,'BG COMP'!I:I) -> -441190386 | E13: =-SUMIF('BG COMP'!$A:$A,$A13,'BG COMP'!J:J) -> -491928077 | G13: =IFERROR((E13/C13)^(1/2)-1,"n.a") -> -0.019654541
A14: Primes d'assurance | B14: Primes d'assurance | C14: =-SUMIF('BG COMP'!$A:$A,$A14,'BG COMP'!H:H) -> -135075701 | D14: =-SUMIF('BG COMP'!$A:$A,$A14,'BG COMP'!I:I) -> -135284717 | E14: =-SUMIF('BG COMP'!$A:$A,$A14,'BG COMP'!J:J) -> -124252017 | G14: =IFERROR((E14/C14)^(1/2)-1,"n.a") -> -0.040901728
A15: Études, recherches et documentation | B15: Études, recherches et documentation | C15: =-SUMIF('BG COMP'!$A:$A,$A15,'BG COMP'!H:H) -> -2662351 | D15: =-SUMIF('BG COMP'!$A:$A,$A15,'BG COMP'!I:I) -> -648607 | E15: =-SUMIF('BG COMP'!$A:$A,$A15,'BG COMP'!J:J) -> -371307 | G15: =IFERROR((E15/C15)^(1/2)-1,"n.a") -> -0.62654875
A16: Publicité et relations publiques | B16: Publicité et relations publiques | C16: =-SUMIF('BG COMP'!$A:$A,$A16,'BG COMP'!H:H) -> -3384500 | D16: =-SUMIF('BG COMP'!$A:$A,$A16,'BG COMP'!I:I) -> -3081000 | E16: =-SUMIF('BG COMP'!$A:$A,$A16,'BG COMP'!J:J) -> -6470650 | G16: =IFERROR((E16/C16)^(1/2)-1,"n.a") -> 0.38269596
A17: Frais de télécommunications | B17: Frais de télécommunications | C17: =-SUMIF('BG COMP'!$A:$A,$A17,'BG COMP'!H:H) -> -33745947 | D17: =-SUMIF('BG COMP'!$A:$A,$A17,'BG COMP'!I:I) -> -50470243 | E17: =-SUMIF('BG COMP'!$A:$A,$A17,'BG COMP'!J:J) -> -43351625 | G17: =IFERROR((E17/C17)^(1/2)-1,"n.a") -> 0.13342263
A18: Frais bancaires | B18: Frais bancaires | C18: =-SUMIF('BG COMP'!$A:$A,$A18,'BG COMP'!H:H) -> -221129138 | D18: =-SUMIF('BG COMP'!$A:$A,$A18,'BG COMP'!I:I) -> -355266320 | E18: =-SUMIF('BG COMP'!$A:$A,$A18,'BG COMP'!J:J) -> -232479385 | G18: =IFERROR((E18/C18)^(1/2)-1,"n.a") -> 0.025343157
... A20: Autres services extérieurs | B20: Autres services extérieurs | C20: =-SUMIF('BG COMP'!$A:$A,$A20,'BG COMP'!H:H) -> -759951975 | D20: =-SUMIF('BG COMP'!$A:$A,$A20,'BG COMP'!I:I) -> -452904165 | E20: =-SUMIF('BG COMP'!$A:$A,$A20,'BG COMP'!J:J) -> -255241663 | G20: =IFERROR((E20/C20)^(1/2)-1,"n.a") -> -0.42046094
B21: Services extérieurs | C21: =C11+C12+C13+C14+C15+C16+C17+C18+C19+C20 -> -2782007013 | D21: =D11+D12+D13+D14+D15+D16+D17+D18+D19+D20 -> -2175523711 | E21: =E11+E12+E13+E14+E15+E16+E17+E18+E19+E20 -> -2167057674 | G21: =IFERROR((E21/C21)^(1/2)-1,"n.a") -> -0.11741585
A22: Impôts et taxes | B22: Impôts et taxes | C22: =-SUMIF('BG COMP'!$A:$A,$A22,'BG COMP'!H:H) -> -194550289 | D22: =-SUMIF('BG COMP'!$A:$A,$A22,'BG COMP'!I:I) -> -73860299 | E22: =-SUMIF('BG COMP'!$A:$A,$A22,'BG COMP'!J:J) -> -99470939 | G22: =IFERROR((E22/C22)^(1/2)-1,"n.a") -> -0.28495698
A23: Charges de personnel | B23: Charges de personnel | C23: =-SUMIF('BG COMP'!$A:$A,$A23,'BG COMP'!H:H) -> -1356205593 | D23: =-SUMIF('BG COMP'!$A:$A,$A23,'BG COMP'!I:I) -> -1359456222 | E23: =-SUMIF('BG COMP'!$A:$A,$A23,'BG COMP'!J:J) -> -1387887823 | G23: =IFERROR((E23/C23)^(1/2)-1,"n.a") -> 0.011613036
A24: Autres produits d'exploitation | B24: Autres produits d'exploitation | C24: =-SUMIF('BG COMP'!$A:$A,$A24,'BG COMP'!H:H) -> 12616990 | D24: =-SUMIF('BG COMP'!$A:$A,$A24,'BG COMP'!I:I) -> 10487000 | E24: =-SUMIF('BG COMP'!$A:$A,$A24,'BG COMP'!J:J) -> 15809750 | G24: =IFERROR((E24/C24)^(1/2)-1,"n.a") -> 0.11939825
A25: Autres charges d'exploitation | B25: Autres charges d'exploitation | C25: =-SUMIF('BG COMP'!$A:$A,$A25,'BG COMP'!H:H) -> -25890895 | D25: =-SUMIF('BG COMP'!$A:$A,$A25,'BG COMP'!I:I) -> -142699537 | E25: =-SUMIF('BG COMP'!$A:$A,$A25,'BG COMP'!J:J) -> -21435714 | G25: =IFERROR((E25/C25)^(1/2)-1,"n.a") -> -0.09009627
B26: EBITDA | C26: =C6+C7+C8+C9+C10+C21+C22+C23+C24+C25 -> 4326632128 | D26: =D6+D7+D8+D9+D10+D21+D22+D23+D24+D25 -> 3251497017 | E26: =E6+E7+E8+E9+E10+E21+E22+E23+E24+E25 -> 3504300449 | G26: =IFERROR((E26/C26)^(1/2)-1,"n.a") -> -0.10003487
B27: EBITDA (% CA) | C27: =IFERROR(C26/C6,"n.a") -> 0.17640362 | D27: =IFERROR(D26/D6,"n.a") -> 0.16274002 | E27: =IFERROR(E26/E6,"n.a") -> 0.14353755 | G27: =AVERAGE(C27:E27) -> 0.16089373
A28: Dotations aux amortissements et provisions | B28: Dotations aux amortissements et provisions | C28: =-SUMIF('BG COMP'!$A:$A,$A28,'BG COMP'!H:H) -> -1373796342 | D28: =-SUMIF('BG COMP'!$A:$A,$A28,'BG COMP'!I:I) -> -915912899 | E28: =-SUMIF('BG COMP'!$A:$A,$A28,'BG COMP'!J:J) -> -1059002616 | G28: =IFERROR((E28/C28)^(1/2)-1,"n.a") -> -0.12201451
A29: Reprises d'amortissements et de provisions | B29: Reprises d'amortissements et de provisions | C29: =-SUMIF('BG COMP'!$A:$A,$A29,'BG COMP'!H:H) -> 0 | D29: =-SUMIF('BG COMP'!$A:$A,$A29,'BG COMP'!I:I) -> 183674280 | E29: =-SUMIF('BG COMP'!$A:$A,$A29,'BG COMP'!J:J) -> 20063402 | G29: =IFERROR((E29/C29)^(1/2)-1,"n.a") -> n.a
B30: D&A | C30: =C28+C29 -> -1373796342 | D30: =D28+D29 -> -732238619 | E30: =E28+E29 -> -1038939214 | G30: =IFERROR((E30/C30)^(1/2)-1,"n.a") -> -0.13037125
B31: EBIT | C31: =C26+C30 -> 2952835786 | D31: =D26+D30 -> 2519258398 | E31: =E26+E30 -> 2465361235 | G31: =IFERROR((E31/C31)^(1/2)-1,"n.a") -> -0.086264215
B32: EBIT (% CA) | C32: =IFERROR(C31/C6,"n.a") -> 0.12039177 | D32: =IFERROR(D31/D6,"n.a") -> 0.12609089 | E32: =IFERROR(E31/E6,"n.a") -> 0.10098218 | G32: =AVERAGE(C32:E32) -> 0.11582161
A33: Produits financiers | B33: Produits financiers | C33: =-SUMIF('BG COMP'!$A:$A,$A33,'BG COMP'!H:H) -> 0 | D33: =-SUMIF('BG COMP'!$A:$A,$A33,'BG COMP'!I:I) -> 21904110 | E33: =-SUMIF('BG COMP'!$A:$A,$A33,'BG COMP'!J:J) -> 27920709 | G33: =IFERROR((E33/C33)^(1/2)-1,"n.a") -> n.a
A34: Charges financières | B34: Charges financières | C34: =-SUMIF('BG COMP'!$A:$A,$A34,'BG COMP'!H:H) -> -1010070132 | D34: =-SUMIF('BG COMP'!$A:$A,$A34,'BG COMP'!I:I) -> -991618677 | E34: =-SUMIF('BG COMP'!$A:$A,$A34,'BG COMP'!J:J) -> -1055921173 | G34: =IFERROR((E34/C34)^(1/2)-1,"n.a") -> 0.022445069
B35: Résultat financier | C35: =C33+C34 -> -1010070132 | D35: =D33+D34 -> -969714567 | E35: =E33+E34 -> -1028000464 | G35: =IFERROR((E35/C35)^(1/2)-1,"n.a") -> 0.0088367417
A36: Résultat HAO | B36: Résultat HAO | C36: =-SUMIF('BG COMP'!$A:$A,$A36,'BG COMP'!H:H) -> -45144123 | D36: =-SUMIF('BG COMP'!$A:$A,$A36,'BG COMP'!I:I) -> 36465526 | E36: =-SUMIF('BG COMP'!$A:$A,$A36,'BG COMP'!J:J) -> 2700000 | G36: =IFERROR((E36/C36)^(1/2)-1,"n.a") -> n.a
A37: Participation des travailleurs | B37: Participation des travailleurs | C37: =-SUMIF('BG COMP'!$A:$A,$A37,'BG COMP'!H:H) -> 0 | D37: =-SUMIF('BG COMP'!$A:$A,$A37,'BG COMP'!I:I) -> 0 | E37: =-SUMIF('BG COMP'!$A:$A,$A37,'BG COMP'!J:J) -> 0 | G37: =IFERROR((E37/C37)^(1/2)-1,"n.a") -> n.a
A38: Impôt sur le résultat | B38: Impôt sur le résultat | C38: =-SUMIF('BG COMP'!$A:$A,$A38,'BG COMP'!H:H) -> 0 | D38: =-SUMIF('BG COMP'!$A:$A,$A38,'BG COMP'!I:I) -> 55306290 | E38: =-SUMIF('BG COMP'!$A:$A,$A38,'BG COMP'!J:J) -> 0 | G38: =IFERROR((E38/C38)^(1/2)-1,"n.a") -> n.a
B39: Résultat net | C39: =C31+C35+C36+C37+C38 -> 1897621531 | D39: =D31+D35+D36+D37+D38 -> 1641315647 | E39: =E31+E35+E36+E37+E38 -> 1440060771 | G39: =IFERROR((E39/C39)^(1/2)-1,"n.a") -> -0.1288647
A41: Source : balance générale comparée, classée selon le plan SYSCOHADA (feuille Plan SYSCOHADA).

Sheet Balance sheet
A1: Actif net — SYSCOHADA
A2: Montants en M FCFA. Actif net et capitaux propres doivent se rejoindre : la dernière ligne contrôle l'équilibre.
A3: Mapping | C3: En M FCFA | D3: FY21 | E3: FY22 | F3: FY23
A4: Immobilisations incorporelles | C4: Immobilisations incorporelles | D4: =SUMIF('BG COMP'!$A:$A,$A4,'BG COMP'!H:H)/1000000 -> -37.398706 | E4: =SUMIF('BG COMP'!$A:$A,$A4,'BG COMP'!I:I)/1000000 -> -46.864666 | F4: =SUMIF('BG COMP'!$A:$A,$A4,'BG COMP'!J:J)/1000000 -> 11.997832
A5: Immobilisations corporelles | C5: Immobilisations corporelles | D5: =SUMIF('BG COMP'!$A:$A,$A5,'BG COMP'!H:H)/1000000 -> 18401.395 | E5: =SUMIF('BG COMP'!$A:$A,$A5,'BG COMP'!I:I)/1000000 -> 17917.461 | F5: =SUMIF('BG COMP'!$A:$A,$A5,'BG COMP'!J:J)/1000000 -> 17962.264
A6: Immobilisations financières | C6: Immobilisations financières | D6: =SUMIF('BG COMP'!$A:$A,$A6,'BG COMP'!H:H)/1000000 -> 38.684397 | E6: =SUMIF('BG COMP'!$A:$A,$A6,'BG COMP'!I:I)/1000000 -> 38.684397 | F6: =SUMIF('BG COMP'!$A:$A,$A6,'BG COMP'!J:J)/1000000 -> 42.384397
C7: Actifs immobilisés | D7: =D4+D5+D6 -> 18402.681 | E7: =E4+E5+E6 -> 17909.281 | F7: =F4+F5+F6 -> 18016.647
A8: Stocks et en-cours | C8: Stocks et en-cours | D8: =SUMIF('BG COMP'!$A:$A,$A8,'BG COMP'!H:H)/1000000 -> 1219.5628 | E8: =SUMIF('BG COMP'!$A:$A,$A8,'BG COMP'!I:I)/1000000 -> 1017.4502 | F8: =SUMIF('BG COMP'!$A:$A,$A8,'BG COMP'!J:J)/1000000 -> 1123.7432
A9: Créances clients | C9: Créances clients | D9: =SUMIF('BG COMP'!$A:$A,$A9,'BG COMP'!H:H)/1000000 -> 4616.8527 | E9: =SUMIF('BG COMP'!$A:$A,$A9,'BG COMP'!I:I)/1000000 -> 1517.6771 | F9: =SUMIF('BG COMP'!$A:$A,$A9,'BG COMP'!J:J)/1000000 -> 1627.0093
A10: Avances reçues des clients | C10: Avances reçues des clients | D10: =SUMIF('BG COMP'!$A:$A,$A10,'BG COMP'!H:H)/1000000 -> 0 | E10: =SUMIF('BG COMP'!$A:$A,$A10,'BG COMP'!I:I)/1000000 -> 0 | F10: =SUMIF('BG COMP'!$A:$A,$A10,'BG COMP'!J:J)/1000000 -> 0
A11: Dettes fournisseurs | C11: Dettes fournisseurs | D11: =SUMIF('BG COMP'!$A:$A,$A11,'BG COMP'!H:H)/1000000 -> -782.96348 | E11: =SUMIF('BG COMP'!$A:$A,$A11,'BG COMP'!I:I)/1000000 -> 1367.062 | F11: =SUMIF('BG COMP'!$A:$A,$A11,'BG COMP'!J:J)/1000000 -> 1984.9593
A12: Avances versées aux fournisseurs | C12: Avances versées aux fournisseurs | D12: =SUMIF('BG COMP'!$A:$A,$A12,'BG COMP'!H:H)/1000000 -> 11.700004 | E12: =SUMIF('BG COMP'!$A:$A,$A12,'BG COMP'!I:I)/1000000 -> 2.617515 | F12: =SUMIF('BG COMP'!$A:$A,$A12,'BG COMP'!J:J)/1000000 -> 2.362605
A13: Dettes et créances sociales | C13: Dettes et créances sociales | D13: =SUMIF('BG COMP'!$A:$A,$A13,'BG COMP'!H:H)/1000000 -> -66.218255 | E13: =SUMIF('BG COMP'!$A:$A,$A13,'BG COMP'!I:I)/1000000 -> -113.44075 | F13: =SUMIF('BG COMP'!$A:$A,$A13,'BG COMP'!J:J)/1000000 -> -128.33161
A14: Dettes et créances fiscales | C14: Dettes et créances fiscales | D14: =SUMIF('BG COMP'!$A:$A,$A14,'BG COMP'!H:H)/1000000 -> -784.44721 | E14: =SUMIF('BG COMP'!$A:$A,$A14,'BG COMP'!I:I)/1000000 -> -743.56066 | F14: =SUMIF('BG COMP'!$A:$A,$A14,'BG COMP'!J:J)/1000000 -> -487.51821
A15: Associés et groupe | C15: Associés et groupe | D15: =SUMIF('BG COMP'!$A:$A,$A15,'BG COMP'!H:H)/1000000 -> 1638.3128 | E15: =SUMIF('BG COMP'!$A:$A,$A15,'BG COMP'!I:I)/1000000 -> 2217.6935 | F15: =SUMIF('BG COMP'!$A:$A,$A15,'BG COMP'!J:J)/1000000 -> 3868.4593
A16: Débiteurs et créditeurs divers | C16: Débiteurs et créditeurs divers | D16: =SUMIF('BG COMP'!$A:$A,$A16,'BG COMP'!H:H)/1000000 -> -16.319042 | E16: =SUMIF('BG COMP'!$A:$A,$A16,'BG COMP'!I:I)/1000000 -> -17.297635 | F16: =SUMIF('BG COMP'!$A:$A,$A16,'BG COMP'!J:J)/1000000 -> -15.238435
C17: BFR | D17: =D8+D9+D10+D11+D12+D13+D14+D15+D16 -> 5836.4803 | E17: =E8+E9+E10+E11+E12+E13+E14+E15+E16 -> 5248.2014 | F17: =F8+F9+F10+F11+F12+F13+F14+F15+F16 -> 7975.4453
A18: Disponibilités | C18: Disponibilités | D18: =SUMIF('BG COMP'!$A:$A,$A18,'BG COMP'!H:H)/1000000 -> -575.55169 | E18: =SUMIF('BG COMP'!$A:$A,$A18,'BG COMP'!I:I)/1000000 -> 862.52869 | F18: =SUMIF('BG COMP'!$A:$A,$A18,'BG COMP'!J:J)/1000000 -> -1105.5612
A19: Crédits de trésorerie | C19: Crédits de trésorerie | D19: =SUMIF('BG COMP'!$A:$A,$A19,'BG COMP'!H:H)/1000000 -> -3712.1714 | E19: =SUMIF('BG COMP'!$A:$A,$A19,'BG COMP'!I:I)/1000000 -> -712.75 | F19: =SUMIF('BG COMP'!$A:$A,$A19,'BG COMP'!J:J)/1000000 -> -967.5137
C20: Trésorerie et équivalents | D20: =D18+D19 -> -4287.7231 | E20: =E18+E19 -> 149.77869 | F20: =F18+F19 -> -2073.0749
A21: Emprunts et dettes financières | C21: Emprunts et dettes financières | D21: =SUMIF('BG COMP'!$A:$A,$A21,'BG COMP'!H:H)/1000000 -> -12536.742 | E21: =SUMIF('BG COMP'!$A:$A,$A21,'BG COMP'!I:I)/1000000 -> -15073.618 | F21: =SUMIF('BG COMP'!$A:$A,$A21,'BG COMP'!J:J)/1000000 -> -13746.804
A22: Dettes de location-acquisition | C22: Dettes de location-acquisition | D22: =SUMIF('BG COMP'!$A:$A,$A22,'BG COMP'!H:H)/1000000 -> -167.79815 | E22: =SUMIF('BG COMP'!$A:$A,$A22,'BG COMP'!I:I)/1000000 -> -81.42723 | F22: =SUMIF('BG COMP'!$A:$A,$A22,'BG COMP'!J:J)/1000000 -> 1e-06
C23: Dettes financières | D23: =D21+D22 -> -12704.54 | E23: =E21+E22 -> -15155.045 | F23: =F21+F22 -> -13746.804
A24: Provisions pour risques et charges | C24: Provisions pour risques et charges | D24: =SUMIF('BG COMP'!$A:$A,$A24,'BG COMP'!H:H)/1000000 -> -240.85634 | E24: =SUMIF('BG COMP'!$A:$A,$A24,'BG COMP'!I:I)/1000000 -> -104.85771 | F24: =SUMIF('BG COMP'!$A:$A,$A24,'BG COMP'!J:J)/1000000 -> -84.794307
C25: Trésorerie / (dette) nette | D25: =D20+D23+D24 -> -17233.119 | E25: =E20+E23+E24 -> -15110.124 | F25: =F20+F23+F24 -> -15904.673
A26: Provisions pour risques à court terme | C26: Provisions pour risques à court terme | D26: =SUMIF('BG COMP'!$A:$A,$A26,'BG COMP'!H:H)/1000000 -> -8.623752 | E26: =SUMIF('BG COMP'!$A:$A,$A26,'BG COMP'!I:I)/1000000 -> -8.623752 | F26: =SUMIF('BG COMP'!$A:$A,$A26,'BG COMP'!J:J)/1000000 -> -8.623752
C27: Actif net | D27: =D7+D17+D25+D26 -> 6997.4183 | E27: =E7+E17+E25+E26 -> 8038.734 | F27: =F7+F17+F25+F26 -> 10078.795
A28: Capital | C28: Capital | D28: =-SUMIF('BG COMP'!$A:$A,$A28,'BG COMP'!H:H)/1000000 -> 5988.0253 | E28: =-SUMIF('BG COMP'!$A:$A,$A28,'BG COMP'!I:I)/1000000 -> 5988.0253 | F28: =-SUMIF('BG COMP'!$A:$A,$A28,'BG COMP'!J:J)/1000000 -> 5988.0253
A29: Réserves | C29: Réserves | D29: =-SUMIF('BG COMP'!$A:$A,$A29,'BG COMP'!H:H)/1000000 -> 0 | E29: =-SUMIF('BG COMP'!$A:$A,$A29,'BG COMP'!I:I)/1000000 -> 0 | F29: =-SUMIF('BG COMP'!$A:$A,$A29,'BG COMP'!J:J)/1000000 -> 0
A30: Report à nouveau | C30: Report à nouveau | D30: =-SUMIF('BG COMP'!$A:$A,$A30,'BG COMP'!H:H)/1000000 -> -889.04517 | E30: =-SUMIF('BG COMP'!$A:$A,$A30,'BG COMP'!I:I)/1000000 -> 409.39298 | F30: =-SUMIF('BG COMP'!$A:$A,$A30,'BG COMP'!J:J)/1000000 -> 2650.7086
A31: Résultat en instance d'affectation | C31: Résultat en instance d'affectation | D31: =-SUMIF('BG COMP'!$A:$A,$A31,'BG COMP'!H:H)/1000000 -> 0 | E31: =-SUMIF('BG COMP'!$A:$A,$A31,'BG COMP'!I:I)/1000000 -> 0 | F31: =-SUMIF('BG COMP'!$A:$A,$A31,'BG COMP'!J:J)/1000000 -> 0
A32: Subventions d'investissement et provisions réglementées | C32: Subventions d'investissement et provisions réglementées | D32: =-SUMIF('BG COMP'!$A:$A,$A32,'BG COMP'!H:H)/1000000 -> 0 | E32: =-SUMIF('BG COMP'!$A:$A,$A32,'BG COMP'!I:I)/1000000 -> 0 | F32: =-SUMIF('BG COMP'!$A:$A,$A32,'BG COMP'!J:J)/1000000 -> 0
C33: Résultat net de l'exercice | D33: ='P&L'!C39/1000000 -> 1897.6215 | E33: ='P&L'!D39/1000000 -> 1641.3156 | F33: ='P&L'!E39/1000000 -> 1440.0608
C34: Capitaux propres | D34: =D28+D29+D30+D31+D32+D33 -> 6996.6017 | E34: =E28+E29+E30+E31+E32+E33 -> 8038.734 | F34: =F28+F29+F30+F31+F32+F33 -> 10078.795
C35: Contrôle : actif net − capitaux propres | D35: =D27-D34 -> 0.816623 | E35: =E27-E34 -> 0 | F35: =F27-F34 -> 0
A37: Source : balance générale comparée, classée selon le plan SYSCOHADA (feuille Plan SYSCOHADA).

Sheet Valorisation >

Sheet DCF
B1: DCF — flux de trésorerie disponibles
B2: M FCFA · actualisation en fin d'année · valeur terminale de Gordon-Shapiro · prévisionnel estimé à partir d'hypothèses
B4: Hypothèses
B5: CMPC, monnaie locale | C5: 0.12142858
B6: Croissance à l'infini (g) | C6: 0.02
B7: Taux d'IS normatif | C7: 0.25
B8: Dette nette (négative : trésorerie nette) | C8: 15904.673
B9: Chiffre d'affaires de base, FY23 | C9: 24413.824
B10: Marge d'EBITDA | C10: 0.144
B11: D&A, en % du CA | C11: 0.043
B12: Variation du BFR, en % de la variation du CA | C12: 0.327
B14: M FCFA | C14: FY24 | D14: FY25 | E14: FY26 | F14: FY27 | G14: FY28
B15: Croissance du CA | C15: -0.002 | D15: -0.002 | E15: -0.002 | F15: -0.002 | G15: -0.002
B16: Chiffre d'affaires | C16: =$C$9*(1+C15) -> 24364.997 | D16: =C16*(1+D15) -> 24316.267 | E16: =D16*(1+E15) -> 24267.634 | F16: =E16*(1+F15) -> 24219.099 | G16: =F16*(1+G15) -> 24170.661
B17: EBITDA | C17: =C16*$C$10 -> 3508.5595 | D17: =D16*$C$10 -> 3501.5424 | E17: =E16*$C$10 -> 3494.5393 | F17: =F16*$C$10 -> 3487.5502 | G17: =G16*$C$10 -> 3480.5751
B18: D&A | C18: =C16*$C$11 -> 1047.6949 | D18: =D16*$C$11 -> 1045.5995 | E18: =E16*$C$11 -> 1043.5083 | F18: =F16*$C$11 -> 1041.4213 | G18: =G16*$C$11 -> 1039.3384
B19: EBIT | C19: =C17-C18 -> 2460.8647 | D19: =D17-D18 -> 2455.9429 | E19: =E17-E18 -> 2451.031 | F19: =F17-F18 -> 2446.129 | G19: =G17-G18 -> 2441.2367
B20: CapEx | C20: 1047.7 | D20: 1045.6 | E20: 1043.5 | F20: 1041.4 | G20: 1039.3
B21: Variation du BFR (signée comme un flux) | C21: =-$C$12*(C16-$C$9) -> 15.966641 | D21: =-$C$12*(D16-C16) -> 15.934708 | E21: =-$C$12*(E16-D16) -> 15.902838 | F21: =-$C$12*(F16-E16) -> 15.871033 | G21: =-$C$12*(G16-F16) -> 15.839291
B23: (−) Impôt normatif sur l'EBIT | C23: =-MAX(0,C19)*$C$7 -> -615.21616 | D23: =-MAX(0,D19)*$C$7 -> -613.98573 | E23: =-MAX(0,E19)*$C$7 -> -612.75776 | F23: =-MAX(0,F19)*$C$7 -> -611.53225 | G23: =-MAX(0,G19)*$C$7 -> -610.30918
B24: NOPAT | C24: =C19+C23 -> 1845.6485 | D24: =D19+D23 -> 1841.9572 | E24: =E19+E23 -> 1838.2733 | F24: =F19+F23 -> 1834.5967 | G24: =G19+G23 -> 1830.9275
B25: FCFF = NOPAT + D&A − CapEx + variation du BFR | C25: =C24+C18-C20+C21 -> 1861.61 | D25: =D24+D18-D20+D21 -> 1857.8914 | E25: =E24+E18-E20+E21 -> 1854.1844 | F25: =F24+F18-F20+F21 -> 1850.489 | G25: =G24+G18-G20+G21 -> 1846.8052
B26: Période d'actualisation (années) | C26: 1 | D26: 2 | E26: 3 | F26: 4 | G26: 5
B27: Facteur d'actualisation | C27: =1/(1+$C$5)^C26 -> 0.89171974 | D27: =1/(1+$C$5)^D26 -> 0.79516409 | E27: =1/(1+$C$5)^E26 -> 0.70906352 | F27: =1/(1+$C$5)^F26 -> 0.63228593 | G27: =1/(1+$C$5)^G26 -> 0.56382185
B28: FCFF actualisé | C28: =C25*C27 -> 1660.0344 | D28: =D25*D27 -> 1477.3285 | E28: =E25*E27 -> 1314.7345 | F28: =F25*F27 -> 1170.0382 | G28: =G25*G27 -> 1041.2691
B29: Somme des FCFF actualisés (FY24-FY38) | G29: =SUM(C28:G28) -> 6663.4047
B30: Valeur terminale à fin FY28 (Gordon-Shapiro) | G30: =G25*(1+$C$6)/($C$5-$C$6) -> 18572.096
B31: Valeur terminale actualisée | G31: =G30*G27 -> 10471.354
B32: Valeur d'entreprise (VE) | G32: =G29+G31 -> 17134.758
B34: Poids de la valeur terminale | C34: =IFERROR(G31/G32,"n.a") -> 0.61111767
B35: (−) Dette nette | C35: =$C$8 -> 15904.673
B36: Valeur des fonds propres | C36: =G32-C35 -> 1230.0849
B39: Test de sensibilité (mFCFA)
D40: 4.8615742e+11 | E40: 0.014 | F40: 0.017 | G40: 0.02 | H40: 0.023 | I40: 0.026
B41: WACC Indirect | D41: 0.103 | E41: 603873 | F41: 620698 | G41: 638746 | H41: 658156 | I41: 679089
D42: 0.113 | E42: 527198 | F42: 539903 | G42: 553432 | H42: 567867 | I42: 583305 | K42: 0.01
D43: 0.123 | E43: 465975 | F43: 475782 | G43: 486162 | H43: 497169 | I43: 508860 | K43: 0.01
D44: 0.133 | E44: 416173 | F44: 423881 | G44: 432000 | H44: 440564 | I44: 449611 | K44: 0.01
D45: 0.143 | E45: 375027 | F45: 381178 | G45: 387631 | H45: 394407 | I45: 401533

Sheet Comparables
B1: Comparables — VE / EBITDA
B2: Secteur Oil, Gas and Consumable Fuels · médiane de 20 sociétés à EBITDA positif, exercice 2025 · VE = capitalisation + dette
B4: Société | C4: Capitalisation (M FCFA) | D4: Dette (M FCFA) | E4: VE (M FCFA) | F4: EBITDA 2025 (M FCFA) | G4: VE / EBITDA
B5: ExxonMobil Holdings Corporation | C5: 2.8353166e+08 | D5: 28206582 | E5: =C5+D5 -> 3.1173824e+08 | F5: 34522524 | G5: =E5/F5 -> 9.0299956
B6: Chevron Corporation | C6: 1.7024484e+08 | D6: 26114847 | E6: =C6+D6 -> 1.9635969e+08 | F6: 21875814 | G6: =E6/F6 -> 8.9761089
B7: Shell plc | C7: 1.1786243e+08 | D7: 42286129 | E7: =C7+D7 -> 160148554 | F7: 27704753 | G7: =E7/F7 -> 5.7805443
B8: TotalEnergies SE | C8: 78179940 | D8: 34315298 | E8: =C8+D8 -> 1.1249524e+08 | F8: 19049997 | G8: =E8/F8 -> 5.9052628
B9: ConocoPhillips | C9: 64626793 | D9: 13628684 | E9: =C9+D9 -> 78255477 | F9: 14045376 | G9: =E9/F9 -> 5.5716184
B10: Enbridge Inc. | C10: 58422793 | D10: 43354380 | E10: =C10+D10 -> 1.0177717e+08 | F10: 7270058.9 | G10: =E10/F10 -> 13.999498
B11: BP p.l.c. | C11: 49782874 | D11: 40521227 | E11: =C11+D11 -> 90304101 | F11: 17537391 | G11: =E11/F11 -> 5.1492323
B12: The Williams Companies, Inc. | C12: 41012017 | D12: 16505937 | E12: =C12+D12 -> 57517955 | F12: 3939634.7 | G12: =E12/F12 -> 14.599819
B13: Canadian Natural Resources Limited | C13: 39460861 | D13: 8036527 | E13: =C13+D13 -> 47497388 | F13: 6583474.6 | G13: =E13/F13 -> 7.2146383
B14: Enterprise Products Partners L.P. | C14: 38748544 | D14: 19488225 | E14: =C14+D14 -> 58236769 | F14: 5567924.1 | G14: =E14/F14 -> 10.459332
B15: Kinder Morgan, Inc. | C15: 34168734 | D15: 18076415 | E15: =C15+D15 -> 52245148 | F15: 4136122.3 | G15: =E15/F15 -> 12.631432
B16: TC Energy Corporation | C16: 32059227 | D16: 24864215 | E16: =C16+D16 -> 56923442 | F16: 3963558.6 | G16: =E16/F16 -> 14.361701
... B24: ONEOK, Inc. | C24: 25838585 | D24: 18466381 | E24: =C24+D24 -> 44304966 | F24: 4264595 | G24: =E24/F24 -> 10.389021
B27: MTN CI - Valorisation selon les comparables boursiers
B28: mFCFA | C28: Min. | D28: Med. | E28: Max
B29: EBITDA de référence, FY23 (M FCFA) — balance générale SYSCOHADA | C29: 3504.3004 | D29: 3504.3004 | E29: 3504.3004
B30: Multiple d'EBITDA | C30: =MIN(G5:G24) -> 5.1492323 | D30: =MEDIAN(G5:G24) -> 8.7116726 | E30: =MAX(G5:G24) -> 14.599819
B31: Valeur d'entreprise | C31: =C29*C30 -> 18044.457 | D31: =D29*D30 -> 30528.318 | E31: =E29*E30 -> 51162.153
B32: Dette financière nette ajustée
B33: Valeur des fonds propres
B34: Source: Analyse Forvis Mazars

Sheet Synthèse
B1: Synthèse des valorisations
B2: M FCFA · moyenne arithmétique des VE · poids modifiables en colonne D
B4: Méthode | C4: VE | D4: Poids | E4: VE pondérée
B5: DCF | C5: =DCF!$G$32 -> 17134.758 | D5: 0.5 | E5: =C5*D5 -> 8567.3791
B6: Comparables | C6: =Comparables!#REF! -> #REF! | D6: 0.5 | E6: =C6*D6 -> #REF!
B7: Somme des poids | D7: =SUM(D5:D6) -> 1
B9: Valeur d'entreprise retenue | C9: =SUM(E5:E6) -> #REF!
B10: (−) Dette nette | C10: =DCF!$C$8 -> 15904.673
B11: Valeur des fonds propres | C11: =C9-C10 -> #REF!

Sheet UPSLIDE_UndoFormatting
A1: 39 | B1: 7

Sheet UPSLIDE_Undo
A1: 39 | B1: 7
