Workbook
Name IQ_CH: 110000
Name IQ_CQ: 5000
Name IQ_CY: 10000
Name IQ_DAILY: 500000
Name IQ_FH: 100000
Name IQ_FQ: 500
Name IQ_FY: 1000
Name IQ_LTM: 2000
Name IQ_MONTH: 15000
Name IQ_NTM: 6000
Name IQ_WEEK: 50000
Name IQ_YTD: 3000

Sheet BG COMP BACI
A3: 1C | B3: 2C | C3: 3C | D3: 4C | E3: Numéro de compte | F3: Mapping | G3: LB | H3: FY22 | I3: FY23 | J3: FY24 | K3: FY25
A4: =LEFT(B4,1) -> 1 | B4: =LEFT(C4,2) -> 10 | C4: =LEFT(D4,3) -> 101 | D4: =LEFT(E4,4) -> 1013 | E4: 101300 | F4: Capital | G4: Capital souscrit, appelé, versé, non amorti | H4: -10000000 | I4: -10000000 | J4: -10000000 | K4: -10000000
A5: =LEFT(B5,1) -> 1 | B5: =LEFT(C5,2) -> 11 | C5: =LEFT(D5,3) -> 111 | D5: =LEFT(E5,4) -> 1110 | E5: 111000 | F5: Reserve légale | G5: RÉSERVE LÉGALE | H5: -567637 | I5: -754257 | J5: -754257 | K5: -754257
A6: =LEFT(B6,1) -> 1 | B6: =LEFT(C6,2) -> 11 | C6: =LEFT(D6,3) -> 118 | D6: =LEFT(E6,4) -> 1188 | E6: 118800 | F6: Reserve diverses | G6: Réserves diverses | H6: -10785102 | I6: -10785102 | J6: -10785102 | K6: -10785102
A7: =LEFT(B7,1) -> 1 | B7: =LEFT(C7,2) -> 12 | C7: =LEFT(D7,3) -> 121 | D7: =LEFT(E7,4) -> 1211 | E7: 121100 | F7: Report a nouveau | G7: REPORT À NOUVEAU CRÉDITEUR | K7: -652824
A8: =LEFT(B8,1) -> 1 | B8: =LEFT(C8,2) -> 12 | C8: =LEFT(D8,3) -> 129 | D8: =LEFT(E8,4) -> 1291 | E8: 129100 | F8: Report a nouveau | G8: Perte nette à reporter | H8: 34651142 | I8: 32971560 | J8: 32971560 | K8: 34656288
A9: =LEFT(B9,1) -> 1 | B9: =LEFT(C9,2) -> 13 | C9: =LEFT(D9,3) -> 130 | D9: =LEFT(E9,4) -> 1300 | E9: 130000 | G9: Résultat en attente d'affectation | K9: 0
A10: =LEFT(B10,1) -> 1 | B10: =LEFT(C10,2) -> 13 | C10: =LEFT(D10,3) -> 130 | D10: =LEFT(E10,4) -> 1301 | E10: 130100 | F10: RIA | G10: Résultat en instance d'affectation : Bénéfice | H10: 0 | I10: 0 | J10: 1684728 | K10: 0
A11: =LEFT(B11,1) -> 1 | B11: =LEFT(C11,2) -> 13 | C11: =LEFT(D11,3) -> 130 | D11: =LEFT(E11,4) -> 1309 | E11: 130900 | F11: RIA | G11: Résultat en instance d'affectation : Perte | H11: 0 | I11: 0 | J11: 0 | K11: 0
A12: =LEFT(B12,1) -> 1 | B12: =LEFT(C12,2) -> 16 | C12: =LEFT(D12,3) -> 162 | D12: =LEFT(E12,4) -> 1620 | E12: 162000 | F12: Emprunt | G12: Emprunts auprès des établissements de crédit | H12: 0 | I12: 0 | J12: 0
A13: =LEFT(B13,1) -> 1 | B13: =LEFT(C13,2) -> 16 | C13: =LEFT(D13,3) -> 162 | D13: =LEFT(E13,4) -> 1620 | E13: 162010 | F13: Emprunt | G13: Emprunts auprès des établissements de crédit - CMT 150M | K13: -124833207
A14: =LEFT(B14,1) -> 1 | B14: =LEFT(C14,2) -> 16 | C14: =LEFT(D14,3) -> 162 | D14: =LEFT(E14,4) -> 1621 | E14: 162100 | F14: Emprunt | G14: Emprunts auprès des établissements de crédit - CMT 30M | H14: -5344683 | I14: 0 | J14: 0 | K14: 0
A15: =LEFT(B15,1) -> 1 | B15: =LEFT(C15,2) -> 16 | C15: =LEFT(D15,3) -> 162 | D15: =LEFT(E15,4) -> 1622 | E15: 162200 | F15: Emprunt | G15: Emprunts auprès des établissements de crédit - CMT 20M | H15: -8539331 | I15: 0 | J15: 0 | K15: 0
A16: =LEFT(B16,1) -> 1 | B16: =LEFT(C16,2) -> 16 | C16: =LEFT(D16,3) -> 162 | D16: =LEFT(E16,4) -> 1623 | E16: 162300 | F16: Emprunt | G16: Emprunts auprès des établissements de crédit - CMT 30M Véhicule | I16: -24895681 | J16: 0 | K16: 0
A17: =LEFT(B17,1) -> 1 | B17: =LEFT(C17,2) -> 16 | C17: =LEFT(D17,3) -> 166 | D17: =LEFT(E17,4) -> 1662 | E17: 166200 | F17: Emprunt | G17: Emprunts auprès des établissements de crédit | K17: 0
A18: =LEFT(B18,1) -> 1 | B18: =LEFT(C18,2) -> 16 | C18: =LEFT(D18,3) -> 166 | D18: =LEFT(E18,4) -> 1662 | E18: 166200 | F18: Emprunt | G18: sur emprunts et dettes auprès des établissements de crédit | H18: -287539 | I18: 0 | J18: 0 | K18: 0
A19: =LEFT(B19,1) -> 1 | B19: =LEFT(C19,2) -> 17 | C19: =LEFT(D19,3) -> 173 | D19: =LEFT(E19,4) -> 1730 | E19: 173000 | F19: Dette sur crédit bail | G19: DETTES DE LOCATION ACQUISITION / CREDIT - BAIL MOBILIER | H19: -13011545 | I19: -7198580 | J19: -3332695 | K19: 0
A20: =LEFT(B20,1) -> 1 | B20: =LEFT(C20,2) -> 17 | C20: =LEFT(D20,3) -> 173 | D20: =LEFT(E20,4) -> 1731 | E20: 173100 | F20: Dette sur crédit bail | G20: DETTES DE LOCATION ACQUISITION / CREDIT - BAIL MOBILIER - CMT 30M véhicule | J20: -17546207 | K20: -9523249
A21: =LEFT(B21,1) -> 1 | B21: =LEFT(C21,2) -> 17 | C21: =LEFT(D21,3) -> 176 | D21: =LEFT(E21,4) -> 1763 | E21: 176300 | F21: Dette sur crédit bail | G21: sur dettes de location acquisition / crédit-bail mobilier | H21: -397709 | I21: -397709 | J21: -11983 | K21: -2498
A22: =LEFT(B22,1) -> 1 | B22: =LEFT(C22,2) -> 19 | C22: =LEFT(D22,3) -> 196 | D22: =LEFT(E22,4) -> 1961 | E22: 196100 | F22: Provisions pour risques et charges | G22: Provisions pour pensions et obligations similaires - engagement de retraite | H22: -4359763 | I22: -7493797 | J22: -10620691 | K22: -24352976
A23: =LEFT(B23,1) -> 2 | B23: =LEFT(C23,2) -> 21 | C23: =LEFT(D23,3) -> 213 | D23: =LEFT(E23,4) -> 2131 | E23: 213100 | F23: Logiciels | G23: Logiciels | K23: 1000000
A24: =LEFT(B24,1) -> 2 | B24: =LEFT(C24,2) -> 21 | C24: =LEFT(D24,3) -> 219 | D24: =LEFT(E24,4) -> 2193 | E24: 219300 | F24: Immobilisations en cours | G24: Logiciels et internet | I24: 116449580 | J24: 184137292 | K24: 245606888
A25: =LEFT(B25,1) -> 2 | B25: =LEFT(C25,2) -> 23 | C25: =LEFT(D25,3) -> 235 | D25: =LEFT(E25,4) -> 2351 | E25: 235100 | F25: Aménagements de bureau | G25: Installations générales | K25: 0
A26: =LEFT(B26,1) -> 2 | B26: =LEFT(C26,2) -> 23 | C26: =LEFT(D26,3) -> 235 | D26: =LEFT(E26,4) -> 2358 | E26: 235800 | F26: Aménagements de bureau | G26: Autres Aménagements de bureau | H26: 3101693 | I26: 3563557 | J26: 6445190 | K26: 22477778
A27: =LEFT(B27,1) -> 2 | B27: =LEFT(C27,2) -> 24 | C27: =LEFT(D27,3) -> 244 | D27: =LEFT(E27,4) -> 2441 | E27: 244100 | F27: Matériel et mobilier de bureau | G27: Matériel de bureau | K27: 0
A28: =LEFT(B28,1) -> 2 | B28: =LEFT(C28,2) -> 24 | C28: =LEFT(D28,3) -> 244 | D28: =LEFT(E28,4) -> 2442 | E28: 244200 | F28: Matériel informatique | G28: Matériel informatique | H28: 7641557 | I28: 24074835 | J28: 28896075 | K28: 34367685
A29: =LEFT(B29,1) -> 2 | B29: =LEFT(C29,2) -> 24 | C29: =LEFT(D29,3) -> 244 | D29: =LEFT(E29,4) -> 2444 | E29: 244400 | F29: Matériel et mobilier de bureau | G29: Mobilier de bureau | H29: 10808801 | I29: 11713348 | J29: 14736586 | K29: 27311138
A30: =LEFT(B30,1) -> 2 | B30: =LEFT(C30,2) -> 24 | C30: =LEFT(D30,3) -> 245 | D30: =LEFT(E30,4) -> 2456 | E30: 245600 | F30: Matériel de transport | G30: Matériel de transport de location-acquisition | H30: 15000000 | I30: 45700000 | J30: 45700000 | K30: 45700000
A31: =LEFT(B31,1) -> 2 | B31: =LEFT(C31,2) -> 27 | C31: =LEFT(D31,3) -> 275 | D31: =LEFT(E31,4) -> 2751 | E31: 275100 | F31: Dépots et cautionnements | G31: Dépôts pour loyers d’avance | K31: 3000000
A32: =LEFT(B32,1) -> 2 | B32: =LEFT(C32,2) -> 28 | C32: =LEFT(D32,3) -> 281 | D32: =LEFT(E32,4) -> 2813 | E32: 281300 | F32: Logiciels | G32: Amortissements des logiciels | K32: -269444
A33: =LEFT(B33,1) -> 2 | B33: =LEFT(C33,2) -> 28 | C33: =LEFT(D33,3) -> 283 | D33: =LEFT(E33,4) -> 2834 | E33: 283400 | F33: Ouvrages d'infrastructure | G33: Amortissements des installations techniques | H33: -1278605 | I33: -1898944 | J33: 0 | K33: 0
A34: =LEFT(B34,1) -> 2 | B34: =LEFT(C34,2) -> 28 | C34: =LEFT(D34,3) -> 283 | D34: =LEFT(E34,4) -> 2835 | E34: 283500 | F34: Ouvrages d'infrastructure | G34: Amortissements des aménagements de bureaux | J34: -3122176 | K34: -789989
A35: =LEFT(B35,1) -> 2 | B35: =LEFT(C35,2) -> 28 | C35: =LEFT(D35,3) -> 284 | D35: =LEFT(E35,4) -> 2844 | E35: 284400 | F35: Matériel et mobilier de bureau | G35: Amortissements du matériel et mobilier | H35: -7909488 | I35: -15510794 | J35: 0 | K35: 0
A36: =LEFT(B36,1) -> 2 | B36: =LEFT(C36,2) -> 28 | C36: =LEFT(D36,3) -> 284 | D36: =LEFT(E36,4) -> 2844 | E36: 284410 | F36: Matériel et mobilier de bureau | G36: Amortissements du mobilier de bureau | J36: -4628771
A37: =LEFT(B37,1) -> 2 | B37: =LEFT(C37,2) -> 28 | C37: =LEFT(D37,3) -> 284 | D37: =LEFT(E37,4) -> 2844 | E37: 284420 | F37: Matériel et mobilier de bureau | G37: mortissements du mobilier de bureau | K37: -6629725
A38: =LEFT(B38,1) -> 2 | B38: =LEFT(C38,2) -> 28 | C38: =LEFT(D38,3) -> 284 | D38: =LEFT(E38,4) -> 2844 | E38: 284420 | F38: Matériel et mobilier de bureau | G38: Amortissements du matériel informatique | J38: -22714796
A39: =LEFT(B39,1) -> 2 | B39: =LEFT(C39,2) -> 28 | C39: =LEFT(D39,3) -> 284 | D39: =LEFT(E39,4) -> 2844 | E39: 284420 | F39: Matériel informatique | G39: mortissements du matériel informatique | K39: -30012484
A40: =LEFT(B40,1) -> 2 | B40: =LEFT(C40,2) -> 28 | C40: =LEFT(D40,3) -> 284 | D40: =LEFT(E40,4) -> 2845 | E40: 284500 | F40: Matériel de transport | G40: Amortissements du matériel de transport | H40: -1623288 | I40: -7302072 | J40: -32768521 | K40: -44007109
A41: =LEFT(B41,1) -> 4 | B41: =LEFT(C41,2) -> 40 | C41: =LEFT(D41,3) -> 401 | D41: =LEFT(E41,4) -> 4011 | E41: 401100 | F41: Fournisseurs | G41: Fournisseurs | H41: -1707149 | I41: -5038100 | J41: -47075821 | K41: -40067935
A42: =LEFT(B42,1) -> 4 | B42: =LEFT(C42,2) -> 40 | C42: =LEFT(D42,3) -> 408 | D42: =LEFT(E42,4) -> 4081 | E42: 408100 | F42: Fournisseurs | G42: Fournisseurs - Factures Non Parvenues | H42: -3418443 | I42: -36218655 | J42: -959948 | K42: -5083299
A43: =LEFT(B43,1) -> 4 | B43: =LEFT(C43,2) -> 40 | C43: =LEFT(D43,3) -> 409 | D43: =LEFT(E43,4) -> 4091 | E43: 409100 | F43: Fournisseurs, débiteurs | G43: Fournisseurs avances et acomptes versés | H43: 2478289 | I43: 7106398 | J43: 6853289 | K43: 12356112
A44: =LEFT(B44,1) -> 4 | B44: =LEFT(C44,2) -> 40 | C44: =LEFT(D44,3) -> 409 | D44: =LEFT(E44,4) -> 4098 | E44: 409800 | G44: Rabais, Remises, Ristournes et autres avoirs à obtenir | K44: 0
A45: =LEFT(B45,1) -> 4 | B45: =LEFT(C45,2) -> 41 | C45: =LEFT(D45,3) -> 411 | D45: =LEFT(E45,4) -> 4111 | E45: 411100 | F45: Clients | G45: Clients | H45: 226238418 | I45: 159820453 | J45: 294476153 | K45: 276204832
A46: =LEFT(B46,1) -> 4 | B46: =LEFT(C46,2) -> 41 | C46: =LEFT(D46,3) -> 418 | D46: =LEFT(E46,4) -> 4181 | E46: 418100 | F46: Clients | G46: Clients, factures à établir | H46: 239055001 | I46: 0 | J46: 0 | K46: 52215467
A47: =LEFT(B47,1) -> 4 | B47: =LEFT(C47,2) -> 41 | C47: =LEFT(D47,3) -> 419 | D47: =LEFT(E47,4) -> 4191 | E47: 419100 | F47: Clients, créditeurs | G47: Clients, avances et acomptes reçus | H47: 0 | I47: -4115175 | J47: 0 | K47: 0
A48: =LEFT(B48,1) -> 4 | B48: =LEFT(C48,2) -> 42 | C48: =LEFT(D48,3) -> 421 | D48: =LEFT(E48,4) -> 4211 | E48: 421100 | F48: Personnel | G48: Personnel, avances | H48: 710000 | I48: 400000 | J48: 45000 | K48: 100000
A49: =LEFT(B49,1) -> 4 | B49: =LEFT(C49,2) -> 42 | C49: =LEFT(D49,3) -> 422 | D49: =LEFT(E49,4) -> 4220 | E49: 422000 | F49: Personnel | G49: PERSONNEL, RÉMUNÉRATIONS DUES | H49: 0 | I49: -103818 | J49: -17726977 | K49: -31092304
A50: =LEFT(B50,1) -> 4 | B50: =LEFT(C50,2) -> 42 | C50: =LEFT(D50,3) -> 428 | D50: =LEFT(E50,4) -> 4281 | E50: 428100 | F50: Personnel | G50: Dettes provisionnées pour congés à payer | H50: -7542536 | I50: -13514386 | J50: -38705023 | K50: -58688513
A51: =LEFT(B51,1) -> 4 | B51: =LEFT(C51,2) -> 43 | C51: =LEFT(D51,3) -> 431 | D51: =LEFT(E51,4) -> 4311 | E51: 431100 | F51: Charges sociales | G51: Prestations familiales | H51: -990150 | I51: 0 | J51: 0 | K51: -750377
A52: =LEFT(B52,1) -> 4 | B52: =LEFT(C52,2) -> 43 | C52: =LEFT(D52,3) -> 431 | D52: =LEFT(E52,4) -> 4312 | E52: 431200 | F52: Charges sociales | G52: Accidents de travail | H52: -516600 | I52: 0 | J52: 0 | K52: -391500
A53: =LEFT(B53,1) -> 4 | B53: =LEFT(C53,2) -> 43 | C53: =LEFT(D53,3) -> 431 | D53: =LEFT(E53,4) -> 4313 | E53: 431300 | F53: Charges sociales | G53: Caisse de retraite obligatoire | H53: -9084320 | I53: 0 | J53: -55294687 | K53: -48173044
A54: =LEFT(B54,1) -> 4 | B54: =LEFT(C54,2) -> 43 | C54: =LEFT(D54,3) -> 431 | D54: =LEFT(E54,4) -> 4318 | E54: 431800 | F54: Charges sociales | G54: Autres cotisations sociales | H54: 0 | I54: -2984709 | J54: 0 | K54: -4219556
A55: =LEFT(B55,1) -> 4 | B55: =LEFT(C55,2) -> 43 | C55: =LEFT(D55,3) -> 431 | D55: =LEFT(E55,4) -> 4318 | E55: 431800 | F55: Charges sociales | G55: Cotisation CMU | J55: -192000
A56: =LEFT(B56,1) -> 4 | B56: =LEFT(C56,2) -> 43 | C56: =LEFT(D56,3) -> 433 | D56: =LEFT(E56,4) -> 4333 | E56: 433300 | F56: Charges sociales | G56: Assurances et organismes de santé-Cotisation CMU | K56: -1163500
A57: =LEFT(B57,1) -> 4 | B57: =LEFT(C57,2) -> 43 | C57: =LEFT(D57,3) -> 438 | D57: =LEFT(E57,4) -> 4382 | E57: 438200 | F57: Charges sociales | G57: Charges sociales sur congés à payer | H57: -761901 | I57: 0 | J57: -1083740 | K57: -4519016
A58: =LEFT(B58,1) -> 4 | B58: =LEFT(C58,2) -> 44 | C58: =LEFT(D58,3) -> 441 | D58: =LEFT(E58,4) -> 4410 | E58: 441000 | F58: Etat, TVA et taxes | G58: ÉTAT, IMPÔT SUR LES BÉNÉFICES | H58: -17108500 | I58: -9493000 | J58: -24462516 | K58: -32412250
A59: =LEFT(B59,1) -> 4 | B59: =LEFT(C59,2) -> 44 | C59: =LEFT(D59,3) -> 442 | D59: =LEFT(E59,4) -> 4421 | E59: 442100 | F59: Etat, TVA et taxes | G59: Impôts et taxes d'Etat | K59: 0
A60: =LEFT(B60,1) -> 4 | B60: =LEFT(C60,2) -> 44 | C60: =LEFT(D60,3) -> 442 | D60: =LEFT(E60,4) -> 4421 | E60: 442110 | F60: Etat, TVA et taxes | G60: Impôts et taxes d'Etat- ITS charges patronale | H60: -2226784 | I60: -381120 | J60: -381120 | K60: 0
A61: =LEFT(B61,1) -> 4 | B61: =LEFT(C61,2) -> 44 | C61: =LEFT(D61,3) -> 442 | D61: =LEFT(E61,4) -> 4421 | E61: 442120 | F61: Etat, TVA et taxes | G61: Impôts et taxes d'Etat- Taxe d'apprentissage | H61: -959467 | I61: -127043 | J61: -1689308 | K61: -1375678
A62: =LEFT(B62,1) -> 4 | B62: =LEFT(C62,2) -> 44 | C62: =LEFT(D62,3) -> 442 | D62: =LEFT(E62,4) -> 4421 | E62: 442130 | F62: Etat, TVA et taxes | G62: Impôts et taxes d'Etat - Taxe de la formation continue | H62: -1765002 | I62: -109254 | J62: -4796050 | K62: -1860405
A63: =LEFT(B63,1) -> 4 | B63: =LEFT(C63,2) -> 44 | C63: =LEFT(D63,3) -> 442 | D63: =LEFT(E63,4) -> 4421 | E63: 442140 | F63: Etat, TVA et taxes | G63: Impôts et taxes d'Etat - Taxe de la formation continue Regul | H63: -976093 | I63: 0 | J63: 0 | K63: -8475268
A64: =LEFT(B64,1) -> 4 | B64: =LEFT(C64,2) -> 44 | C64: =LEFT(D64,3) -> 442 | D64: =LEFT(E64,4) -> 4428 | E64: 442800 | F64: Etat, TVA et taxes | G64: Autres impôts et taxes | I64: 0 | J64: -441731 | K64: 0
A65: =LEFT(B65,1) -> 4 | B65: =LEFT(C65,2) -> 44 | C65: =LEFT(D65,3) -> 442 | D65: =LEFT(E65,4) -> 4428 | E65: 442801 | F65: Etat, TVA et taxes | G65: Autres impôts et taxes - Pénalités | K65: -220865
A66: =LEFT(B66,1) -> 4 | B66: =LEFT(C66,2) -> 44 | C66: =LEFT(D66,3) -> 443 | D66: =LEFT(E66,4) -> 4431 | E66: 443100 | F66: Etat, TVA et taxes | G66: T.V.A. facturée sur ventes | H66: -62705700 | I66: -116093982 | J66: -42430786 | K66: -226164548
A67: =LEFT(B67,1) -> 4 | B67: =LEFT(C67,2) -> 44 | C67: =LEFT(D67,3) -> 443 | D67: =LEFT(E67,4) -> 4432 | E67: 443200 | F67: Etat, TVA et taxes | G67: T.V.A. facturée sur prestations de services | H67: -166248997 | I67: -74683399 | J67: -244644746 | K67: -411666595
A68: =LEFT(B68,1) -> 4 | B68: =LEFT(C68,2) -> 44 | C68: =LEFT(D68,3) -> 443 | D68: =LEFT(E68,4) -> 4435 | E68: 443500 | F68: Etat, TVA et taxes | G68: T.V.A sur factures à établir | K68: -7965071
A69: =LEFT(B69,1) -> 4 | B69: =LEFT(C69,2) -> 44 | C69: =LEFT(D69,3) -> 444 | D69: =LEFT(E69,4) -> 4441 | E69: 444100 | F69: Etat, TVA et taxes | G69: État, T.V.A. due | H69: -37801893 | I69: -37840921 | J69: -22148427 | K69: -32001006
A70: =LEFT(B70,1) -> 4 | B70: =LEFT(C70,2) -> 44 | C70: =LEFT(D70,3) -> 444 | D70: =LEFT(E70,4) -> 4449 | E70: 444900 | F70: Etat, TVA et taxes | G70: État, crédit de T.V.A. à reporter | H70: 0 | I70: 622413 | J70: 0 | K70: 0
A71: =LEFT(B71,1) -> 4 | B71: =LEFT(C71,2) -> 44 | C71: =LEFT(D71,3) -> 445 | D71: =LEFT(E71,4) -> 4451 | E71: 445100 | F71: Etat, TVA et taxes | G71: T.V.A. récupérable sur immobilisations | H71: 1469143 | I71: 2121473 | J71: 2121473 | K71: 0
A72: =LEFT(B72,1) -> 4 | B72: =LEFT(C72,2) -> 44 | C72: =LEFT(D72,3) -> 445 | D72: =LEFT(E72,4) -> 4452 | E72: 445200 | F72: Etat, TVA et taxes | G72: T.V.A. récupérable sur achats | H72: 43307300 | I72: -2136767 | J72: -1186161 | K72: 118797
A73: =LEFT(B73,1) -> 4 | B73: =LEFT(C73,2) -> 44 | C73: =LEFT(D73,3) -> 445 | D73: =LEFT(E73,4) -> 4453 | E73: 445300 | F73: Etat, TVA et taxes | G73: T.V.A. récupérable sur transport | H73: 15063 | I73: 0 | J73: 0 | K73: 0
A74: =LEFT(B74,1) -> 4 | B74: =LEFT(C74,2) -> 44 | C74: =LEFT(D74,3) -> 445 | D74: =LEFT(E74,4) -> 4454 | E74: 445400 | F74: Etat, TVA et taxes | G74: T.V.A. récupérable sur services extérieurs et autres charges | H74: 3822360 | I74: 26312598 | J74: 29623322 | K74: 1667795
A75: =LEFT(B75,1) -> 4 | B75: =LEFT(C75,2) -> 44 | C75: =LEFT(D75,3) -> 445 | D75: =LEFT(E75,4) -> 4455 | E75: 445500 | F75: Etat, TVA et taxes | G75: T.V.A. récupérable sur factures non parvenues | H75: 274577 | I75: 274577 | J75: 322285 | K75: 546303
A76: =LEFT(B76,1) -> 4 | B76: =LEFT(C76,2) -> 44 | C76: =LEFT(D76,3) -> 446 | D76: =LEFT(E76,4) -> 4460 | E76: 446000 | F76: Etat, TVA et taxes | G76: ÉTAT, AUTRES TAXES SUR LE CHIFFRE D'AFFAIRES | H76: 19721 | I76: -168971 | J76: -1233923 | K76: -1631531
A77: =LEFT(B77,1) -> 4 | B77: =LEFT(C77,2) -> 44 | C77: =LEFT(D77,3) -> 447 | D77: =LEFT(E77,4) -> 4472 | E77: 447200 | F77: Etat, TVA et taxes | G77: Impôts sur salaires | H77: -29191412 | I77: -9735603 | J77: -97754318 | K77: -80201933
A78: =LEFT(B78,1) -> 4 | B78: =LEFT(C78,2) -> 44 | C78: =LEFT(D78,3) -> 447 | D78: =LEFT(E78,4) -> 4478 | E78: 447800 | F78: Etat, TVA et taxes | G78: Autres impôts et contributions | H78: -10286455 | I78: -20879733 | J78: -34780704 | K78: -47998692
A79: =LEFT(B79,1) -> 4 | B79: =LEFT(C79,2) -> 44 | C79: =LEFT(D79,3) -> 447 | D79: =LEFT(E79,4) -> 4478 | E79: 447801 | F79: Etat, TVA et taxes | G79: Retenue PPSSI | K79: -221390
A80: =LEFT(B80,1) -> 4 | B80: =LEFT(C80,2) -> 44 | C80: =LEFT(D80,3) -> 447 | D80: =LEFT(E80,4) -> 4478 | E80: 447810 | F80: Etat, TVA et taxes | G80: Autres impôts et contributions - RIRL | H80: -1632000 | I80: -1088000 | J80: 0 | K80: 0
A81: =LEFT(B81,1) -> 4 | B81: =LEFT(C81,2) -> 44 | C81: =LEFT(D81,3) -> 448 | D81: =LEFT(E81,4) -> 4486 | E81: 448600 | F81: Etat, TVA et taxes | G81: Charges à payer | H81: -211191 | I81: 0 | J81: -2980286 | K81: -1643278
A82: =LEFT(B82,1) -> 4 | B82: =LEFT(C82,2) -> 44 | C82: =LEFT(D82,3) -> 449 | D82: =LEFT(E82,4) -> 4492 | E82: 449200 | F82: Etat, TVA et taxes | G82: État, avances et acomptes versés sur impôts | H82: 0 | I82: 0 | J82: 0 | K82: 0
A83: =LEFT(B83,1) -> 4 | B83: =LEFT(C83,2) -> 46 | C83: =LEFT(D83,3) -> 461 | D83: =LEFT(E83,4) -> 4612 | E83: 461200 | F83: Débiteurs et créditeurs divers | G83: Associés apports en numéraire | H83: 0 | I83: 0 | J83: 0 | K83: 0
A84: =LEFT(B84,1) -> 4 | B84: =LEFT(C84,2) -> 46 | C84: =LEFT(D84,3) -> 462 | D84: =LEFT(E84,4) -> 4621 | E84: 462110 | F84: Débiteurs et créditeurs divers | G84: Associé compte courant - DIOP Ibrahima | H84: 0 | I84: 0 | J84: 0 | K84: 85000000
A85: =LEFT(B85,1) -> 4 | B85: =LEFT(C85,2) -> 46 | C85: =LEFT(D85,3) -> 462 | D85: =LEFT(E85,4) -> 4621 | E85: 462120 | F85: Débiteurs et créditeurs divers | G85: Associé compte courant - KONE Nombel | K85: 15000000
A86: =LEFT(B86,1) -> 4 | B86: =LEFT(C86,2) -> 47 | C86: =LEFT(D86,3) -> 471 | D86: =LEFT(E86,4) -> 4711 | E86: 471100 | F86: Débiteurs et créditeurs divers | G86: Débiteur divers - BAIF | K86: 19800000
A87: =LEFT(B87,1) -> 4 | B87: =LEFT(C87,2) -> 47 | C87: =LEFT(D87,3) -> 471 | D87: =LEFT(E87,4) -> 4711 | E87: 471100 | F87: Débiteurs et créditeurs divers | G87: Débiteurs divers | H87: 0 | I87: 0 | J87: 80810812 | K87: 81810812
A88: =LEFT(B88,1) -> 4 | B88: =LEFT(C88,2) -> 47 | C88: =LEFT(D88,3) -> 471 | D88: =LEFT(E88,4) -> 4711 | E88: 471102 | F88: Débiteurs et créditeurs divers | G88: Débiteurs divers - PLACE AFRICA | K88: 23681758
A89: =LEFT(B89,1) -> 4 | B89: =LEFT(C89,2) -> 47 | C89: =LEFT(D89,3) -> 471 | D89: =LEFT(E89,4) -> 4711 | E89: 471103 | F89: Débiteurs et créditeurs divers | G89: Débiteurs divers - BABF | H89: 0 | I89: 17000000 | J89: 0 | K89: 0
A90: =LEFT(B90,1) -> 4 | B90: =LEFT(C90,2) -> 47 | C90: =LEFT(D90,3) -> 471 | D90: =LEFT(E90,4) -> 4711 | E90: 471104 | F90: Débiteurs et créditeurs divers | G90: Débiteurs divers - BA Niger | K90: 9604343
A91: =LEFT(B91,1) -> 4 | B91: =LEFT(C91,2) -> 47 | C91: =LEFT(D91,3) -> 471 | D91: =LEFT(E91,4) -> 4711 | E91: 471105 | F91: Débiteurs et créditeurs divers | G91: Débiteurs divers - BA Groupe | K91: 10914534
A92: =LEFT(B92,1) -> 4 | B92: =LEFT(C92,2) -> 47 | C92: =LEFT(D92,3) -> 471 | D92: =LEFT(E92,4) -> 4711 | E92: 471106 | F92: Débiteurs et créditeurs divers | G92: Ibrahima DIOP | K92: 38484016
A93: =LEFT(B93,1) -> 4 | B93: =LEFT(C93,2) -> 47 | C93: =LEFT(D93,3) -> 471 | D93: =LEFT(E93,4) -> 4711 | E93: 471107 | F93: Débiteurs et créditeurs divers | G93: KONE Nombelgnerigué | K93: 27991742
A94: =LEFT(B94,1) -> 4 | B94: =LEFT(C94,2) -> 47 | C94: =LEFT(D94,3) -> 471 | D94: =LEFT(E94,4) -> 4712 | E94: 471200 | F94: Débiteurs et créditeurs divers | G94: Créditeurs divers | H94: -174193466 | I94: 0 | J94: 0 | K94: 0
A95: =LEFT(B95,1) -> 4 | B95: =LEFT(C95,2) -> 47 | C95: =LEFT(D95,3) -> 476 | D95: =LEFT(E95,4) -> 4760 | E95: 476000 | F95: Débiteurs et créditeurs divers | G95: CHARGES CONSTATÉES D'AVANCE | H95: 12556000 | I95: 32028895 | J95: 21308043 | K95: 32719383
A96: =LEFT(B96,1) -> 4 | B96: =LEFT(C96,2) -> 47 | C96: =LEFT(D96,3) -> 477 | D96: =LEFT(E96,4) -> 4770 | E96: 477000 | F96: Débiteurs et créditeurs divers | G96: PRODUITS CONSTATÉS D'AVANCE | H96: 0 | I96: 0 | J96: 0 | K96: 0
A97: =LEFT(B97,1) -> 5 | B97: =LEFT(C97,2) -> 51 | C97: =LEFT(D97,3) -> 510 | D97: =LEFT(E97,4) -> 5100 | E97: 510002 | F97: Banque | G97: Outstanding Receipts | H97: 2700 | I97: 2700 | J97: 2700 | K97: 0
A98: =LEFT(B98,1) -> 5 | B98: =LEFT(C98,2) -> 51 | C98: =LEFT(D98,3) -> 511 | D98: =LEFT(E98,4) -> 5110 | E98: 511000 | F98: Banque | G98: Effets à encaisser | K98: 0
A99: =LEFT(B99,1) -> 5 | B99: =LEFT(C99,2) -> 51 | C99: =LEFT(D99,3) -> 512 | D99: =LEFT(E99,4) -> 5120 | E99: 512000 | F99: Banque | G99: Effets à l'encaissement | K99: 0
A100: =LEFT(B100,1) -> 5 | B100: =LEFT(C100,2) -> 52 | C100: =LEFT(D100,3) -> 520 | D100: =LEFT(E100,4) -> 5200 | E100: 520001 | F100: Banque | G100: Compte d'attente de la banque | J100: 0 | K100: 0
A101: =LEFT(B101,1) -> 5 | B101: =LEFT(C101,2) -> 52 | C101: =LEFT(D101,3) -> 520 | D101: =LEFT(E101,4) -> 5200 | E101: 520002 | F101: Banque | G101: Outstanding Receipts | J101: 0 | K101: 0
A102: =LEFT(B102,1) -> 5 | B102: =LEFT(C102,2) -> 52 | C102: =LEFT(D102,3) -> 520 | D102: =LEFT(E102,4) -> 5200 | E102: 520003 | F102: Banque | G102: Outstanding Payments | K102: 0
...

Sheet BG COMP BABF
A1: Mapping | B1: C1 | C1: C2 | D1: C3 | E1: C4 | F1: NC | G1: LB | H1: FY23 | I1: FY24 | J1: FY 25
A2: Capital | B2: =LEFT(C2,1) -> 1 | C2: =LEFT(D2,2) -> 10 | D2: =_xlfn.NUMBERVALUE(LEFT(E2,3)) -> 101 | E2: =_xlfn.NUMBERVALUE(LEFT(F2,4)) -> 1013 | F2: 101310 | G2: Capital souscrit, appelé, versé, non amorti - DIOP Ibrahima | H2: -8500000 | I2: -8500000 | J2: -8500000
A3: Capital | B3: =LEFT(C3,1) -> 1 | C3: =LEFT(D3,2) -> 10 | D3: =_xlfn.NUMBERVALUE(LEFT(E3,3)) -> 101 | E3: =_xlfn.NUMBERVALUE(LEFT(F3,4)) -> 1013 | F3: 101320 | G3: Capital souscrit, appelé, versé, non amorti - BADO Hermann | H3: -1000000 | I3: -1000000 | J3: -1000000
A4: Capital | B4: =LEFT(C4,1) -> 1 | C4: =LEFT(D4,2) -> 10 | D4: =_xlfn.NUMBERVALUE(LEFT(E4,3)) -> 101 | E4: =_xlfn.NUMBERVALUE(LEFT(F4,4)) -> 1013 | F4: 101330 | G4: Capital souscrit, appelé, versé, non amorti - KONE Nombelegnerigue | H4: -500000 | I4: -500000 | J4: -500000
A5: Reserve légale | B5: =LEFT(C5,1) -> 1 | C5: =LEFT(D5,2) -> 11 | D5: =_xlfn.NUMBERVALUE(LEFT(E5,3)) -> 111 | E5: =_xlfn.NUMBERVALUE(LEFT(F5,4)) -> 1110 | F5: 111000 | G5: RÉSERVE LÉGALE | H5: 0 | I5: -353151 | J5: -1097948
A6: Report a nouveau | B6: =LEFT(C6,1) -> 1 | C6: =LEFT(D6,2) -> 12 | D6: =_xlfn.NUMBERVALUE(LEFT(E6,3)) -> 121 | E6: =_xlfn.NUMBERVALUE(LEFT(F6,4)) -> 1210 | F6: 121000 | G6: REPORT À NOUVEAU CRÉDITEUR | H6: -741664 | I6: -3849388 | J6: -10403598
A7: Report a nouveau | B7: =LEFT(C7,1) -> 1 | C7: =LEFT(D7,2) -> 12 | D7: =_xlfn.NUMBERVALUE(LEFT(E7,3)) -> 129 | E7: =_xlfn.NUMBERVALUE(LEFT(F7,4)) -> 1291 | F7: 129100 | G7: Perte nette à reporter | H7: 0 | I7: 0 | J7: 0
A8: RIA | B8: =LEFT(C8,1) -> 1 | C8: =LEFT(D8,2) -> 13 | D8: =_xlfn.NUMBERVALUE(LEFT(E8,3)) -> 130 | E8: =_xlfn.NUMBERVALUE(LEFT(F8,4)) -> 1301 | F8: 130100 | G8: Résultat en instance d'affectation : Bénéfice | H8: 0 | I8: 0 | J8: 0
A9: Emprunt | B9: =LEFT(C9,1) -> 1 | C9: =LEFT(D9,2) -> 16 | D9: =_xlfn.NUMBERVALUE(LEFT(E9,3)) -> 162 | E9: =_xlfn.NUMBERVALUE(LEFT(F9,4)) -> 1620 | F9: 162000 | G9: EMPRUNTS ET DETTES AUPRÈS DES ÉTABLISSEMENTS DE CRÉDIT | H9: 0 | I9: 0 | J9: 0
A10: Aménagements de bureau | B10: =LEFT(C10,1) -> 2 | C10: =LEFT(D10,2) -> 23 | D10: =_xlfn.NUMBERVALUE(LEFT(E10,3)) -> 235 | E10: =_xlfn.NUMBERVALUE(LEFT(F10,4)) -> 2351 | F10: 235100 | G10: Installations générales | H10: 4082500 | I10: 4082500 | J10: 4082500
A11: Matériel et mobilier de bureau | B11: =LEFT(C11,1) -> 2 | C11: =LEFT(D11,2) -> 24 | D11: =_xlfn.NUMBERVALUE(LEFT(E11,3)) -> 244 | E11: =_xlfn.NUMBERVALUE(LEFT(F11,4)) -> 2441 | F11: 244100 | G11: Matériel de bureau | H11: 5409052 | I11: 6241052 | J11: 3959052
A12: Matériel informatique | B12: =LEFT(C12,1) -> 2 | C12: =LEFT(D12,2) -> 24 | D12: =_xlfn.NUMBERVALUE(LEFT(E12,3)) -> 244 | E12: =_xlfn.NUMBERVALUE(LEFT(F12,4)) -> 2442 | F12: 244200 | G12: Matériel informatique | H12: 2128480 | I12: 2208480 | J12: 7542930
A13: Matériel et mobilier de bureau | B13: =LEFT(C13,1) -> 2 | C13: =LEFT(D13,2) -> 24 | D13: =_xlfn.NUMBERVALUE(LEFT(E13,3)) -> 244 | E13: =_xlfn.NUMBERVALUE(LEFT(F13,4)) -> 2444 | F13: 244400 | G13: Mobilier de bureau | H13: 3168696 | I13: 3168696 | J13: 3117543
A14: Matériel de transport | B14: =LEFT(C14,1) -> 2 | C14: =LEFT(D14,2) -> 24 | D14: =_xlfn.NUMBERVALUE(LEFT(E14,3)) -> 245 | E14: =_xlfn.NUMBERVALUE(LEFT(F14,4)) -> 2451 | F14: 245100 | G14: Matériel automobile | H14: 8296170 | I14: 6709370 | J14: 13815627
... A84: Virement de fonds | B84: =LEFT(C84,1) -> 5 | C84: =LEFT(D84,2) -> 58 | D84: =_xlfn.NUMBERVALUE(LEFT(E84,3)) -> 588 | E84: =_xlfn.NUMBERVALUE(LEFT(F84,4)) -> 5880 | F84: 588001 | G84: Transfert de liquidités | H84: 0 | I84: 0 | J84: 0
A85: Achat de marchandises | B85: =LEFT(C85,1) -> 6 | C85: =LEFT(D85,2) -> 60 | D85: =_xlfn.NUMBERVALUE(LEFT(E85,3)) -> 601 | E85: =_xlfn.NUMBERVALUE(LEFT(F85,4)) -> 6011 | F85: 601100 | G85: Achats dans la Région | H85: 6663594 | I85: 15548012 | J85: 103082451 | K85: =-H85/'Cdr BABF'!F8 -> 0.020907488 | L85: =-I85/'Cdr BABF'!G8 -> 0.091698024 | M85: =-J85/'Cdr BABF'!H8 -> 0.43493089 | N85: =(J85-H85)/H85 -> 14.469498 | O85: =((J85/H85)^(1/2))-1 -> 2.9331282
A86: Achat de marchandises | B86: =LEFT(C86,1) -> 6 | C86: =LEFT(D86,2) -> 60 | D86: =_xlfn.NUMBERVALUE(LEFT(E86,3)) -> 601 | E86: =_xlfn.NUMBERVALUE(LEFT(F86,4)) -> 6012 | F86: 601200 | G86: hors Région | H86: 272645541 | I86: 154017885 | J86: 132468945 | K86: =-H86/'Cdr BABF'!F8 -> 0.85544428 | L86: =-I86/'Cdr BABF'!G8 -> 0.90835637 | M86: =-J86/'Cdr BABF'!H8 -> 0.55891993 | N86: =(J86-H86)/H86 -> -0.51413493
A87: Achat de marchandises | B87: =LEFT(C87,1) -> 6 | C87: =LEFT(D87,2) -> 60 | D87: =_xlfn.NUMBERVALUE(LEFT(E87,3)) -> 601 | E87: =_xlfn.NUMBERVALUE(LEFT(F87,4)) -> 6015 | F87: 601500 | G87: Frais sur achats | H87: 39408924 | I87: 565777 | J87: 1457409 | K87: =-H87/'Cdr BABF'!F8 -> 0.12364823 | L87: =-I87/'Cdr BABF'!G8 -> 0.0033368017 | M87: =-J87/'Cdr BABF'!H8 -> 0.0061491766
A88: FNS - Electricité | B88: =LEFT(C88,1) -> 6 | C88: =LEFT(D88,2) -> 60 | D88: =_xlfn.NUMBERVALUE(LEFT(E88,3)) -> 605 | E88: =_xlfn.NUMBERVALUE(LEFT(F88,4)) -> 6052 | F88: 605200 | G88: Fournitures non stockables - Electricité | H88: 2489435 | I88: 1843333 | J88: 1362875
A89: FNS - Autres énergies | B89: =LEFT(C89,1) -> 6 | C89: =LEFT(D89,2) -> 60 | D89: =_xlfn.NUMBERVALUE(LEFT(E89,3)) -> 605 | E89: =_xlfn.NUMBERVALUE(LEFT(F89,4)) -> 6053 | F89: 605300 | G89: Fournitures non stockables – Autres énergies | H89: 4098500 | I89: 4121900 | J89: 4680000
A90: Achat de produits d'entretien | B90: =LEFT(C90,1) -> 6 | C90: =LEFT(D90,2) -> 60 | D90: =_xlfn.NUMBERVALUE(LEFT(E90,3)) -> 605 | E90: =_xlfn.NUMBERVALUE(LEFT(F90,4)) -> 6054 | F90: 605400 | G90: Fournitures d'entretien non stockables | H90: 411100 | I90: 360813 | J90: 302625
A91: Achat de fournitures | B91: =LEFT(C91,1) -> 6 | C91: =LEFT(D91,2) -> 60 | D91: =_xlfn.NUMBERVALUE(LEFT(E91,3)) -> 605 | E91: =_xlfn.NUMBERVALUE(LEFT(F91,4)) -> 6055 | F91: 605500 | G91: Fournitures de bureau non stockables | H91: 380225 | I91: 433784 | J91: 668049
A92: Achat de fournitures | B92: =LEFT(C92,1) -> 6 | C92: =LEFT(D92,2) -> 60 | D92: =_xlfn.NUMBERVALUE(LEFT(E92,3)) -> 605 | E92: =_xlfn.NUMBERVALUE(LEFT(F92,4)) -> 6055 | F92: 605501 | G92: Fournitures de bureau informatique | H92: 0 | I92: 0 | J92: 2957500
A93: Achat de fournitures | B93: =LEFT(C93,1) -> 6 | C93: =LEFT(D93,2) -> 60 | D93: =_xlfn.NUMBERVALUE(LEFT(E93,3)) -> 605 | E93: =_xlfn.NUMBERVALUE(LEFT(F93,4)) -> 6055 | F93: 605550 | G93: Fournitures divers | H93: 0 | I93: 0 | J93: 0
A94: Achat de petit matériel et outillage | B94: =LEFT(C94,1) -> 6 | C94: =LEFT(D94,2) -> 60 | D94: =_xlfn.NUMBERVALUE(LEFT(E94,3)) -> 605 | E94: =_xlfn.NUMBERVALUE(LEFT(F94,4)) -> 6056 | F94: 605600 | G94: Achats de petit matériel et outillage | H94: 0 | I94: 0 | J94: 419850
A95: Achat de petit matériel et outillage | B95: =LEFT(C95,1) -> 6 | C95: =LEFT(D95,2) -> 60 | D95: =_xlfn.NUMBERVALUE(LEFT(E95,3)) -> 605 | E95: =_xlfn.NUMBERVALUE(LEFT(F95,4)) -> 6056 | F95: 605601 | G95: Achats de petit matériel et outillage informatique | H95: 1052378 | I95: 1958236 | J95: 4899628
A96: Etudes et prestation de services | B96: =LEFT(C96,1) -> 6 | C96: =LEFT(D96,2) -> 60 | D96: =_xlfn.NUMBERVALUE(LEFT(E96,3)) -> 605 | E96: =_xlfn.NUMBERVALUE(LEFT(F96,4)) -> 6057 | F96: 605700 | G96: Achats d'études et prestations de services | H96: 10965385 | I96: 29125940 | J96: 54802867
A97: Etudes et prestation de services | B97: =LEFT(C97,1) -> 6 | C97: =LEFT(D97,2) -> 60 | D97: =_xlfn.NUMBERVALUE(LEFT(E97,3)) -> 605 | E97: =_xlfn.NUMBERVALUE(LEFT(F97,4)) -> 6057 | F97: 605701 | G97: Achats d'études et prestations de services - Frais généraux | H97: 5791178 | I97: 2929348 | J97: 13527061
A98: Travaux, matériel et équipement | B98: =LEFT(C98,1) -> 6 | C98: =LEFT(D98,2) -> 60 | D98: =_xlfn.NUMBERVALUE(LEFT(E98,3)) -> 605 | E98: =_xlfn.NUMBERVALUE(LEFT(F98,4)) -> 6058 | F98: 605800 | G98: Achats de travaux, matériels et équipements | H98: 16452263 | I98: 38047837 | J98: 29006
A99: Achat de marchandises | D99: =_xlfn.NUMBERVALUE(LEFT(E99,3)) -> 608 | E99: =_xlfn.NUMBERVALUE(LEFT(F99,4)) -> 6089 | F99: 608900 | G99: Rabais, Remises et Ristournes obtenus (non ventilés) | H99: 0 | I99: -575000
A100: Transport | B100: =LEFT(C100,1) -> 6 | C100: =LEFT(D100,2) -> 61 | D100: =_xlfn.NUMBERVALUE(LEFT(E100,3)) -> 613 | E100: =_xlfn.NUMBERVALUE(LEFT(F100,4)) -> 6130 | F100: 613000 | G100: TRANSPORTS POUR LE COMPTE DE TIERS | H100: 0 | I100: 0 | J100: 0
A101: Transport | B101: =LEFT(C101,1) -> 6 | C101: =LEFT(D101,2) -> 61 | D101: =_xlfn.NUMBERVALUE(LEFT(E101,3)) -> 616 | E101: =_xlfn.NUMBERVALUE(LEFT(F101,4)) -> 6160 | F101: 616000 | G101: TRANSPORTS DE PLIS | H101: 0 | I101: 0 | J101: 88000
A102: Transport | B102: =LEFT(C102,1) -> 6 | C102: =LEFT(D102,2) -> 61 | D102: =_xlfn.NUMBERVALUE(LEFT(E102,3)) -> 616 | E102: =_xlfn.NUMBERVALUE(LEFT(F102,4)) -> 6161 | F102: 616100 | G102: Frais d'expédition et Livraison de marchandises | H102: 0 | I102: 0 | J102: 1124051
A103: Transport | B103: =LEFT(C103,1) -> 6 | C103: =LEFT(D103,2) -> 61 | D103: =_xlfn.NUMBERVALUE(LEFT(E103,3)) -> 618 | E103: =_xlfn.NUMBERVALUE(LEFT(F103,4)) -> 6181 | F103: 618100 | G103: Voyages et déplacements | H103: 8320800 | I103: 5312900 | J103: 5463801
A104: Transport | B104: =LEFT(C104,1) -> 6 | C104: =LEFT(D104,2) -> 61 | D104: =_xlfn.NUMBERVALUE(LEFT(E104,3)) -> 618 | E104: =_xlfn.NUMBERVALUE(LEFT(F104,4)) -> 6183 | F104: 618300 | G104: Transports administratifs | H104: 2050000 | I104: 1045000 | J104: 252116
A105: Charges locatives matières diverses | B105: =LEFT(C105,1) -> 6 | C105: =LEFT(D105,2) -> 62 | D105: =_xlfn.NUMBERVALUE(LEFT(E105,3)) -> 622 | E105: =_xlfn.NUMBERVALUE(LEFT(F105,4)) -> 6221 | F105: 622100 | G105: Locations de terrains | H105: 1200000 | I105: 0
A106: Charges locatives matières diverses | B106: =LEFT(C106,1) -> 6 | C106: =LEFT(D106,2) -> 62 | D106: =_xlfn.NUMBERVALUE(LEFT(E106,3)) -> 622 | E106: =_xlfn.NUMBERVALUE(LEFT(F106,4)) -> 6222 | F106: 622200 | G106: Locations de bâtiments | H106: 7200000 | I106: 7200000 | J106: 8132568
A107: Charges locatives matières diverses | B107: =LEFT(C107,1) -> 6 | C107: =LEFT(D107,2) -> 62 | D107: =_xlfn.NUMBERVALUE(LEFT(E107,3)) -> 622 | E107: =_xlfn.NUMBERVALUE(LEFT(F107,4)) -> 6223 | F107: 622300 | G107: Locations de matériels et outillages | H107: 0 | I107: 0 | J107: 40500
A108: Charges locatives matières diverses | B108: =LEFT(C108,1) -> 6 | C108: =LEFT(D108,2) -> 62 | D108: =_xlfn.NUMBERVALUE(LEFT(E108,3)) -> 622 | E108: =_xlfn.NUMBERVALUE(LEFT(F108,4)) -> 6228 | F108: 622800 | G108: Locations et charges locatives diverses | H108: 2110880 | I108: 708118 | J108: 1168947
A109: Charges locatives matières diverses | B109: =LEFT(C109,1) -> 6 | C109: =LEFT(D109,2) -> 62 | D109: =_xlfn.NUMBERVALUE(LEFT(E109,3)) -> 622 | E109: =_xlfn.NUMBERVALUE(LEFT(F109,4)) -> 6228 | F109: 622801 | G109: Locations pour clients | H109: 0 | I109: 0 | J109: 195600
A110: Charges locatives matières diverses | D110: =_xlfn.NUMBERVALUE(LEFT(E110,3)) -> 623 | E110: =_xlfn.NUMBERVALUE(LEFT(F110,4)) -> 6238 | F110: 623800 | G110: 623800 Autres contrats de location acquisition | H110: 0 | I110: 200000
A111: Ent. & réparatIon | B111: =LEFT(C111,1) -> 6 | C111: =LEFT(D111,2) -> 62 | D111: =_xlfn.NUMBERVALUE(LEFT(E111,3)) -> 624 | E111: =_xlfn.NUMBERVALUE(LEFT(F111,4)) -> 6241 | F111: 624100 | G111: Entretien et réparations des biens immobiliers | H111: 0 | I111: 0 | J111: 572500
A112: Ent. & réparatIon | B112: =LEFT(C112,1) -> 6 | C112: =LEFT(D112,2) -> 62 | D112: =_xlfn.NUMBERVALUE(LEFT(E112,3)) -> 624 | E112: =_xlfn.NUMBERVALUE(LEFT(F112,4)) -> 6242 | F112: 624200 | G112: Entretien et réparations des biens mobiliers | H112: 391000 | I112: 561000 | J112: 118600
A113: Ent. & réparatIon | B113: =LEFT(C113,1) -> 6 | C113: =LEFT(D113,2) -> 62 | D113: =_xlfn.NUMBERVALUE(LEFT(E113,3)) -> 624 | E113: =_xlfn.NUMBERVALUE(LEFT(F113,4)) -> 6248 | F113: 624800 | G113: Autres entretiens et réparations | H113: 926617 | I113: 2033717 | J113: 1524500
A114: Assurances | B114: =LEFT(C114,1) -> 6 | C114: =LEFT(D114,2) -> 62 | D114: =_xlfn.NUMBERVALUE(LEFT(E114,3)) -> 625 | E114: =_xlfn.NUMBERVALUE(LEFT(F114,4)) -> 6251 | F114: 625100 | G114: Assurances multirisques | H114: 0 | I114: 0 | J114: 352000
A115: Assurances | B115: =LEFT(C115,1) -> 6 | C115: =LEFT(D115,2) -> 62 | D115: =_xlfn.NUMBERVALUE(LEFT(E115,3)) -> 625 | E115: =_xlfn.NUMBERVALUE(LEFT(F115,4)) -> 6252 | F115: 625200 | G115: Assurances matériel de transport | H115: 350000 | I115: 350000 | J115: 73750
A116: Assurances | B116: =LEFT(C116,1) -> 6 | C116: =LEFT(D116,2) -> 62 | D116: =_xlfn.NUMBERVALUE(LEFT(E116,3)) -> 625 | E116: =_xlfn.NUMBERVALUE(LEFT(F116,4)) -> 6258 | F116: 625800 | G116: Autres primes d'assurances | H116: 3823750 | I116: 1404988 | J116: 850442
A117: Etudes, recherches et documentation | B117: =LEFT(C117,1) -> 6 | C117: =LEFT(D117,2) -> 62 | D117: =_xlfn.NUMBERVALUE(LEFT(E117,3)) -> 626 | E117: =_xlfn.NUMBERVALUE(LEFT(F117,4)) -> 6266 | F117: 626600 | G117: Documentation technique | H117: 0 | I117: 0 | J117: 48000
A118: Publicité et relations publiques | B118: =LEFT(C118,1) -> 6 | C118: =LEFT(D118,2) -> 62 | D118: =_xlfn.NUMBERVALUE(LEFT(E118,3)) -> 627 | E118: =_xlfn.NUMBERVALUE(LEFT(F118,4)) -> 6272 | F118: 627200 | G118: Catalogues, imprimés publicitaires | H118: 0 | I118: 0 | J118: 1106000
A119: Publicité et relations publiques | B119: =LEFT(C119,1) -> 6 | C119: =LEFT(D119,2) -> 62 | D119: =_xlfn.NUMBERVALUE(LEFT(E119,3)) -> 627 | E119: =_xlfn.NUMBERVALUE(LEFT(F119,4)) -> 6275 | F119: 627500 | G119: Publications | H119: 0 | I119: 0 | J119: 100000
A120: Publicité et relations publiques | B120: =LEFT(C120,1) -> 6 | C120: =LEFT(D120,2) -> 62 | D120: =_xlfn.NUMBERVALUE(LEFT(E120,3)) -> 627 | E120: =_xlfn.NUMBERVALUE(LEFT(F120,4)) -> 6276 | F120: 627600 | G120: Cadeaux à la clientèle | H120: 0 | I120: 19000 | J120: 2994171
A121: Publicité et relations publiques | B121: =LEFT(C121,1) -> 6 | C121: =LEFT(D121,2) -> 62 | D121: =_xlfn.NUMBERVALUE(LEFT(E121,3)) -> 627 | E121: =_xlfn.NUMBERVALUE(LEFT(F121,4)) -> 6277 | F121: 627700 | G121: Frais de colloques, séminaires, conférences | H121: 0 | I121: 0 | J121: 250000
A122: Publicité et relations publiques | B122: =LEFT(C122,1) -> 6 | C122: =LEFT(D122,2) -> 62 | D122: =_xlfn.NUMBERVALUE(LEFT(E122,3)) -> 627 | E122: =_xlfn.NUMBERVALUE(LEFT(F122,4)) -> 6278 | F122: 627800 | G122: Autres charges de publicité et relations publiques | H122: 0 | I122: 0 | J122: 47566000
A123: Frais de télécommunication | D123: =_xlfn.NUMBERVALUE(LEFT(E123,3)) -> 628 | E123: =_xlfn.NUMBERVALUE(LEFT(F123,4)) -> 6281 | F123: 628100 | G123: 628100 Frais de téléphone | H123: 0 | I123: 102000
A124: Frais de télécommunication | B124: =LEFT(C124,1) -> 6 | C124: =LEFT(D124,2) -> 62 | D124: =_xlfn.NUMBERVALUE(LEFT(E124,3)) -> 628 | E124: =_xlfn.NUMBERVALUE(LEFT(F124,4)) -> 6288 | F124: 628800 | G124: Autres frais de télécommunications | H124: 2708865 | I124: 2084056 | J124: 3414757
A125: Frais bancaires | B125: =LEFT(C125,1) -> 6 | C125: =LEFT(D125,2) -> 63 | D125: =_xlfn.NUMBERVALUE(LEFT(E125,3)) -> 631 | E125: =_xlfn.NUMBERVALUE(LEFT(F125,4)) -> 6317 | F125: 631700 | G125: Frais sur instruments monnaie électronique | H125: 0 | I125: 0 | J125: 8728
A126: Frais bancaires | B126: =LEFT(C126,1) -> 6 | C126: =LEFT(D126,2) -> 63 | D126: =_xlfn.NUMBERVALUE(LEFT(E126,3)) -> 631 | E126: =_xlfn.NUMBERVALUE(LEFT(F126,4)) -> 6318 | F126: 631800 | G126: Autres frais bancaires | H126: 9023514 | I126: 13831789 | J126: 14465315
A127: Rémunérations d'intermédiaires | B127: =LEFT(C127,1) -> 6 | C127: =LEFT(D127,2) -> 63 | D127: =_xlfn.NUMBERVALUE(LEFT(E127,3)) -> 632 | E127: =_xlfn.NUMBERVALUE(LEFT(F127,4)) -> 6324 | F127: 632400 | G127: Honoraires des professions réglementées | H127: 2930800 | I127: 1200000 | J127: 1905000
A128: Rémunérations d'intermédiaires | B128: =LEFT(C128,1) -> 6 | C128: =LEFT(D128,2) -> 63 | D128: =_xlfn.NUMBERVALUE(LEFT(E128,3)) -> 632 | E128: =_xlfn.NUMBERVALUE(LEFT(F128,4)) -> 6327 | F128: 632700 | G128: Rémunérations des autres prestataires de service | H128: 0 | I128: 0 | J128: 18242223
A129: Rémunérations d'intermédiaires | B129: =LEFT(C129,1) -> 6 | C129: =LEFT(D129,2) -> 63 | D129: =_xlfn.NUMBERVALUE(LEFT(E129,3)) -> 632 | E129: =_xlfn.NUMBERVALUE(LEFT(F129,4)) -> 6328 | F129: 632800 | G129: Divers frais | H129: 681635 | I129: 0 | J129: 1838090
A130: Autres services extérieurs | B130: =LEFT(C130,1) -> 6 | C130: =LEFT(D130,2) -> 63 | D130: =_xlfn.NUMBERVALUE(LEFT(E130,3)) -> 633 | E130: =_xlfn.NUMBERVALUE(LEFT(F130,4)) -> 6330 | F130: 633000 | G130: FRAIS DE FORMATION DU PERSONNEL | H130: 0 | I130: 0 | J130: 203280
A131: Autres services extérieurs | B131: =LEFT(C131,1) -> 6 | C131: =LEFT(D131,2) -> 63 | D131: =_xlfn.NUMBERVALUE(LEFT(E131,3)) -> 634 | E131: =_xlfn.NUMBERVALUE(LEFT(F131,4)) -> 6343 | F131: 634300 | G131: Redevances pour logiciels | H131: 0 | I131: 0 | J131: 191624
A132: Autres services extérieurs | B132: =LEFT(C132,1) -> 6 | C132: =LEFT(D132,2) -> 63 | D132: =_xlfn.NUMBERVALUE(LEFT(E132,3)) -> 638 | E132: =_xlfn.NUMBERVALUE(LEFT(F132,4)) -> 6383 | F132: 638300 | G132: Réceptions | H132: 6987934 | I132: 7367031 | J132: 4978380
A133: Autres services extérieurs | B133: =LEFT(C133,1) -> 6 | C133: =LEFT(D133,2) -> 63 | D133: =_xlfn.NUMBERVALUE(LEFT(E133,3)) -> 638 | E133: =_xlfn.NUMBERVALUE(LEFT(F133,4)) -> 6383 | F133: 638301 | G133: Frais de réception formation clients | H133: 0 | I133: 0 | J133: 3951950
A134: Autres services extérieurs | B134: =LEFT(C134,1) -> 6 | C134: =LEFT(D134,2) -> 63 | D134: =_xlfn.NUMBERVALUE(LEFT(E134,3)) -> 638 | E134: =_xlfn.NUMBERVALUE(LEFT(F134,4)) -> 6384 | F134: 638400 | G134: Missions | H134: 4478600 | I134: 19503431 | J134: 11221265
A135: Impôts et taxes | B135: =LEFT(C135,1) -> 6 | C135: =LEFT(D135,2) -> 64 | D135: =_xlfn.NUMBERVALUE(LEFT(E135,3)) -> 641 | E135: =_xlfn.NUMBERVALUE(LEFT(F135,4)) -> 6411 | F135: 641100 | G135: Impôts fonciers et taxes annexes | H135: 816000 | I135: 816000 | J135: 18436
... A139: Impôts et taxes | B139: =LEFT(C139,1) -> 6 | C139: =LEFT(D139,2) -> 64 | D139: =_xlfn.NUMBERVALUE(LEFT(E139,3)) -> 646 | E139: =_xlfn.NUMBERVALUE(LEFT(F139,4)) -> 6460 | F139: 646000 | G139: Droit d'enregistrement | H139: 0 | I139: 0 | J139: 195900
A140: Impôts et taxes | B140: =LEFT(C140,1) -> 6 | C140: =LEFT(D140,2) -> 64 | D140: =_xlfn.NUMBERVALUE(LEFT(E140,3)) -> 646 | E140: =_xlfn.NUMBERVALUE(LEFT(F140,4)) -> 6461 | F140: 646100 | G140: 646100 Droits de mutation | H140: 360000 | I140: 766628
A141: Impôts et taxes | B141: =LEFT(C141,1) -> 6 | C141: =LEFT(D141,2) -> 64 | D141: =_xlfn.NUMBERVALUE(LEFT(E141,3)) -> 646 | E141: =_xlfn.NUMBERVALUE(LEFT(F141,4)) -> 6462 | F141: 646200 | G141: Droits de timbre | H141: 17530 | I141: 13710 | J141: 22930
A142: Impôts et taxes | B142: =LEFT(C142,1) -> 6 | C142: =LEFT(D142,2) -> 64 | D142: =_xlfn.NUMBERVALUE(LEFT(E142,3)) -> 646 | E142: =_xlfn.NUMBERVALUE(LEFT(F142,4)) -> 6463 | F142: 646300 | G142: Taxes sur les véhicules de société | H142: 0 | I142: 40000 | J142: 35000
A143: Impôts et taxes | B143: =LEFT(C143,1) -> 6 | C143: =LEFT(D143,2) -> 64 | D143: =_xlfn.NUMBERVALUE(LEFT(E143,3)) -> 646 | E143: =_xlfn.NUMBERVALUE(LEFT(F143,4)) -> 6468 | F143: 646800 | G143: Autres droits | H143: 186500 | I143: 869352 | J143: 4388203
A144: Impôts et taxes | B144: =LEFT(C144,1) -> 6 | C144: =LEFT(D144,2) -> 64 | D144: =_xlfn.NUMBERVALUE(LEFT(E144,3)) -> 647 | E144: =_xlfn.NUMBERVALUE(LEFT(F144,4)) -> 6478 | F144: 647800 | G144: Autres pénalités et amendes fiscales | H144: 0 | I144: 0 | J144: 2500
A145: Impôts et taxes | B145: =LEFT(C145,1) -> 6 | C145: =LEFT(D145,2) -> 64 | D145: =_xlfn.NUMBERVALUE(LEFT(E145,3)) -> 648 | E145: =_xlfn.NUMBERVALUE(LEFT(F145,4)) -> 6480 | F145: 648000 | G145: AUTRES IMPÔTS ET TAXES | H145: 0 | I145: 0 | J145: 1011608
A146: Autres charges | B146: =LEFT(C146,1) -> 6 | C146: =LEFT(D146,2) -> 65 | D146: =_xlfn.NUMBERVALUE(LEFT(E146,3)) -> 651 | E146: =_xlfn.NUMBERVALUE(LEFT(F146,4)) -> 6515 | F146: 651500 | G146: Autres débiteurs | H146: 0 | I146: 0 | J146: 59783
A147: Autres charges | B147: =LEFT(C147,1) -> 6 | C147: =LEFT(D147,2) -> 65 | D147: =_xlfn.NUMBERVALUE(LEFT(E147,3)) -> 652 | E147: =_xlfn.NUMBERVALUE(LEFT(F147,4)) -> 6525 | F147: 652500 | G147: Pertes imputées par transfert (comptabilité des associés non gérants) | H147: 0 | I147: 0
A148: Autres charges | B148: =LEFT(C148,1) -> 6 | C148: =LEFT(D148,2) -> 65 | D148: =_xlfn.NUMBERVALUE(LEFT(E148,3)) -> 656 | E148: =_xlfn.NUMBERVALUE(LEFT(F148,4)) -> 6560 | F148: 656000 | G148: PERTE DE CHANGE SUR CREANCES ET DETTES COMMERCIALES | H148: 650903 | I148: 0 | J148: 2364134
A149: Autres charges | B149: =LEFT(C149,1) -> 6 | C149: =LEFT(D149,2) -> 65 | D149: =_xlfn.NUMBERVALUE(LEFT(E149,3)) -> 658 | E149: =_xlfn.NUMBERVALUE(LEFT(F149,4)) -> 6582 | F149: 658200 | G149: Dons | H149: 925050 | I149: 99523 | J149: 901625
A150: Autres charges | B150: =LEFT(C150,1) -> 6 | C150: =LEFT(D150,2) -> 65 | D150: =_xlfn.NUMBERVALUE(LEFT(E150,3)) -> 658 | E150: =_xlfn.NUMBERVALUE(LEFT(F150,4)) -> 6588 | F150: 658800 | G150: Autres charges diverses | H150: 0 | I150: 0 | J150: 139574
A151: Charges de personnel | B151: =LEFT(C151,1) -> 6 | C151: =LEFT(D151,2) -> 66 | D151: =_xlfn.NUMBERVALUE(LEFT(E151,3)) -> 661 | E151: =_xlfn.NUMBERVALUE(LEFT(F151,4)) -> 6611 | F151: 661100 | G151: Appointements salaires et commissions | H151: 35367914 | I151: 36176943 | J151: 36719852 | L151: =H151/SUM(H151:H162) -> 0.70702844 | M151: =I151/SUM(I151:I162) -> 0.70146466 | N151: =J151/SUM(J151:J162) -> 0.63723067
A152: Charges de personnel | B152: =LEFT(C152,1) -> 6 | C152: =LEFT(D152,2) -> 66 | D152: =_xlfn.NUMBERVALUE(LEFT(E152,3)) -> 661 | E152: =_xlfn.NUMBERVALUE(LEFT(F152,4)) -> 6612 | F152: 661210 | G152: Primes de stage | H152: 310000 | I152: 330000 | J152: 550000
A153: Charges de personnel | B153: =LEFT(C153,1) -> 6 | C153: =LEFT(D153,2) -> 66 | D153: =_xlfn.NUMBERVALUE(LEFT(E153,3)) -> 661 | E153: =_xlfn.NUMBERVALUE(LEFT(F153,4)) -> 6618 | F153: 661800 | G153: Autres rémunérations directes | H153: 0 | I153: 0 | J153: 2757250
A154: Charges de personnel | D154: =_xlfn.NUMBERVALUE(LEFT(E154,3)) -> 662 | E154: =_xlfn.NUMBERVALUE(LEFT(F154,4)) -> 6621 | F154: 662100 | G154: Appointements salaires et commissions | H154: 0 | I154: 297000
A155: Charges de personnel | B155: =LEFT(C155,1) -> 6 | C155: =LEFT(D155,2) -> 66 | D155: =_xlfn.NUMBERVALUE(LEFT(E155,3)) -> 663 | E155: =_xlfn.NUMBERVALUE(LEFT(F155,4)) -> 6631 | F155: 663100 | G155: Indemnités de logement | H155: 4980000 | I155: 5315000 | J155: 5805000
A156: Charges de personnel | B156: =LEFT(C156,1) -> 6 | C156: =LEFT(D156,2) -> 66 | D156: =_xlfn.NUMBERVALUE(LEFT(E156,3)) -> 663 | E156: =_xlfn.NUMBERVALUE(LEFT(F156,4)) -> 6634 | F156: 663400 | G156: Indemnité de transport | H156: 1965000 | I156: 2090000 | J156: 2330000
A157: Charges de personnel | B157: =LEFT(C157,1) -> 6 | C157: =LEFT(D157,2) -> 66 | D157: =_xlfn.NUMBERVALUE(LEFT(E157,3)) -> 663 | E157: =_xlfn.NUMBERVALUE(LEFT(F157,4)) -> 6638 | F157: 663800 | G157: Autres indemnités et avantages divers | H157: 4110000 | I157: 3960000 | J157: 5015495
A158: Charges de personnel | B158: =LEFT(C158,1) -> 6 | C158: =LEFT(D158,2) -> 66 | D158: =_xlfn.NUMBERVALUE(LEFT(E158,3)) -> 663 | E158: =_xlfn.NUMBERVALUE(LEFT(F158,4)) -> 6638 | F158: 663810 | G158: Autres avantages et dons aux salariés | H158: 0 | I158: 0 | J158: 54000
A159: Charges de personnel | B159: =LEFT(C159,1) -> 6 | C159: =LEFT(D159,2) -> 66 | D159: =_xlfn.NUMBERVALUE(LEFT(E159,3)) -> 664 | E159: =_xlfn.NUMBERVALUE(LEFT(F159,4)) -> 6641 | F159: 664100 | G159: Charges sociales sur rémunération du personnel national | H159: 3290412 | I159: 3402493 | J159: 3875277
A160: Charges de personnel | B160: =LEFT(C160,1) -> 6 | C160: =LEFT(D160,2) -> 66 | D160: =_xlfn.NUMBERVALUE(LEFT(E160,3)) -> 668 | E160: =_xlfn.NUMBERVALUE(LEFT(F160,4)) -> 6683 | F160: 668300 | G160: Versements et contributions aux autres œuvres sociales | H160: 0 | I160: 0 | J160: 20000
A161: Charges de personnel | B161: =LEFT(C161,1) -> 6 | C161: =LEFT(D161,2) -> 66 | D161: =_xlfn.NUMBERVALUE(LEFT(E161,3)) -> 668 | E161: =_xlfn.NUMBERVALUE(LEFT(F161,4)) -> 6687 | F161: 668700 | G161: Majorations et pénalités sociales | H161: 0 | I161: 2000 | J161: 1091
A162: Charges de personnel | B162: =LEFT(C162,1) -> 6 | C162: =LEFT(D162,2) -> 66 | D162: =_xlfn.NUMBERVALUE(LEFT(E162,3)) -> 668 | E162: =_xlfn.NUMBERVALUE(LEFT(F162,4)) -> 6688 | F162: 668800 | G162: Charges sociales diverses | H162: 0 | I162: 0 | J162: 496148
A163: Intérêts sur emprunts | B163: =LEFT(C163,1) -> 6 | C163: =LEFT(D163,2) -> 67 | D163: =_xlfn.NUMBERVALUE(LEFT(E163,3)) -> 671 | E163: =_xlfn.NUMBERVALUE(LEFT(F163,4)) -> 6712 | F163: 671200 | G163: Emprunts auprès des établissements de crédit | H163: 7904467 | I163: 7637078
A164: Produits d'intérêts | B164: =LEFT(C164,1) -> 6 | C164: =LEFT(D164,2) -> 67 | D164: =_xlfn.NUMBERVALUE(LEFT(E164,3)) -> 676 | E164: =_xlfn.NUMBERVALUE(LEFT(F164,4)) -> 6760 | F164: 676000 | G164: PERTES DE CHANGE | H164: 0 | I164: 0 | J164: 984052
A165: Dotations aux at | B165: =LEFT(C165,1) -> 6 | C165: =LEFT(D165,2) -> 68 | D165: =_xlfn.NUMBERVALUE(LEFT(E165,3)) -> 681 | E165: =_xlfn.NUMBERVALUE(LEFT(F165,4)) -> 6813 | F165: 681300 | G165: Dotations aux amortissements des immobilisations corporelles | H165: 3531374 | I165: 3834084 | J165: 4925482
A166: Ventes de marchandises | B166: =LEFT(C166,1) -> 7 | C166: =LEFT(D166,2) -> 70 | D166: =_xlfn.NUMBERVALUE(LEFT(E166,3)) -> 701 | E166: =_xlfn.NUMBERVALUE(LEFT(F166,4)) -> 7011 | F166: 701100 | G166: Ventes dans la Région | H166: -366135552 | I166: -240296378 | J166: -111840096
A167: Ventes de marchandises | B167: =LEFT(C167,1) -> 7 | C167: =LEFT(D167,2) -> 70 | D167: =_xlfn.NUMBERVALUE(LEFT(E167,3)) -> 701 | E167: =_xlfn.NUMBERVALUE(LEFT(F167,4)) -> 7011 | F167: 701110 | G167: Ventes de licences dans la Région | H167: 0 | I167: 0 | J167: -175893666
A168: Services vendus | B168: =LEFT(C168,1) -> 7 | C168: =LEFT(D168,2) -> 70 | D168: =_xlfn.NUMBERVALUE(LEFT(E168,3)) -> 706 | E168: =_xlfn.NUMBERVALUE(LEFT(F168,4)) -> 7061 | F168: 706100 | G168: Services dans la Région | H168: -118841793 | I168: -145674205 | J168: -291645980
A169: Services vendus | B169: =LEFT(C169,1) -> 7 | C169: =LEFT(D169,2) -> 70 | D169: =_xlfn.NUMBERVALUE(LEFT(E169,3)) -> 706 | E169: =_xlfn.NUMBERVALUE(LEFT(F169,4)) -> 7062 | F169: 706200 | G169: hors Région | H169: -700000 | I169: 0
A170: Autres produits | B170: =LEFT(C170,1) -> 7 | C170: =LEFT(D170,2) -> 75 | D170: =_xlfn.NUMBERVALUE(LEFT(E170,3)) -> 756 | E170: =_xlfn.NUMBERVALUE(LEFT(F170,4)) -> 7560 | F170: 756000 | G170: GAINS DE CHANGE SUR CREANCES ET DETTES COMMERCIALES | H170: -613059 | I170: 0 | J170: -2665977
A171: Autres produits | B171: =LEFT(C171,1) -> 7 | C171: =LEFT(D171,2) -> 75 | D171: =_xlfn.NUMBERVALUE(LEFT(E171,3)) -> 758 | E171: =_xlfn.NUMBERVALUE(LEFT(F171,4)) -> 7588 | F171: 758800 | G171: Autres Produits Divers | H171: 0 | I171: 0 | J171: -5090725
A172: Produits d'intérêts | B172: =LEFT(C172,1) -> 7 | C172: =LEFT(D172,2) -> 77 | D172: =_xlfn.NUMBERVALUE(LEFT(E172,3)) -> 774 | E172: =_xlfn.NUMBERVALUE(LEFT(F172,4)) -> 7740 | F172: 774000 | G172: REVENUS DE PLACEMENT | H172: 0 | I172: -4313136
...

Sheet Cdr BABF
E2: Box Africa BF - P&L
C3: Mapping | E3: mFCFA | F3: FY23 | G3: FY24 | H3: FY25 | J3: CAGR 23-25 | L3: Commentaires
C4: Ventes de marchandises | E4: Travaux et Services vendus | F4: =-SUMIF('BG COMP BABF'!$A:$A,'Cdr BABF'!$C4,'BG COMP BABF'!H:H) -> 366135552 | G4: =-SUMIF('BG COMP BABF'!$A:$A,'Cdr BABF'!$C4,'BG COMP BABF'!I:I) -> 240296378 | H4: =-SUMIF('BG COMP BABF'!$A:$A,'Cdr BABF'!$C4,'BG COMP BABF'!J:J) -> 287733762 | J4: =IFERROR((H4/F4)^(1/2)-1,"n.a") -> -0.11350873 | M4: =F4/F6 -> 0.75386582 | N4: =G4/G6 -> 0.62257692 | O4: =H4/H6 -> 0.49662379 | P4: =AVERAGE(M4:O4) -> 0.62435551
C5: Services vendus | E5: Services vendus | F5: =-SUMIF('BG COMP BABF'!$A:$A,'Cdr BABF'!$C5,'BG COMP BABF'!H:H) -> 119541793 | G5: =-SUMIF('BG COMP BABF'!$A:$A,'Cdr BABF'!$C5,'BG COMP BABF'!I:I) -> 145674205 | H5: =-SUMIF('BG COMP BABF'!$A:$A,'Cdr BABF'!$C5,'BG COMP BABF'!J:J) -> 291645980 | J5: =IFERROR((H5/F5)^(1/2)-1,"n.a") -> 0.56195355 | M5: =F5/F6 -> 0.24613418 | N5: =G5/G6 -> 0.37742308 | O5: =H5/H6 -> 0.50337621 | P5: =AVERAGE(M5:O5) -> 0.37564449
E6: Chiffre d'affaires | F6: =SUM(F4:F5) -> 485677345 | G6: =SUM(G4:G5) -> 385970583 | H6: =SUM(H4:H5) -> 579379742 | J6: =IFERROR((H6/F6)^(1/2)-1,"n.a") -> 0.092213978
C7: Production immobilisée | E7: Production immobilisée | F7: =-SUMIF('BG COMP BABF'!$A:$A,'Cdr BABF'!$C7,'BG COMP BABF'!H:H) -> 0 | G7: =-SUMIF('BG COMP BABF'!A:A,'Cdr BABF'!$C7,'BG COMP BABF'!I:I) -> 0 | H7: =-SUMIF('BG COMP BABF'!$A:$A,'Cdr BABF'!$C7,'BG COMP BABF'!J:J) -> 0 | J7: =IFERROR((H7/F7)^(1/2)-1,"n.a") -> n.a
C8: Achat de marchandises | E8: Achats de marchandises | F8: =-SUMIF('BG COMP BABF'!$A:$A,'Cdr BABF'!$C8,'BG COMP BABF'!H:H) -> -318718059 | G8: =-SUMIF('BG COMP BABF'!A:A,'Cdr BABF'!$C8,'BG COMP BABF'!I:I) -> -169556674 | H8: =-SUMIF('BG COMP BABF'!$A:$A,'Cdr BABF'!$C8,'BG COMP BABF'!J:J) -> -237008805 | J8: =IFERROR((H8/F8)^(1/2)-1,"n.a") -> -0.13765926
C9: Charges de personnel | E9: Charges de personnel | F9: =-SUMIF('BG COMP BABF'!$A:$A,'Cdr BABF'!$C9,'BG COMP BABF'!H:H) -> -50023326 | G9: =-SUMIF('BG COMP BABF'!A:A,'Cdr BABF'!$C9,'BG COMP BABF'!I:I) -> -51573436 | H9: =-SUMIF('BG COMP BABF'!$A:$A,'Cdr BABF'!$C9,'BG COMP BABF'!J:J) -> -57624113 | J9: =IFERROR((H9/F9)^(1/2)-1,"n.a") -> 0.07328694
C10: Transport | E10: Transport | F10: =-SUMIF('BG COMP BABF'!$A:$A,'Cdr BABF'!$C10,'BG COMP BABF'!H:H) -> -10370800 | G10: =-SUMIF('BG COMP BABF'!A:A,'Cdr BABF'!$C10,'BG COMP BABF'!I:I) -> -6357900 | H10: =-SUMIF('BG COMP BABF'!$A:$A,'Cdr BABF'!$C10,'BG COMP BABF'!J:J) -> -6927968 | J10: =IFERROR((H10/F10)^(1/2)-1,"n.a") -> -0.18267119
C11: Sous traitance | E11: Sous traitance | F11: =-SUMIF('BG COMP BABF'!$A:$A,'Cdr BABF'!$C11,'BG COMP BABF'!H:H) -> 0 | G11: =-SUMIF('BG COMP BABF'!A:A,'Cdr BABF'!$C11,'BG COMP BABF'!I:I) -> 0 | H11: =-SUMIF('BG COMP BABF'!$A:$A,'Cdr BABF'!$C11,'BG COMP BABF'!J:J) -> 0 | J11: =IFERROR((H11/F11)^(1/2)-1,"n.a") -> n.a
C12: Charges locatives matières diverses | E12: Charges locatives matières diverses | F12: =-SUMIF('BG COMP BABF'!$A:$A,'Cdr BABF'!$C12,'BG COMP BABF'!H:H) -> -10510880 | G12: =-SUMIF('BG COMP BABF'!A:A,'Cdr BABF'!$C12,'BG COMP BABF'!I:I) -> -8108118 | H12: =-SUMIF('BG COMP BABF'!$A:$A,'Cdr BABF'!$C12,'BG COMP BABF'!J:J) -> -9537615 | J12: =IFERROR((H12/F12)^(1/2)-1,"n.a") -> -0.047422422
C13: Ent. & réparatIon | E13: Ent. & réparatIon | F13: =-SUMIF('BG COMP BABF'!$A:$A,'Cdr BABF'!$C13,'BG COMP BABF'!H:H) -> -1317617 | G13: =-SUMIF('BG COMP BABF'!A:A,'Cdr BABF'!$C13,'BG COMP BABF'!I:I) -> -2594717 | H13: =-SUMIF('BG COMP BABF'!$A:$A,'Cdr BABF'!$C13,'BG COMP BABF'!J:J) -> -2215600 | J13: =IFERROR((H13/F13)^(1/2)-1,"n.a") -> 0.29673455
C14: Assurances | E14: Assurances | F14: =-SUMIF('BG COMP BABF'!$A:$A,'Cdr BABF'!$C14,'BG COMP BABF'!H:H) -> -4173750 | G14: =-SUMIF('BG COMP BABF'!A:A,'Cdr BABF'!$C14,'BG COMP BABF'!I:I) -> -1754988 | H14: =-SUMIF('BG COMP BABF'!$A:$A,'Cdr BABF'!$C14,'BG COMP BABF'!J:J) -> -1276192 | J14: =IFERROR((H14/F14)^(1/2)-1,"n.a") -> -0.44703863
C15: Etudes, recherches et documentation | E15: Etudes, recherches et documentation | F15: =-SUMIF('BG COMP BABF'!$A:$A,'Cdr BABF'!$C15,'BG COMP BABF'!H:H) -> 0 | G15: =-SUMIF('BG COMP BABF'!A:A,'Cdr BABF'!$C15,'BG COMP BABF'!I:I) -> 0 | H15: =-SUMIF('BG COMP BABF'!$A:$A,'Cdr BABF'!$C15,'BG COMP BABF'!J:J) -> -48000 | J15: =IFERROR((H15/F15)^(1/2)-1,"n.a") -> n.a
C16: Publicité et relations publiques | E16: Publicité et relations publiques | F16: =-SUMIF('BG COMP BABF'!$A:$A,'Cdr BABF'!$C16,'BG COMP BABF'!H:H) -> 0 | G16: =-SUMIF('BG COMP BABF'!A:A,'Cdr BABF'!$C16,'BG COMP BABF'!I:I) -> -19000 | H16: =-SUMIF('BG COMP BABF'!$A:$A,'Cdr BABF'!$C16,'BG COMP BABF'!J:J) -> -52016171 | J16: =IFERROR((H16/F16)^(1/2)-1,"n.a") -> n.a
C17: Frais de télécommunication | E17: Frais de télécommunication | F17: =-SUMIF('BG COMP BABF'!$A:$A,'Cdr BABF'!$C17,'BG COMP BABF'!H:H) -> -2708865 | G17: =-SUMIF('BG COMP BABF'!A:A,'Cdr BABF'!$C17,'BG COMP BABF'!I:I) -> -2186056 | H17: =-SUMIF('BG COMP BABF'!$A:$A,'Cdr BABF'!$C17,'BG COMP BABF'!J:J) -> -3414757 | J17: =IFERROR((H17/F17)^(1/2)-1,"n.a") -> 0.12275816
C18: Frais bancaires | E18: Frais bancaires | F18: =-SUMIF('BG COMP BABF'!$A:$A,'Cdr BABF'!$C18,'BG COMP BABF'!H:H) -> -9023514 | G18: =-SUMIF('BG COMP BABF'!A:A,'Cdr BABF'!$C18,'BG COMP BABF'!I:I) -> -13831789 | H18: =-SUMIF('BG COMP BABF'!$A:$A,'Cdr BABF'!$C18,'BG COMP BABF'!J:J) -> -14474043 | J18: =IFERROR((H18/F18)^(1/2)-1,"n.a") -> 0.2665055
... C22: Travaux, matériel et équipement | E22: Travaux, matériel et équipement | F22: =-SUMIF('BG COMP BABF'!$A:$A,'Cdr BABF'!$C22,'BG COMP BABF'!H:H) -> -16452263 | G22: =-SUMIF('BG COMP BABF'!A:A,'Cdr BABF'!$C22,'BG COMP BABF'!I:I) -> -38047837 | H22: =-SUMIF('BG COMP BABF'!$A:$A,'Cdr BABF'!$C22,'BG COMP BABF'!J:J) -> -29006 | J22: =IFERROR((H22/F22)^(1/2)-1,"n.a") -> -0.95801143
E23: Services extérieurs | F23: =SUM(F11:F22) -> -76022421 | G23: =SUM(G11:G22) -> -126668255 | H23: =SUM(H11:H22) -> -193873124 | J23: =IFERROR((H23/F23)^(1/2)-1,"n.a") -> 0.59693764 | M23: =F4*(1+J4) -> 3.2457597e+08
C24: FNS - Electricité | E24: Electricité | F24: =-SUMIF('BG COMP BABF'!$A:$A,'Cdr BABF'!$C24,'BG COMP BABF'!H:H) -> -2489435 | G24: =-SUMIF('BG COMP BABF'!A:A,'Cdr BABF'!$C24,'BG COMP BABF'!I:I) -> -1843333 | H24: =-SUMIF('BG COMP BABF'!$A:$A,'Cdr BABF'!$C24,'BG COMP BABF'!J:J) -> -1362875 | J24: =IFERROR((H24/F24)^(1/2)-1,"n.a") -> -0.26009218
C25: FNS - Autres énergies | E25: Autres énergies | F25: =-SUMIF('BG COMP BABF'!$A:$A,'Cdr BABF'!$C25,'BG COMP BABF'!H:H) -> -4098500 | G25: =-SUMIF('BG COMP BABF'!A:A,'Cdr BABF'!$C25,'BG COMP BABF'!I:I) -> -4121900 | H25: =-SUMIF('BG COMP BABF'!$A:$A,'Cdr BABF'!$C25,'BG COMP BABF'!J:J) -> -4680000 | J25: =IFERROR((H25/F25)^(1/2)-1,"n.a") -> 0.068588403
C26: Achat de produits d'entretien | E26: Achat de produits d'entretien | F26: =-SUMIF('BG COMP BABF'!$A:$A,'Cdr BABF'!$C26,'BG COMP BABF'!H:H) -> -411100 | G26: =-SUMIF('BG COMP BABF'!A:A,'Cdr BABF'!$C26,'BG COMP BABF'!I:I) -> -360813 | H26: =-SUMIF('BG COMP BABF'!$A:$A,'Cdr BABF'!$C26,'BG COMP BABF'!J:J) -> -302625 | J26: =IFERROR((H26/F26)^(1/2)-1,"n.a") -> -0.14201704
C27: Achat de fournitures | E27: Achat de fournitures | F27: =-SUMIF('BG COMP BABF'!$A:$A,'Cdr BABF'!$C27,'BG COMP BABF'!H:H) -> -380225 | G27: =-SUMIF('BG COMP BABF'!A:A,'Cdr BABF'!$C27,'BG COMP BABF'!I:I) -> -433784 | H27: =-SUMIF('BG COMP BABF'!$A:$A,'Cdr BABF'!$C27,'BG COMP BABF'!J:J) -> -3625549 | J27: =IFERROR((H27/F27)^(1/2)-1,"n.a") -> 2.0879237
C28: Achat de petit matériel et outillage | E28: Achat de petit matériel et outillage | F28: =-SUMIF('BG COMP BABF'!$A:$A,'Cdr BABF'!$C28,'BG COMP BABF'!H:H) -> -1052378 | G28: =-SUMIF('BG COMP BABF'!A:A,'Cdr BABF'!$C28,'BG COMP BABF'!I:I) -> -1958236 | H28: =-SUMIF('BG COMP BABF'!$A:$A,'Cdr BABF'!$C28,'BG COMP BABF'!J:J) -> -5319478 | J28: =IFERROR((H28/F28)^(1/2)-1,"n.a") -> 1.2482708
E29: Autres achats et charges externes | F29: =SUM(F24:F28) -> -8431638 | G29: =SUM(G24:G28) -> -8718066 | H29: =SUM(H24:H28) -> -15290527 | J29: =IFERROR((H29/F29)^(1/2)-1,"n.a") -> 0.3466516
C30: Impôts et taxes | E30: Impôts et taxes | F30: =-SUMIF('BG COMP BABF'!$A:$A,'Cdr BABF'!$C30,'BG COMP BABF'!H:H) -> -3876717 | G30: =-SUMIF('BG COMP BABF'!A:A,'Cdr BABF'!$C30,'BG COMP BABF'!I:I) -> -5256287 | H30: =-SUMIF('BG COMP BABF'!$A:$A,'Cdr BABF'!$C30,'BG COMP BABF'!J:J) -> -8721750 | J30: =IFERROR((H30/F30)^(1/2)-1,"n.a") -> 0.49992577
C31: Autres produits | E31: Autres produits | F31: =-SUMIF('BG COMP BABF'!$A:$A,'Cdr BABF'!$C31,'BG COMP BABF'!H:H) -> 1687290 | G31: =-SUMIF('BG COMP BABF'!$A:$A,'Cdr BABF'!$C31,'BG COMP BABF'!I:I) -> 0 | H31: =-SUMIF('BG COMP BABF'!$A:$A,'Cdr BABF'!$C31,'BG COMP BABF'!J:J) -> 13306430 | J31: =IFERROR((H31/F31)^(1/2)-1,"n.a") -> 1.8082509
C32: Autres charges | E32: Autres charges | F32: =-SUMIF('BG COMP BABF'!$A:$A,'Cdr BABF'!$C32,'BG COMP BABF'!H:H) -> -1575953 | G32: =-SUMIF('BG COMP BABF'!A:A,'Cdr BABF'!$C32,'BG COMP BABF'!I:I) -> -99523 | H32: =-SUMIF('BG COMP BABF'!$A:$A,'Cdr BABF'!$C32,'BG COMP BABF'!J:J) -> -3465116 | J32: =IFERROR((H32/F32)^(1/2)-1,"n.a") -> 0.48281598
E33: Autres produits et charges | F33: =-SUMIF('BG COMP BABF'!$A:$A,'Cdr BABF'!$C33,'BG COMP BABF'!H:H) -> 0 | G33: =G31+G32 -> -99523 | H33: =H31+H32 -> 9841314 | J33: =IFERROR((H33/F33)^(1/2)-1,"n.a") -> n.a
E34: Charges d'exploitation | F34: =F33+F30+F29+F23+F10+F9 -> -148724902 | G34: =G33+G30+G29+G23+G10+G9 -> -198673467 | H34: =H33+H30+H29+H23+H10+H9 -> -272596168 | J34: =IFERROR((H34/F34)^(1/2)-1,"n.a") -> 0.35384214
E35: EBITDA | F35: =+SUM(F6,F8,F9,F10,F23,F29,F30,F33) -> 18234384 | G35: =+SUM(G6,G8,G9,G10,G23,G29,G30,G33) -> 17740442 | H35: =+SUM(H6,H8,H9,H10,H23,H29,H30,H33) -> 69774769 | J35: =IFERROR((H35/F35)^(1/2)-1,"n.a") -> 0.95615676 | M35: =(H35-G35)/G35 -> 2.9330908
E36: EBITDA (% CA) | F36: =IFERROR(F35/F$6,"n.a") -> 0.037544234 | G36: =IFERROR(G35/G$6,"n.a") -> 0.045963197 | H36: =IFERROR(H35/H$6,"n.a") -> 0.12043012 | J36: =AVERAGE(F36:H36) -> 0.067979182 | M36: =AVERAGE(F36:H36) -> 0.067979182
C37: Reprises de provisions | E37: Reprises de provisions | F37: =-SUMIF('BG COMP BABF'!$A:$A,'Cdr BABF'!$C37,'BG COMP BABF'!H:H) -> 0 | G37: =-SUMIF('BG COMP BABF'!A:A,'Cdr BABF'!$C37,'BG COMP BABF'!I:I) -> 0 | H37: =-SUMIF('BG COMP BABF'!$A:$A,'Cdr BABF'!$C37,'BG COMP BABF'!J:J) -> 256022 | J37: =IFERROR((H37/F37)^(1/2)-1,"n.a") -> n.a
C38: Dotations aux provisions pour risques et charges | E38: Provisions pour risques et charges | F38: =-SUMIF('BG COMP BABF'!$A:$A,'Cdr BABF'!$C38,'BG COMP BABF'!H:H) -> 0 | G38: =-SUMIF('BG COMP BABF'!A:A,'Cdr BABF'!$C38,'BG COMP BABF'!I:I) -> 0 | H38: =-SUMIF('BG COMP BABF'!$A:$A,'Cdr BABF'!$C38,'BG COMP BABF'!J:J) -> 0 | J38: =IFERROR((H38/F38)^(1/2)-1,"n.a") -> n.a
C39: Dotations aux at | E39: Dotations aux amortissements | F39: =-SUMIF('BG COMP BABF'!$A:$A,'Cdr BABF'!$C39,'BG COMP BABF'!H:H) -> -3531374 | G39: =-SUMIF('BG COMP BABF'!A:A,'Cdr BABF'!$C39,'BG COMP BABF'!I:I) -> -3834084 | H39: =-SUMIF('BG COMP BABF'!$A:$A,'Cdr BABF'!$C39,'BG COMP BABF'!J:J) -> -4925482 | J39: =IFERROR((H39/F39)^(1/2)-1,"n.a") -> 0.18100711
E40: D&A | F40: =SUM(F37:F39) -> -3531374 | G40: =SUM(G37:G39) -> -3834084 | H40: =SUM(H37:H39) -> -4669460 | J40: =IFERROR((H40/F40)^(1/2)-1,"n.a") -> 0.1499037
E41: EBIT | F41: =F35+F40 -> 14703010 | G41: =G35+G40 -> 13906358 | H41: =H35+H40 -> 65105309 | J41: =IFERROR((H41/F41)^(1/2)-1,"n.a") -> 1.1042875
E42: EBIT (% CA) | F42: =IFERROR(F41/F$6,"n.a") -> 0.030273205 | G42: =IFERROR(G41/G$6,"n.a") -> 0.03602958 | H42: =IFERROR(H41/H$6,"n.a") -> 0.1123707 | J42: =AVERAGE(F42:H42) -> 0.05955783
C43: Produits d'intérêts | E43: Produits financiers | F43: =-SUMIF('BG COMP BABF'!$A:$A,'Cdr BABF'!$C43,'BG COMP BABF'!H:H) -> 0 | G43: =-SUMIF('BG COMP BABF'!A:A,'Cdr BABF'!$C43,'BG COMP BABF'!I:I) -> 4313136 | H43: =-SUMIF('BG COMP BABF'!$A:$A,'Cdr BABF'!$C43,'BG COMP BABF'!J:J) -> -883954 | J43: =IFERROR((H43/F43)^(1/2)-1,"n.a") -> n.a
C44: Intérêts sur emprunts | E44: Intérêts sur emprunts | F44: =-SUMIF('BG COMP BABF'!$A:$A,'Cdr BABF'!$C44,'BG COMP BABF'!H:H) -> -7904467 | G44: =-SUMIF('BG COMP BABF'!A:A,'Cdr BABF'!$C44,'BG COMP BABF'!I:I) -> -7637078 | H44: =-SUMIF('BG COMP BABF'!$A:$A,'Cdr BABF'!$C44,'BG COMP BABF'!J:J) -> 0 | J44: =IFERROR((H44/F44)^(1/2)-1,"n.a") -> -1
C45: Intérêts sur dettes de credit bail | E45: Intérêts sur dettes de credit bail | F45: =-SUMIF('BG COMP BABF'!$A:$A,'Cdr BABF'!$C45,'BG COMP BABF'!H:H) -> 0 | G45: =-SUMIF('BG COMP BABF'!A:A,'Cdr BABF'!$C45,'BG COMP BABF'!I:I) -> 0 | H45: =-SUMIF('BG COMP BABF'!$A:$A,'Cdr BABF'!$C45,'BG COMP BABF'!J:J) -> 0 | J45: =IFERROR((H45/F45)^(1/2)-1,"n.a") -> n.a
C46: Autres intérêts | E46: Autres intérêts | F46: =-SUMIF('BG COMP BABF'!$A:$A,'Cdr BABF'!$C46,'BG COMP BABF'!H:H) -> 0 | G46: =-SUMIF('BG COMP BABF'!A:A,'Cdr BABF'!$C46,'BG COMP BABF'!I:I) -> 0 | H46: =-SUMIF('BG COMP BABF'!$A:$A,'Cdr BABF'!$C46,'BG COMP BABF'!J:J) -> 0 | J46: =IFERROR((H46/F46)^(1/2)-1,"n.a") -> n.a
E47: Charges financières | F47: =SUBTOTAL(9,F44:F46) -> -7904467 | G47: =SUBTOTAL(9,G44:G46) -> -7637078 | H47: =SUBTOTAL(9,H44:H46) -> 0 | J47: =IFERROR((H47/F47)^(1/2)-1,"n.a") -> -1
E48: Résultat financier | F48: =SUBTOTAL(9,F43:F47) -> -7904467 | G48: =SUBTOTAL(9,G43:G47) -> -3323942 | H48: =SUBTOTAL(9,H43:H47) -> -883954 | J48: =-IFERROR((H48/F48)^(1/2)-1,"n.a") -> 0.66559055
C49: Resultat exceptionnel | E49: Résultat exceptionnel | F49: =-SUMIF('BG COMP BABF'!$A:$A,'Cdr BABF'!$C49,'BG COMP BABF'!H:H) -> 0 | G49: =-SUMIF('BG COMP BABF'!A:A,'Cdr BABF'!$C49,'BG COMP BABF'!I:I) -> 0 | H49: =-SUMIF('BG COMP BABF'!$A:$A,'Cdr BABF'!$C49,'BG COMP BABF'!J:J) -> -186723487 | J49: =IFERROR((H49/F49)^(1/2)-1,"n.a") -> n.a
C50: IS | E50: IS | F50: =-SUMIF('BG COMP BABF'!$A:$A,'Cdr BABF'!$C50,'BG COMP BABF'!H:H) -> -3378375 | G50: =-SUMIF('BG COMP BABF'!A:A,'Cdr BABF'!$C50,'BG COMP BABF'!I:I) -> -3134450 | H50: =-SUMIF('BG COMP BABF'!$A:$A,'Cdr BABF'!$C50,'BG COMP BABF'!J:J) -> 0 | J50: =IFERROR((H50/F50)^(1/2)-1,"n.a") -> -1
E51: Résultat net | F51: =F41+F48+F49+F50 -> 3420168 | G51: =G41+G48+G49+G50 -> 7447966 | H51: =H41+H48+H49+H50 -> -122502132 | J51: =IFERROR(((H51/F51)^(1/2))-1,"n.a") -> n.a
E52: Source : Données Management, Analyse Forvis Mazars

Sheet Bilan BABF
D6: Projet BOX AFRICA - Actif net BABF
B7: Mapping | D7: En mFCFA | E7: FY22 | F7: FY23 | G7: FY24 | H7: FY25
B8: Ouvrages d'infrastructure | D8: Ouvrages d'infrastructure | F8: =(((-SUMIF('BG COMP BABF'!$A:$A,$B8,'BG COMP BABF'!H:H)))/1000000)*-1 -> -1.958114 | G8: =(((-SUMIF('BG COMP BABF'!$A:$A,$B8,'BG COMP BABF'!I:I)))/1000000)*-1 -> -2.774614 | H8: =(((-SUMIF('BG COMP BABF'!$A:$A,$B8,'BG COMP BABF'!J:J)))/1000000)*-1 -> -3.591114
B9: Matériel et outillage | D9: Matériel et outillage | F9: =(((-SUMIF('BG COMP BABF'!$A:$A,$B9,'BG COMP BABF'!H:H)))/1000000)*-1 -> 0 | G9: =(((-SUMIF('BG COMP BABF'!$A:$A,$B9,'BG COMP BABF'!I:I)))/1000000)*-1 -> 0 | H9: =(((-SUMIF('BG COMP BABF'!$A:$A,$B9,'BG COMP BABF'!J:J)))/1000000)*-1 -> 0
B10: Matériel de bureau | D10: Matériel de bureau | F10: =(((-SUMIF('BG COMP BABF'!$A:$A,$B10,'BG COMP BABF'!H:H)))/1000000)*-1 -> 0 | G10: =(((-SUMIF('BG COMP BABF'!$A:$A,$B10,'BG COMP BABF'!I:I)))/1000000)*-1 -> 0 | H10: =(((-SUMIF('BG COMP BABF'!$A:$A,$B10,'BG COMP BABF'!J:J)))/1000000)*-1 -> 0
B11: Aménagements de bureau | D11: Aménagements de bureau | F11: =(((-SUMIF('BG COMP BABF'!$A:$A,$B11,'BG COMP BABF'!H:H)))/1000000)*-1 -> 4.0825 | G11: =(((-SUMIF('BG COMP BABF'!$A:$A,$B11,'BG COMP BABF'!I:I)))/1000000)*-1 -> 4.0825 | H11: =(((-SUMIF('BG COMP BABF'!$A:$A,$B11,'BG COMP BABF'!J:J)))/1000000)*-1 -> 4.0825
B12: Matériel informatique | D12: Matériel informatique | F12: =(((-SUMIF('BG COMP BABF'!$A:$A,$B12,'BG COMP BABF'!H:H)))/1000000)*-1 -> 2.12848 | G12: =(((-SUMIF('BG COMP BABF'!$A:$A,$B12,'BG COMP BABF'!I:I)))/1000000)*-1 -> 2.20848 | H12: =(((-SUMIF('BG COMP BABF'!$A:$A,$B12,'BG COMP BABF'!J:J)))/1000000)*-1 -> 7.54293
B13: Matériel et mobilier de bureau | D13: Matériel et mobilier de bureau | F13: =(((-SUMIF('BG COMP BABF'!$A:$A,$B13,'BG COMP BABF'!H:H)))/1000000)*-1 -> 2.047227 | G13: =(((-SUMIF('BG COMP BABF'!$A:$A,$B13,'BG COMP BABF'!I:I)))/1000000)*-1 -> 1.552517 | H13: =(((-SUMIF('BG COMP BABF'!$A:$A,$B13,'BG COMP BABF'!J:J)))/1000000)*-1 -> -3.017904
B14: Mat. & mob. des logements du pers. | D14: Mat. & mob. des logements du pers. | F14: =(((-SUMIF('BG COMP BABF'!$A:$A,$B14,'BG COMP BABF'!H:H)))/1000000)*-1 -> 0 | G14: =(((-SUMIF('BG COMP BABF'!$A:$A,$B14,'BG COMP BABF'!I:I)))/1000000)*-1 -> 0 | H14: =(((-SUMIF('BG COMP BABF'!$A:$A,$B14,'BG COMP BABF'!J:J)))/1000000)*-1 -> 0
B15: Matériel de transport | D15: Matériel de transport | F15: =(((-SUMIF('BG COMP BABF'!$A:$A,$B15,'BG COMP BABF'!H:H)))/1000000)*-1 -> 7.865498 | G15: =(((-SUMIF('BG COMP BABF'!$A:$A,$B15,'BG COMP BABF'!I:I)))/1000000)*-1 -> 6.201743 | H15: =(((-SUMIF('BG COMP BABF'!$A:$A,$B15,'BG COMP BABF'!J:J)))/1000000)*-1 -> 9.960051
B16: Avances et acomptes | D16: Avances et acomptes | F16: =(((-SUMIF('BG COMP BABF'!$A:$A,$B16,'BG COMP BABF'!H:H)))/1000000)*-1 -> 0 | G16: =(((-SUMIF('BG COMP BABF'!$A:$A,$B16,'BG COMP BABF'!I:I)))/1000000)*-1 -> 0 | H16: =(((-SUMIF('BG COMP BABF'!$A:$A,$B16,'BG COMP BABF'!J:J)))/1000000)*-1 -> 0
D17: Immobilisations corporelles | F17: =SUM(F8:F16) -> 14.165591 | G17: =SUM(G8:G16) -> 11.270626 | H17: =SUM(H8:H16) -> 14.976463
B18: Dépots et cautionnements | D18: Dépots et cautionnements | F18: =(((-SUMIF('BG COMP BABF'!$A:$A,$B18,'BG COMP BABF'!H:H)))/1000000)*-1 -> 0 | G18: =(((-SUMIF('BG COMP BABF'!$A:$A,$B18,'BG COMP BABF'!I:I)))/1000000)*-1 -> 0 | H18: =(((-SUMIF('BG COMP BABF'!$A:$A,$B18,'BG COMP BABF'!J:J)))/1000000)*-1 -> 1.86558
D19: Immobilisations financières | F19: =SUM(F18) -> 0 | G19: =SUM(G18) -> 0 | H19: =SUM(H18) -> 1.86558
B20: Immobilisations en cours | D20: Immobilisations en cours | F20: =(((-SUMIF('BG COMP BABF'!$A:$A,$B20,'BG COMP BABF'!H:H)))/1000000)*-1 -> 123.49674 | G20: =(((-SUMIF('BG COMP BABF'!$A:$A,$B20,'BG COMP BABF'!I:I)))/1000000)*-1 -> 73.074271 | H20: =(((-SUMIF('BG COMP BABF'!$A:$A,$B20,'BG COMP BABF'!J:J)))/1000000)*-1 -> 0
D21: Actifs immobilisés | F21: =SUM(F19:F20,F17) -> 137.66233 | G21: =SUM(G19:G20,G17) -> 84.344897 | H21: =SUM(H19:H20,H17) -> 16.842043
B22: Clients | D22: Créances clients | F22: =(((-SUMIF('BG COMP BABF'!$A:$A,$B22,'BG COMP BABF'!H:H)))/1000000)*-1 -> 10.690842 | G22: =(((-SUMIF('BG COMP BABF'!$A:$A,$B22,'BG COMP BABF'!I:I)))/1000000)*-1 -> 80.194076 | H22: =(((-SUMIF('BG COMP BABF'!$A:$A,$B22,'BG COMP BABF'!J:J)))/1000000)*-1 -> 203.83622
B23: Clients, créditeurs | D23: Acomptes clients | F23: =(((-SUMIF('BG COMP BABF'!$A:$A,$B23,'BG COMP BABF'!H:H)))/1000000)*-1 -> 0 | G23: =(((-SUMIF('BG COMP BABF'!$A:$A,$B23,'BG COMP BABF'!I:I)))/1000000)*-1 -> 0 | H23: =(((-SUMIF('BG COMP BABF'!$A:$A,$B23,'BG COMP BABF'!J:J)))/1000000)*-1 -> 0
D24: Créances clients | F24: =SUM(F22:F23) -> 10.690842 | G24: =SUM(G22:G23) -> 80.194076 | H24: =SUM(H22:H23) -> 203.83622
B25: Fournisseurs | D25: Dettes fournisseurs | F25: =(((-SUMIF('BG COMP BABF'!$A:$A,$B25,'BG COMP BABF'!H:H)))/1000000)*-1 -> -47.847901 | G25: =(((-SUMIF('BG COMP BABF'!$A:$A,$B25,'BG COMP BABF'!I:I)))/1000000)*-1 -> -49.43267 | H25: =(((-SUMIF('BG COMP BABF'!$A:$A,$B25,'BG COMP BABF'!J:J)))/1000000)*-1 -> -60.124212
B26: Fournisseurs, débiteurs | D26: Acomptes aux fournisseurs | F26: =(((-SUMIF('BG COMP BABF'!$A:$A,$B26,'BG COMP BABF'!H:H)))/1000000)*-1 -> 0 | G26: =(((-SUMIF('BG COMP BABF'!$A:$A,$B26,'BG COMP BABF'!I:I)))/1000000)*-1 -> 0 | H26: =(((-SUMIF('BG COMP BABF'!$A:$A,$B26,'BG COMP BABF'!J:J)))/1000000)*-1 -> 1.0875
D27: Dettes fournisseurs | F27: =SUM(F25:F26) -> -47.847901 | G27: =SUM(G25:G26) -> -49.43267 | H27: =SUM(H25:H26) -> -59.036712
B28: Personnel | D28: Personnel | F28: =(((-SUMIF('BG COMP BABF'!$A:$A,$B28,'BG COMP BABF'!H:H)))/1000000)*-1 -> 3.180432 | G28: =(((-SUMIF('BG COMP BABF'!$A:$A,$B28,'BG COMP BABF'!I:I)))/1000000)*-1 -> 0.012432 | H28: =(((-SUMIF('BG COMP BABF'!$A:$A,$B28,'BG COMP BABF'!J:J)))/1000000)*-1 -> 0
B29: Charges_sociales | D29: Charges sociales | F29: =(((-SUMIF('BG COMP BABF'!$A:$A,$B29,'BG COMP BABF'!H:H)))/1000000)*-1 -> -5.36566 | G29: =(((-SUMIF('BG COMP BABF'!$A:$A,$B29,'BG COMP BABF'!I:I)))/1000000)*-1 -> -9.937768 | H29: =(((-SUMIF('BG COMP BABF'!$A:$A,$B29,'BG COMP BABF'!J:J)))/1000000)*-1 -> -15.642411
D30: Dettes et créances sociales | F30: =SUM(F28:F29) -> -2.185228 | G30: =SUM(G28:G29) -> -9.925336 | H30: =SUM(H28:H29) -> -15.642411
B31: Etat, TVA et taxes | D31: Etat, TVA et taxes | F31: =(((-SUMIF('BG COMP BABF'!$A:$A,$B31,'BG COMP BABF'!H:H)))/1000000)*-1 -> -134.01262 | G31: =(((-SUMIF('BG COMP BABF'!$A:$A,$B31,'BG COMP BABF'!I:I)))/1000000)*-1 -> -171.56861 | H31: =(((-SUMIF('BG COMP BABF'!$A:$A,$B31,'BG COMP BABF'!J:J)))/1000000)*-1 -> -240.65371
D32: Dettes et créances fiscales | F32: =F31 -> -134.01262 | G32: =G31 -> -171.56861 | H32: =H31 -> -240.65371
B33: Débiteurs et créditeurs divers | D33: Débiteurs et créditeurs divers | F33: =(((-SUMIF('BG COMP BABF'!$A:$A,$B33,'BG COMP BABF'!H:H)))/1000000)*-1 -> -78.344233 | G33: =(((-SUMIF('BG COMP BABF'!$A:$A,$B33,'BG COMP BABF'!I:I)))/1000000)*-1 -> -24.717581 | H33: =(((-SUMIF('BG COMP BABF'!$A:$A,$B33,'BG COMP BABF'!J:J)))/1000000)*-1 -> -45.558339
B34: Groupe, compte courant | D34: Groupe, compte courant | F34: =(((-SUMIF('BG COMP BABF'!$A:$A,$B34,'BG COMP BABF'!H:H)))/1000000)*-1 -> 0 | G34: =(((-SUMIF('BG COMP BABF'!$A:$A,$B34,'BG COMP BABF'!I:I)))/1000000)*-1 -> 0 | H34: =(((-SUMIF('BG COMP BABF'!$A:$A,$B34,'BG COMP BABF'!J:J)))/1000000)*-1 -> 0
B35: Dépréciations | D35: Dépréciations | F35: =(((-SUMIF('BG COMP BABF'!$A:$A,$B35,'BG COMP BABF'!H:H)))/1000000)*-1 -> 0 | G35: =(((-SUMIF('BG COMP BABF'!$A:$A,$B35,'BG COMP BABF'!I:I)))/1000000)*-1 -> 0 | H35: =(((-SUMIF('BG COMP BABF'!$A:$A,$B35,'BG COMP BABF'!J:J)))/1000000)*-1 -> 0
D36: Autres créances et dettes | F36: =SUM(F33:F35) -> -78.344233 | G36: =SUM(G33:G35) -> -24.717581 | H36: =SUM(H33:H35) -> -45.558339
D37: BFR | F37: =F36+F32+F30+F27+F24 -> -251.69914 | G37: =G36+G32+G30+G27+G24 -> -175.45012 | H37: =H36+H32+H30+H27+H24 -> -157.05496
B38: Banque | D38: Banque | F38: =(((-SUMIF('BG COMP BABF'!$A:$A,$B38,'BG COMP BABF'!H:H)))/1000000)*-1 -> 125.38724 | G38: =(((-SUMIF('BG COMP BABF'!$A:$A,$B38,'BG COMP BABF'!I:I)))/1000000)*-1 -> 164.23045 | H38: =(((-SUMIF('BG COMP BABF'!$A:$A,$B38,'BG COMP BABF'!J:J)))/1000000)*-1 -> 95.547542
B39: Crédit de trésorerie | D39: Crédit de trésorerie | F39: =(((-SUMIF('BG COMP BABF'!$A:$A,$B39,'BG COMP BABF'!H:H)))/1000000)*-1 -> 0.388579 | G39: =(((-SUMIF('BG COMP BABF'!$A:$A,$B39,'BG COMP BABF'!I:I)))/1000000)*-1 -> -53.298016 | H39: =(((-SUMIF('BG COMP BABF'!$A:$A,$B39,'BG COMP BABF'!J:J)))/1000000)*-1 -> -61.653068
B40: Caisse | D40: Caisse | F40: =(((-SUMIF('BG COMP BABF'!$A:$A,$B40,'BG COMP BABF'!H:H)))/1000000)*-1 -> 2.534162 | G40: =(((-SUMIF('BG COMP BABF'!$A:$A,$B40,'BG COMP BABF'!I:I)))/1000000)*-1 -> 1.823302 | H40: =(((-SUMIF('BG COMP BABF'!$A:$A,$B40,'BG COMP BABF'!J:J)))/1000000)*-1 -> 5.317857
B41: Virement de fonds | D41: Virement de fonds | F41: =(((-SUMIF('BG COMP BABF'!$A:$A,$B41,'BG COMP BABF'!H:H)))/1000000)*-1 -> 0 | G41: =(((-SUMIF('BG COMP BABF'!$A:$A,$B41,'BG COMP BABF'!I:I)))/1000000)*-1 -> 0 | H41: =(((-SUMIF('BG COMP BABF'!$A:$A,$B41,'BG COMP BABF'!J:J)))/1000000)*-1 -> 0
D42: Trésorerie et équivalents de trésorerie | F42: =SUM(F38:F41) -> 128.30998 | G42: =SUM(G38:G41) -> 112.75573 | H42: =SUM(H38:H41) -> 39.212331
B43: Emprunt | D43: Emprunt bancaire | F43: =(((-SUMIF('BG COMP BABF'!$A:$A,$B43,'BG COMP BABF'!H:H)))/1000000)*-1 -> 0 | G43: =(((-SUMIF('BG COMP BABF'!$A:$A,$B43,'BG COMP BABF'!I:I)))/1000000)*-1 -> 0 | H43: =(((-SUMIF('BG COMP BABF'!$A:$A,$B43,'BG COMP BABF'!J:J)))/1000000)*-1 -> 0
B44: Dette sur crédit bail | D44: Dette sur crédit bail | F44: =(((-SUMIF('BG COMP BABF'!$A:$A,$B44,'BG COMP BABF'!H:H)))/1000000)*-1 -> 0 | G44: =(((-SUMIF('BG COMP BABF'!$A:$A,$B44,'BG COMP BABF'!I:I)))/1000000)*-1 -> 0 | H44: =(((-SUMIF('BG COMP BABF'!$A:$A,$B44,'BG COMP BABF'!J:J)))/1000000)*-1 -> 0
D45: Dettes financières | F45: =SUM(F43:F44) -> 0 | G45: =SUM(G43:G44) -> 0 | H45: =SUM(H43:H44) -> 0
B46: Provisions pour risques et charges | D46: Provisions pour risques et charges | F46: =(((-SUMIF('BG COMP BABF'!$A:$A,$B46,'BG COMP BABF'!H:H)))/1000000)*-1 -> 0 | G46: =(((-SUMIF('BG COMP BABF'!$A:$A,$B46,'BG COMP BABF'!I:I)))/1000000)*-1 -> 0 | H46: =(((-SUMIF('BG COMP BABF'!$A:$A,$B46,'BG COMP BABF'!J:J)))/1000000)*-1 -> 0
D47: Trésorerie / (dette) nette | F47: =F46+F45+F42 -> 128.30998 | G47: =G46+G45+G42 -> 112.75573 | H47: =H46+H45+H42 -> 39.212331
B48: provisions pour risques à court terme | D48: provisions pour risques à court terme | F48: =(((-SUMIF('BG COMP BABF'!$A:$A,$B48,'BG COMP BABF'!H:H)))/1000000)*-1 -> 0 | G48: =(((-SUMIF('BG COMP BABF'!$A:$A,$B48,'BG COMP BABF'!I:I)))/1000000)*-1 -> 0 | H48: =(((-SUMIF('BG COMP BABF'!$A:$A,$B48,'BG COMP BABF'!J:J)))/1000000)*-1 -> 0
D49: Provisions | F49: =F48 -> 0 | G49: =G48 -> 0 | H49: =H48 -> 0
D50: Actif net | F50: =F47+F49+F37+F21 -> 14.273169 | G50: =G47+G49+G37+G21 -> 21.650505 | H50: =H47+H49+H37+H21 -> -101.00059
F51: =(((-SUMIF('BG COMP BABF'!$A:$A,$B51,'BG COMP BABF'!H:H)))/1000000)*-1 -> 0 | G51: =(((-SUMIF('BG COMP BABF'!$A:$A,$B51,'BG COMP BABF'!I:I)))/1000000)*-1 -> 0 | H51: =(((-SUMIF('BG COMP BABF'!$A:$A,$B51,'BG COMP BABF'!J:J)))/1000000)*-1 -> 0
B52: Capital | D52: Capital | F52: =-(((-SUMIF('BG COMP BABF'!$A:$A,$B52,'BG COMP BABF'!H:H)))/1000000)*-1 -> 10 | G52: =-(((-SUMIF('BG COMP BABF'!$A:$A,$B52,'BG COMP BABF'!I:I)))/1000000)*-1 -> 10 | H52: =-(((-SUMIF('BG COMP BABF'!$A:$A,$B52,'BG COMP BABF'!J:J)))/1000000)*-1 -> 10
B53: Reserve légale | D53: Reserve légale | F53: =-(((-SUMIF('BG COMP BABF'!$A:$A,$B53,'BG COMP BABF'!H:H)))/1000000)*-1 -> 0 | G53: =-(((-SUMIF('BG COMP BABF'!$A:$A,$B53,'BG COMP BABF'!I:I)))/1000000)*-1 -> 0.353151 | H53: =-(((-SUMIF('BG COMP BABF'!$A:$A,$B53,'BG COMP BABF'!J:J)))/1000000)*-1 -> 1.097948
B54: Reserve diverses | D54: Reserve diverses | F54: =(((-SUMIF('BG COMP BABF'!$A:$A,$B54,'BG COMP BABF'!H:H)))/1000000)*-1 -> 0 | G54: =(((-SUMIF('BG COMP BABF'!$A:$A,$B54,'BG COMP BABF'!I:I)))/1000000)*-1 -> 0 | H54: =(((-SUMIF('BG COMP BABF'!$A:$A,$B54,'BG COMP BABF'!J:J)))/1000000)*-1 -> 0
B55: Report a nouveau | D55: Report a nouveau | F55: =-(((-SUMIF('BG COMP BABF'!$A:$A,$B55,'BG COMP BABF'!H:H)))/1000000)*-1 -> 0.741664 | G55: =-(((-SUMIF('BG COMP BABF'!$A:$A,$B55,'BG COMP BABF'!I:I)))/1000000)*-1 -> 3.849388 | H55: =-(((-SUMIF('BG COMP BABF'!$A:$A,$B55,'BG COMP BABF'!J:J)))/1000000)*-1 -> 10.403598
B56: RIA | D56: RIA | F56: =(((-SUMIF('BG COMP BABF'!$A:$A,$B56,'BG COMP BABF'!H:H)))/1000000)*-1 -> 0 | G56: =(((-SUMIF('BG COMP BABF'!$A:$A,$B56,'BG COMP BABF'!I:I)))/1000000)*-1 -> 0 | H56: =(((-SUMIF('BG COMP BABF'!$A:$A,$B56,'BG COMP BABF'!J:J)))/1000000)*-1 -> 0
D57: Résultat net | F57: ='Cdr BABF'!F51/1000000 -> 3.420168 | G57: ='Cdr BABF'!G51/1000000 -> 7.447966 | H57: ='Cdr BABF'!H51/1000000 -> -122.50213
F58: =(((-SUMIF('BG COMP BABF'!$A:$A,$B58,'BG COMP BABF'!H:H)))/1000000)*-1 -> 0 | G58: =(((-SUMIF('BG COMP BABF'!$A:$A,$B58,'BG COMP BABF'!I:I)))/1000000)*-1 -> 0 | H58: =(((-SUMIF('BG COMP BABF'!$A:$A,$B58,'BG COMP BABF'!J:J)))/1000000)*-1 -> 0
D59: Capitaux propres | F59: =SUM(F52:F57) -> 14.161832 | G59: =SUM(G52:G57) -> 21.650505 | H59: =SUM(H52:H57) -> -101.00059
D64: Source : Balances générales
D66: Check équilibre | H66: =H50-H59 -> 0

Sheet UPSLIDE_UndoFormatting
A1: 66 | B1: 25

Sheet UPSLIDE_Undo
A1: 83 | B1: 25
